Workbook

Sheet Előlap
A1: PR-10-43-03 | B1: Key machine output follow
A3: Folyamatgazda: | B3: Termelési csoport
A5: Folyamat | B5: R | C5: A | D5: C | E5: I | H5: A szabályzattal kapcsolatos személyek
A6: Management | C6: X | E6: X | H6: Készítette | I6: Borics Krisztián
A7: Quality | D7: X | E7: X | H7: Ellenőrizte | I7: László Tamás
A8: Production | B8: X | D8: X | E8: X | H8: Jóváhagyta és elrendelte | I8: Chiaki Hashiba
A9: Logistics | D9: X | E9: X | H9: Hatálybalépés dátuma | I9: 43116
A10: Sales | E10: X | H10: Változások
A11: Project Management | E11: X | H11: =I9 -> 43116 | I11: Első kiadás
A12: Human resources | D12: X | E12: X | H12: 43628 | I12: Kiegészítés : Üzemi kimentet időarányos követése, Átcsomagolós anyagok időarányos követése, Action Plan bevezetése.
A13: Engineering Support | E13: X

Sheet COIL inkjet_Laci
B1: QTY | C1: SH
A2: 1200-1347 | B2: 1 | C2: 1.26 | D2: =C2*B2 -> 1.26
A3: 1200-1368 | B3: 15 | C3: =1.05*3 -> 3.15 | D3: =C3*B3 -> 47.25
A4: 1201-1221 | B4: 31 | C4: 1.67 | D4: =C4*B4 -> 51.77
A5: 2000-0722 | B5: 0.326 | C5: 2.33 | D5: =C5*B5 -> 0.75958
A6: SZUM | D6: =SUM(D2:D5) -> 101.03958
D7: =2*17*8 -> 272 | E7: =D6/D7 -> 0.37146904

Sheet Headcount
A1: Head | F1: AVG Difference to the plan
A2: Count
B7: Workday | F7: 15 | Q7: Adott napi könyvelt üzemidő, USB, Visual, ContiVisual, Pack nélkül.
B8: Actual day | F8: 15 | L8: Állandó
A9: Day | B9: Netto HC plan | C9: Nettó létszámterv (kumulált) / Netto HC plan (cum) | D9: Brutto HC plan | E9: Other Work (PL. Support tape cleaning, Packaging) | F9: Daily Actual HC | G9: FFC Indirect | H9: QA Indirect | I9: FFC direct+indirect | J9: Aktuális Létszám (kumulatív) / Actual HC (cum) | K9: Daily Actual HC AVG | L9: Daily HC plan AVG | M9: Holiday | N9: Sick leave | O9: Difference | P9: Available Working hour (AWH) | Q9: Generate standard hour (GSH) Actual WK from BC) wihout packaging, conti, visual, usb (manual inspection csoport)
A10: 2 | B10: 20 | C10: =B10 -> 20 | D10: =B10*1.13 -> 22.6 | E10: 0 | F10: 17 | G10: 6 | H10: 5 | I10: =F10+G10 -> 23 | J10: =F10 -> 17 | K10: =J10 -> 17 | L10: 20 | M10: 0 | N10: 6 | O10: =IF(F10+E10="",0,F10-B10) -> -3 | P10: =B10*7.33 -> 146.6 | Q10: 149.56 | R10: =Q10/P10 -> 1.020191 | S10: =B10/F10 -> 1.1764706
A11: 3 | B11: 20 | C11: =C10+B11 -> 40 | D11: =B11*1.13 -> 22.6 | E11: 0 | F11: 16 | G11: 6 | H11: 5 | I11: =F11+G11 -> 22 | J11: =J10+F11 -> 33 | K11: =F11 -> 16 | L11: 20 | M11: 1 | N11: 6 | O11: =IF(F11+E11="",0,F11-B11) -> -4 | P11: =B11*7.33 -> 146.6 | Q11: 145.13 | R11: =Q11/P11 -> 0.98997271 | S11: =B11/F11 -> 1.25
A12: 4 | B12: 22 | C12: =C11+B12 -> 62 | D12: =B12*1.13 -> 24.86 | E12: 0 | F12: 17 | G12: 6 | H12: 5 | I12: =F12+G12 -> 23 | J12: =J11+F12 -> 50 | K12: =(K11+F12)/2 -> 16.5 | L12: 20 | M12: 0 | N12: 6 | O12: =IF(F12+E12="",0,F12-B12) -> -5 | P12: =B12*7.33 -> 161.26 | Q12: 158.49 | R12: =Q12/P12 -> 0.98282277 | S12: =B12/F12 -> 1.2941176
A13: 5 | B13: 22 | C13: =C12+B13 -> 84 | D13: =B13*1.13 -> 24.86 | E13: 0 | F13: 17 | G13: 6 | H13: 5 | I13: =F13+G13 -> 23 | J13: =J12+F13 -> 67 | K13: =(K12+F13)/2 -> 16.75 | L13: 20 | M13: 1 | N13: 5 | O13: =IF(F13+E13="",0,F13-B13) -> -5 | P13: =B13*7.33 -> 161.26 | Q13: 160.66 | R13: =Q13/P13 -> 0.9962793 | S13: =B13/F13 -> 1.2941176
A14: 6 | B14: 22 | C14: =C13+B14 -> 106 | D14: =B14*1.13 -> 24.86 | E14: 0 | F14: 15 | G14: 6 | H14: 6 | I14: =F14+G14 -> 21 | J14: =J13+F14 -> 82 | K14: =(K13+F14)/2 -> 15.875 | L14: 20 | M14: 2 | N14: 6 | O14: =IF(F14+E14="",0,F14-B14) -> -7 | P14: =B14*7.33 -> 161.26 | Q14: 150.16 | R14: =Q14/P14 -> 0.93116706 | S14: =B14/F14 -> 1.4666667
A15: 9 | B15: 23 | C15: =C14+B15 -> 129 | D15: =B15*1.13 -> 25.99 | E15: 0 | F15: 19 | G15: 6 | H15: 6 | I15: =F15+G15 -> 25 | J15: =J14+F15 -> 101 | K15: =(K14+F15)/2 -> 17.4375 | L15: 20 | M15: 0 | N15: 4 | O15: =IF(F15+E15="",0,F15-B15) -> -4 | P15: =B15*6 -> 138 | Q15: 170.92 | R15: =Q15/P15 -> 1.2385507 | S15: =B15/F15 -> 1.2105263
A16: 10 | B16: 22 | C16: =C15+B16 -> 151 | D16: =B16*1.13 -> 24.86 | E16: 0 | F16: 19 | G16: 6 | H16: 6 | I16: =F16+G16 -> 25 | J16: =J15+F16 -> 120 | K16: =(K15+F16)/2 -> 18.21875 | L16: 20 | M16: 0 | N16: 4 | O16: =IF(F16+E16="",0,F16-B16) -> -3 | P16: =B16*7.33 -> 161.26 | Q16: 177.26 | R16: =Q16/P16 -> 1.0992187 | S16: =B16/F16 -> 1.1578947
A17: 11 | B17: 23 | C17: =C16+B17 -> 174 | D17: =B17*1.13 -> 25.99 | E17: 0 | F17: 18 | G17: 6 | H17: 9 | I17: =F17+G17 -> 24 | J17: =J16+F17 -> 138 | K17: =(K16+F17)/2 -> 18.109375 | L17: 20 | M17: 1 | N17: 4 | O17: =IF(F17+E17="",0,F17-B17) -> -5 | P17: =B17*7.33 -> 168.59 | Q17: 157.46 | R17: =Q17/P17 -> 0.93398185 | S17: =B17/F17 -> 1.2777778
A18: 12 | B18: 24 | C18: =C17+B18 -> 198 | D18: =B18*1.13 -> 27.12 | E18: 0 | F18: 19 | G18: 6 | H18: 9 | I18: =F18+G18 -> 25 | J18: =J17+F18 -> 157 | K18: =(K17+F18)/2 -> 18.554688 | L18: 20 | M18: 0 | N18: 3 | O18: =IF(F18+E18="",0,F18-B18) -> -5 | P18: =B18*7.33 -> 175.92 | Q18: 149.98 | R18: =Q18/P18 -> 0.85254661 | S18: =B18/F18 -> 1.2631579
A19: 13 | B19: 23 | C19: =C18+B19 -> 221 | D19: =B19*1.13 -> 25.99 | E19: 0 | F19: 11 | G19: 5 | H19: 16 | I19: =F19+G19 -> 16 | J19: =J18+F19 -> 168 | K19: =(K18+F19)/2 -> 14.777344 | L19: 20 | M19: 1 | N19: 3 | O19: =IF(F19+E19="",0,F19-B19) -> -12 | P19: =B19*7.33 -> 168.59 | Q19: 115.46 | R19: =Q19/P19 -> 0.68485675 | S19: =B19/F19 -> 2.0909091
A20: 16 | B20: 20 | C20: =C19+B20 -> 241 | D20: =B20*1.13 -> 22.6 | E20: 0 | F20: 11 | G20: 6 | H20: 16 | I20: =F20+G20 -> 17 | J20: =J19+F20 -> 179 | K20: =(K19+F20)/2 -> 12.888672 | L20: 20 | M20: 0 | N20: 4 | O20: =IF(F20+E20="",0,F20-B20) -> -9 | P20: =B20*7.33 -> 146.6 | Q20: 106.49 | R20: =Q20/P20 -> 0.72639836 | S20: =B20/F20 -> 1.8181818
A21: 17 | B21: 21 | C21: =C20+B21 -> 262 | D21: =B21*1.13 -> 23.73 | E21: 0 | F21: 11 | G21: 6 | H21: 16 | I21: =F21+G21 -> 17 | J21: =J20+F21 -> 190 | K21: =(K20+F21)/2 -> 11.944336 | L21: 20 | M21: 0 | N21: 4 | O21: =IF(F21+E21="",0,F21-B21) -> -10 | P21: =B21*7.33 -> 153.93 | Q21: 106.26 | R21: =Q21/P21 -> 0.69031378 | S21: =B21/F21 -> 1.9090909
A22: 18 | B22: 16 | C22: =C21+B22 -> 278 | D22: =B22*1.13 -> 18.08 | E22: 0 | F22: 11 | G22: 6 | H22: 16 | I22: =F22+G22 -> 17 | J22: =J21+F22 -> 201 | K22: =(K21+F22)/2 -> 11.472168 | L22: 20 | M22: 0 | N22: 4 | O22: =IF(F22+E22="",0,F22-B22) -> -5 | P22: =B22*7.33 -> 117.28 | Q22: 97.42 | R22: =Q22/P22 -> 0.83066166 | S22: =B22/F22 -> 1.4545455
A23: 19 | B23: 17 | C23: =C22+B23 -> 295 | D23: =B23*1.13 -> 19.21 | E23: 0 | F23: 11 | G23: 6 | H23: 15 | I23: =F23+G23 -> 17 | J23: =J22+F23 -> 212 | K23: =(K22+F23)/2 -> 11.236084 | L23: 20 | M23: 0 | N23: 4 | O23: =IF(F23+E23="",0,F23-B23) -> -6 | P23: =B23*7.33 -> 124.61 | Q23: 93.51 | R23: =Q23/P23 -> 0.75042131 | S23: =B23/F23 -> 1.5454545
A24: 20 | B24: 13 | C24: =C23+B24 -> 308 | D24: =B24*1.13 -> 14.69 | E24: 0 | F24: 11 | G24: 6 | H24: 9 | I24: =F24+G24 -> 17 | J24: =J23+F24 -> 223 | K24: =(K23+F24)/2 -> 11.118042 | L24: 20 | M24: 3 | N24: 4 | O24: =IF(F24+E24="",0,F24-B24) -> -2 | P24: =B24*7.33 -> 95.29 | Q24: 80.98 | R24: =Q24/P24 -> 0.84982684 | S24: =B24/F24 -> 1.1818182

Sheet Munka1
K3: BC-ből
D4: 202506 | K4: Gépcsoportlista
E5: Létszám | K5: Termelési terv
E6: Gépek | K6: Létszámterv, de melyik???
E7: Kézi
E8: …
E9: Szum
D10: Metaadatok | E10: Munkanapok
E11: Műszakszám (Kézi, Gépi)
E12: Műszakhossz gépi
E13: Műszakhossz kézi
E14: Absense ratio
E15: Kezdő dátum
E16: Bef. Dátum
E17: Desc.

Sheet ADAMI
A1: ADAMI | D1: Difference to the plan | H1: =F27-D27 -> 14
D3: Mennyiség/ Quantity | E3: Óra/ Hours | F3: Gépszám | P3: Munka3
F4: 2 | L4: =C9/3200*8 -> 22.5
B5: Napi Terv / Daily plan | D5: 600 | E5: =D5/(3000*F4/8) -> 0.8 | F5: =E23/D23 -> 1.0015556 | L5: =2*D6*8 -> 240 | M5: =L4/L5 -> 0.09375
C6: Workdays | D6: =Headcount!F7 -> 15
C7: Actual day | D7: =Headcount!F8 -> 15 | F7: Out put daily good | J7: Reject
A8: Munkanap / Workdays | B8: Napi terv / Daily plan | C8: Hátralévő mennyiség | D8: Kumulált terv / Cumulative plan | E8: Kimenet (Kumulált) / Output (cumulative) | F8: Teljes kimenet / Total output | G8: Shift 1 | H8: Shift 2 | I8: Shift 3 | J8: Total (QTY) | K8: Total (Ratio) | L8: Shift 1 (Qty) | M8: Shift 2 (Qty) | N8: Shift 3 (Qty) | O8: High reject item code / reject code | P8: Operating hours | Q8: Available operation hours target | R8: Daily opeation hours plan target | S8: Cél / Target | T8: Hatékonyság (kumulált) / Efficiency (cumulative) | U8: Hatékonyság / Efficiency
A9: =Headcount!A10 -> 2 | B9: =$D$5 -> 600 | C9: =D5*D6 -> 9000 | D9: =D5 -> 600 | E9: =F9 -> 1 | F9: =G9+H9+I9 -> 1 | G9: 1 | H9: 0 | I9: 0 | J9: =L9+M9+N9 -> 0 | K9: =IF(J9=0,0,J9/(J9+F9)) -> 0 | L9: 0 | M9: 0 | N9: 0 | P9: =[1]Munka3!$B5 -> 0 | Q9: 16 | R9: =$E$5 -> 0.8 | S9: 1 | T9: =AVERAGE($U$9:U9) -> #DIV/0! | U9: -
A10: =Headcount!A11 -> 3 | B10: =$D$5 -> 600 | C10: =$C$9-D9 -> 8400 | D10: =$D$5+D9 -> 1200 | E10: =IF(E9=0,0,E9+F10) -> 2 | F10: =G10+H10+I10 -> 1 | G10: 1 | H10: 0 | I10: 0 | J10: =L10+M10+N10 -> 0 | K10: =IF(J10=0,0,J10/(J10+F10)) -> 0 | L10: 0 | M10: 0 | N10: 0 | P10: =[1]Munka3!$B6 -> 0 | Q10: 16 | R10: =$E$5 -> 0.8 | S10: 1 | T10: =AVERAGE($U$9:U10) -> #DIV/0! | U10: -
A11: =Headcount!A12 -> 4 | B11: =$D$5 -> 600 | C11: =$C$9-D10 -> 7800 | D11: =$D$5+D10 -> 1800 | E11: =IF(E10=0,0,E10+F11) -> 3 | F11: =G11+H11+I11 -> 1 | G11: 1 | H11: 0 | I11: 0 | J11: =L11+M11+N11 -> 0 | K11: =IF(J11=0,0,J11/(J11+F11)) -> 0 | L11: 0 | M11: 0 | N11: 0 | P11: =[1]Munka3!$B7 -> 0 | Q11: 16 | R11: =$E$5 -> 0.8 | S11: 1 | T11: =AVERAGE($U$9:U11) -> #DIV/0! | U11: -
A12: =Headcount!A13 -> 5 | B12: =$D$5 -> 600 | C12: =$C$9-D11 -> 7200 | D12: =$D$5+D11 -> 2400 | E12: =IF(E11=0,0,E11+F12) -> 4 | F12: =G12+H12+I12 -> 1 | G12: 1 | H12: 0 | I12: 0 | J12: =L12+M12+N12 -> 0 | K12: =IF(J12=0,0,J12/(J12+F12)) -> 0 | L12: 0 | M12: 0 | N12: 0 | P12: =[1]Munka3!$B8 -> 0 | Q12: 16 | R12: =$E$5 -> 0.8 | S12: 1 | T12: =AVERAGE($U$9:U12) -> #DIV/0! | U12: -
A13: =Headcount!A14 -> 6 | B13: =$D$5 -> 600 | C13: =$C$9-D12 -> 6600 | D13: =$D$5+D12 -> 3000 | E13: =IF(E12=0,0,E12+F13) -> 5 | F13: =G13+H13+I13 -> 1 | G13: 1 | H13: 0 | I13: 0 | J13: =L13+M13+N13 -> 0 | K13: =IF(J13=0,0,J13/(J13+F13)) -> 0 | L13: 0 | M13: 0 | N13: 0 | P13: =[1]Munka3!$B9 -> 0 | Q13: 16 | R13: =$E$5 -> 0.8 | S13: 1 | T13: =AVERAGE($U$9:U13) -> #DIV/0! | U13: -
A14: =Headcount!A15 -> 9 | B14: =$D$5 -> 600 | C14: =$C$9-D13 -> 6000 | D14: =$D$5+D13 -> 3600 | E14: =IF(E13=0,0,E13+F14) -> 6 | F14: =G14+H14+I14 -> 1 | G14: 1 | H14: 0 | I14: 0 | J14: =L14+M14+N14 -> 0 | K14: =IF(J14=0,0,J14/(J14+F14)) -> 0 | L14: 0 | M14: 0 | N14: 0 | P14: =[1]Munka3!$B10 -> 0 | Q14: 16 | R14: =$E$5 -> 0.8 | S14: 1 | T14: =AVERAGE($U$9:U14) -> #DIV/0! | U14: -
A15: =Headcount!A16 -> 10 | B15: =$D$5 -> 600 | C15: =$C$9-D14 -> 5400 | D15: =$D$5+D14 -> 4200 | E15: =IF(E14=0,0,E14+F15) -> 2245 | F15: =G15+H15+I15 -> 2239 | G15: 2239 | H15: 0 | I15: 0 | J15: =L15+M15+N15 -> 0 | K15: =IF(J15=0,0,J15/(J15+F15)) -> 0 | L15: 0 | M15: 0 | N15: 0 | P15: =[1]Munka3!$B11 -> 0 | Q15: 16 | R15: =$E$5 -> 0.8 | S15: 1 | T15: =AVERAGE($U$9:U15) -> 1.0949 | U15: 1.0949
A16: =Headcount!A17 -> 11 | B16: =$D$5 -> 600 | C16: =$C$9-D15 -> 4800 | D16: =$D$5+D15 -> 4800 | E16: =IF(E15=0,0,E15+F16) -> 7758 | F16: =G16+H16+I16 -> 5513 | G16: 5513 | H16: 0 | I16: 0 | J16: =L16+M16+N16 -> 0 | K16: =IF(J16=0,0,J16/(J16+F16)) -> 0 | L16: 0 | M16: 0 | N16: 0 | P16: =[1]Munka3!$B12 -> 0 | Q16: 16 | R16: =$E$5 -> 0.8 | S16: 1 | T16: =AVERAGE($U$9:U16) -> 1.04915 | U16: 1.0034
A17: =Headcount!A18 -> 12 | B17: =$D$5 -> 600 | C17: =$C$9-D16 -> 4200 | D17: =$D$5+D16 -> 5400 | E17: =IF(E16=0,0,E16+F17) -> 9008 | F17: =G17+H17+I17 -> 1250 | G17: 1250 | H17: 0 | I17: 0 | J17: =L17+M17+N17 -> 0 | K17: =IF(J17=0,0,J17/(J17+F17)) -> 0 | L17: 0 | M17: 0 | N17: 0 | P17: =[1]Munka3!$B13 -> 0 | Q17: 16 | R17: =$E$5 -> 0.8 | S17: 1 | T17: =AVERAGE($U$9:U17) -> 1.0359667 | U17: 1.0096
A18: =Headcount!A19 -> 13 | B18: =$D$5 -> 600 | C18: =$C$9-D17 -> 3600 | D18: =$D$5+D17 -> 6000 | E18: =IF(E17=0,0,E17+F18) -> 9009 | F18: =G18+H18+I18 -> 1 | G18: 1 | H18: 0 | I18: 0 | J18: =L18+M18+N18 -> 0 | K18: =IF(J18=0,0,J18/(J18+F18)) -> 0 | L18: 0 | M18: 0 | N18: 0 | P18: =[1]Munka3!$B14 -> 0 | Q18: 16 | R18: =$E$5 -> 0.8 | S18: 1 | T18: =AVERAGE($U$9:U18) -> 1.0359667 | U18: -
A19: =Headcount!A20 -> 16 | B19: =$D$5 -> 600 | C19: =$C$9-D18 -> 3000 | D19: =$D$5+D18 -> 6600 | E19: =IF(E18=0,0,E18+F19) -> 9010 | F19: =G19+H19+I19 -> 1 | G19: 1 | H19: 0 | I19: 0 | J19: =L19+M19+N19 -> 0 | K19: =IF(J19=0,0,J19/(J19+F19)) -> 0 | L19: 0 | M19: 0 | N19: 0 | P19: =[1]Munka3!$B15 -> 0 | Q19: 16 | R19: =$E$5 -> 0.8 | S19: 1 | T19: =AVERAGE($U$9:U19) -> 1.0359667 | U19: -
A20: =Headcount!A21 -> 17 | B20: =$D$5 -> 600 | C20: =$C$9-D19 -> 2400 | D20: =$D$5+D19 -> 7200 | E20: =IF(E19=0,0,E19+F20) -> 9011 | F20: =G20+H20+I20 -> 1 | G20: 1 | H20: 0 | I20: 0 | J20: =L20+M20+N20 -> 0 | K20: =IF(J20=0,0,J20/(J20+F20)) -> 0 | L20: 0 | M20: 0 | N20: 0 | P20: =[1]Munka3!$B16 -> 0 | Q20: 16 | R20: =$E$5 -> 0.8 | S20: 1 | T20: =AVERAGE($U$9:U20) -> 1.0359667 | U20: -
A21: =Headcount!A22 -> 18 | B21: =$D$5 -> 600 | C21: =$C$9-D20 -> 1800 | D21: =$D$5+D20 -> 7800 | E21: =IF(E20=0,0,E20+F21) -> 9012 | F21: =G21+H21+I21 -> 1 | G21: 1 | H21: 0 | I21: 0 | J21: =L21+M21+N21 -> 0 | K21: =IF(J21=0,0,J21/(J21+F21)) -> 0 | L21: 0 | M21: 0 | N21: 0 | P21: =[1]Munka3!$B17 -> 0 | Q21: 16 | R21: =$E$5 -> 0.8 | S21: 1 | T21: =AVERAGE($U$9:U21) -> 1.0359667 | U21: -
A22: =Headcount!A23 -> 19 | B22: =$D$5 -> 600 | C22: =$C$9-D21 -> 1200 | D22: =$D$5+D21 -> 8400 | E22: =IF(E21=0,0,E21+F22) -> 9013 | F22: =G22+H22+I22 -> 1 | G22: 1 | H22: 0 | I22: 0 | J22: =L22+M22+N22 -> 0 | K22: =IF(J22=0,0,J22/(J22+F22)) -> 0 | L22: 0 | M22: 0 | N22: 0 | P22: =[1]Munka3!$B18 -> 0 | Q22: 16 | R22: =$E$5 -> 0.8 | S22: 1 | T22: =AVERAGE($U$9:U22) -> 1.0359667 | U22: -
A23: =Headcount!A24 -> 20 | B23: =$D$5 -> 600 | C23: =$C$9-D22 -> 600 | D23: =$D$5+D22 -> 9000 | E23: =IF(E22=0,0,E22+F23) -> 9014 | F23: =G23+H23+I23 -> 1 | G23: 1 | H23: 0 | I23: 0 | J23: =L23+M23+N23 -> 0 | K23: =IF(J23=0,0,J23/(J23+F23)) -> 0 | L23: 0 | M23: 0 | N23: 0 | P23: =[1]Munka3!$B19 -> 0 | Q23: 16 | R23: =$E$5 -> 0.8 | S23: 1 | T23: =AVERAGE($U$9:U23) -> 1.0359667 | U23: -
A27: Summ Line | D27: =D7*D5 -> 9000 | F27: =SUM(F9:F25) -> 9014 | L27: =SUM(L9:L26) -> 0 | M27: =SUM(M9:M26) -> 0 | N27: =SUM(N9:N26) -> 0 | O27: =SUM(L27:N27) -> 0

Sheet MIM
A1: MIM | D1: Difference to the plan | H1: =F31-D31 -> 0
B5: Napi Terv / Daily plan | D5: 0 | F5: =E9/D9 -> #DIV/0!
C6: Workdays | D6: =Headcount!F7 -> 15
C7: Actual day | D7: =Headcount!F8 -> 15 | F7: Out put daily good | J7: Reject
A8: Munkanap / Workdays | B8: Napi terv / Daily plan | C8: Hátralévő mennyiség | D8: Kumulált terv / Cumulative plan | E8: Kimenet (Kumulált) / Output (cumulative) | F8: Teljes kimenet / Total output | G8: Shift 1 | H8: Shift 2 | I8: Shift 3 | J8: Total (QTY) | K8: Total (Ratio) | L8: Shift 1 (Qty) | M8: Shift 2 (Qty) | N8: Shift 3 (Qty) | O8: High reject item code / reject code | P8: Cél / Target | Q8: Hatékonyság (kumulált) / Efficiency (cumulative) | R8: Hatékonyság / Efficiency
A9: =Headcount!A10 -> 2 | B9: =$D$5 -> 0 | C9: =D5*D6 -> 0 | D9: =D5 -> 0 | E9: =F9 -> 0 | F9: =G9+H9+I9 -> 0 | H9: 0 | I9: 0 | J9: =L9+M9+N9 -> 0 | K9: =IF(J9=0,0,J9/(J9+F9)) -> 0 | M9: 0 | N9: 0 | P9: 1
A10: =Headcount!A11 -> 3 | B10: =$D$5 -> 0 | C10: =$C$9-D9 -> 0 | D10: =$D$5+D9 -> 0 | E10: =IF(E9=0,0,E9+F10) -> 0 | F10: =G10+H10+I10 -> 0 | H10: 0 | I10: 0 | J10: =L10+M10+N10 -> 0 | K10: =IF(J10=0,0,J10/(J10+F10)) -> 0 | M10: 0 | N10: 0 | P10: 1
A11: =Headcount!A12 -> 4 | B11: =$D$5 -> 0 | C11: =$C$9-D10 -> 0 | D11: =$D$5+D10 -> 0 | F11: =G11+H11+I11 -> 0 | H11: 0 | I11: 0 | J11: =L11+M11+N11 -> 0 | K11: =IF(J11=0,0,J11/(J11+F11)) -> 0 | M11: 0 | N11: 0 | P11: 1
A12: =Headcount!A13 -> 5 | B12: =$D$5 -> 0 | C12: =$C$9-D11 -> 0 | D12: =$D$5+D11 -> 0 | F12: =G12+H12+I12 -> 0 | H12: 0 | I12: 0 | J12: =L12+M12+N12 -> 0 | K12: =IF(J12=0,0,J12/(J12+F12)) -> 0 | M12: 0 | N12: 0 | P12: 1
A13: =Headcount!A14 -> 6 | B13: =$D$5 -> 0 | C13: =$C$9-D12 -> 0 | D13: =$D$5+D12 -> 0 | F13: =G13+H13+I13 -> 0 | H13: 0 | I13: 0 | J13: =L13+M13+N13 -> 0 | K13: =IF(J13=0,0,J13/(J13+F13)) -> 0 | M13: 0 | N13: 0 | P13: 1
A14: =Headcount!A15 -> 9 | B14: =$D$5 -> 0 | C14: =$C$9-D13 -> 0 | D14: =$D$5+D13 -> 0 | F14: =G14+H14+I14 -> 0 | H14: 0 | I14: 0 | J14: =L14+M14+N14 -> 0 | K14: =IF(J14=0,0,J14/(J14+F14)) -> 0 | M14: 0 | N14: 0 | P14: 1
A15: =Headcount!A16 -> 10 | B15: =$D$5 -> 0 | C15: =$C$9-D14 -> 0 | D15: =$D$5+D14 -> 0 | F15: =G15+H15+I15 -> 0 | H15: 0 | I15: 0 | J15: =L15+M15+N15 -> 0 | K15: =IF(J15=0,0,J15/(J15+F15)) -> 0 | M15: 0 | N15: 0 | P15: 1
A16: =Headcount!A17 -> 11 | B16: =$D$5 -> 0 | C16: =$C$9-D15 -> 0 | D16: =$D$5+D15 -> 0 | F16: =G16+H16+I16 -> 0 | H16: 0 | I16: 0 | J16: =L16+M16+N16 -> 0 | K16: =IF(J16=0,0,J16/(J16+F16)) -> 0 | M16: 0 | N16: 0 | P16: 1
A17: =Headcount!A18 -> 12 | B17: =$D$5 -> 0 | C17: =$C$9-D16 -> 0 | D17: =$D$5+D16 -> 0 | F17: =G17+H17+I17 -> 0 | H17: 0 | I17: 0 | J17: =L17+M17+N17 -> 0 | K17: =IF(J17=0,0,J17/(J17+F17)) -> 0 | M17: 0 | N17: 0 | P17: 1
A18: =Headcount!A19 -> 13 | B18: =$D$5 -> 0 | C18: =$C$9-D17 -> 0 | D18: =$D$5+D17 -> 0 | F18: =G18+H18+I18 -> 0 | H18: 0 | I18: 0 | J18: =L18+M18+N18 -> 0 | K18: =IF(J18=0,0,J18/(J18+F18)) -> 0 | M18: 0 | N18: 0 | P18: 1
A19: =Headcount!A20 -> 16 | B19: =$D$5 -> 0 | C19: =$C$9-D18 -> 0 | D19: =$D$5+D18 -> 0 | F19: =G19+H19+I19 -> 0 | H19: 0 | I19: 0 | J19: =L19+M19+N19 -> 0 | K19: =IF(J19=0,0,J19/(J19+F19)) -> 0 | M19: 0 | N19: 0 | P19: 1
A20: =Headcount!A21 -> 17 | B20: =$D$5 -> 0 | C20: =$C$9-D19 -> 0 | D20: =$D$5+D19 -> 0 | F20: =G20+H20+I20 -> 0 | H20: 0 | I20: 0 | J20: =L20+M20+N20 -> 0 | K20: =IF(J20=0,0,J20/(J20+F20)) -> 0 | M20: 0 | N20: 0 | P20: 1
A21: =Headcount!A22 -> 18 | B21: =$D$5 -> 0 | C21: =$C$9-D20 -> 0 | D21: =$D$5+D20 -> 0 | F21: =G21+H21+I21 -> 0 | H21: 0 | I21: 0 | J21: =L21+M21+N21 -> 0 | K21: =IF(J21=0,0,J21/(J21+F21)) -> 0 | M21: 0 | N21: 0 | P21: 1
A22: =Headcount!A23 -> 19 | B22: =$D$5 -> 0 | C22: =$C$9-D21 -> 0 | D22: =$D$5+D21 -> 0 | F22: =G22+H22+I22 -> 0 | H22: 0 | I22: 0 | J22: =L22+M22+N22 -> 0 | K22: =IF(J22=0,0,J22/(J22+F22)) -> 0 | M22: 0 | N22: 0 | P22: 1
... A28: =Headcount!A29 -> 0 | B28: =$D$5 -> 0 | C28: =$C$9-D27 -> 0 | D28: =$D$5+D27 -> 0 | F28: =G28+H28+I28 -> 0 | H28: 0 | I28: 0 | J28: =L28+M28+N28 -> 0 | K28: =IF(J28=0,0,J28/(J28+F28)) -> 0 | M28: 0 | N28: 0 | P28: 1
A31: Summ Line | D31: =D7*D5 -> 0 | F31: =SUM(F9:F29) -> 0 | L31: =SUM(L9:L30) -> 0 | M31: =SUM(M9:M30) -> 0 | N31: =SUM(N9:N30) -> 0 | O31: =SUM(L31:N31) -> 0

Sheet CAOI
A1: CAOI | D1: Difference to the plan | H1: =F27-D27 -> 0
D3: Mennyiség/ Quantity | E3: Óra/ Hours
L4: =C9/3200*8 -> 0
B5: Napi Terv / Daily plan | D5: 0 | E5: =D5/(3000/8) -> 0 | F5: =E9/D9 -> #DIV/0! | L5: =1*D6*8 -> 120 | M5: =L4/L5 -> 0
C6: Workdays | D6: =Headcount!F7 -> 15
C7: Actual day | D7: =Headcount!F8 -> 15 | F7: Out put daily good | J7: Reject
A8: Munkanap / Workdays | B8: Napi terv / Daily plan | C8: Hátralévő mennyiség | D8: Kumulált terv / Cumulative plan | E8: Kimenet (Kumulált) / Output (cumulative) | F8: Teljes kimenet / Total output | G8: Shift 1 | H8: Shift 2 | I8: Shift 3 | J8: Total (QTY) | K8: Total (Ratio) | L8: Shift 1 | M8: Shift 2 | N8: Shift 3 | O8: Comment | P8: Operating hours | Q8: Operation hours target | R8: Daily opeation hours plan target | S8: Cél / Target | T8: Hatékonyság (kumulált) / Efficiency (cumulative) | U8: Hatékonyság / Efficiency
A9: =Headcount!A10 -> 2 | B9: =$D$5 -> 0 | C9: =D5*D6 -> 0 | D9: =D5 -> 0 | E9: =F9 -> 0 | F9: =G9+H9+I9 -> 0 | G9: 0 | H9: 0 | I9: 0 | J9: =L9+M9+N9 -> 0 | K9: =IF(J9=0,0,J9/(J9+F9)) -> 0 | L9: 0 | M9: 0 | N9: 0 | P9: =[1]Munka3!$E5 -> 0 | Q9: 8 | R9: =$E$5 -> 0 | S9: 1 | T9: =AVERAGE($U$9:U9) -> #DIV/0! | U9: -
A10: =Headcount!A11 -> 3 | B10: =$D$5 -> 0 | C10: =$C$9-D9 -> 0 | D10: =D9+$D$5 -> 0 | E10: =IF(E9=0,0,E9+F10) -> 0 | F10: =G10+H10+I10 -> 0 | H10: 0 | I10: 0 | J10: =L10+M10+N10 -> 0 | K10: 0 | L10: 0 | M10: 0 | N10: 0 | P10: =[1]Munka3!$E6 -> 0 | Q10: 8 | R10: =$E$5 -> 0 | S10: 1 | T10: =AVERAGE($U$9:U10) -> #DIV/0!
A11: =Headcount!A12 -> 4 | B11: =$D$5 -> 0 | C11: =$C$9-D10 -> 0 | D11: =D10+$D$5 -> 0 | E11: =IF(E10=0,0,E10+F11) -> 0 | F11: =G11+H11+I11 -> 0 | H11: 0 | I11: 0 | J11: =L11+M11+N11 -> 0 | K11: 0 | L11: 0 | M11: 0 | N11: 0 | P11: =[1]Munka3!$E7 -> 0 | Q11: 8 | R11: =$E$5 -> 0 | S11: 1 | T11: =AVERAGE($U$9:U11) -> #DIV/0!
A12: =Headcount!A13 -> 5 | B12: =$D$5 -> 0 | C12: =$C$9-D11 -> 0 | D12: =D11+$D$5 -> 0 | E12: =IF(E11=0,0,E11+F12) -> 0 | F12: =G12+H12+I12 -> 0 | H12: 0 | I12: 0 | J12: =L12+M12+N12 -> 0 | K12: =IF(J12=0,0,J12/(J12+F12)) -> 0 | L12: 0 | M12: 0 | N12: 0 | P12: =[1]Munka3!$E8 -> 0 | Q12: 8 | R12: =$E$5 -> 0 | S12: 1 | T12: =AVERAGE($U$9:U12) -> #DIV/0!
A13: =Headcount!A14 -> 6 | B13: =$D$5 -> 0 | C13: =$C$9-D12 -> 0 | D13: =D12+$D$5 -> 0 | E13: =IF(E12=0,0,E12+F13) -> 0 | F13: =G13+H13+I13 -> 0 | H13: 0 | I13: 0 | J13: =L13+M13+N13 -> 0 | K13: =IF(J13=0,0,J13/(J13+F13)) -> 0 | L13: 0 | M13: 0 | N13: 0 | P13: =[1]Munka3!$E9 -> 0 | Q13: 8 | R13: =$E$5 -> 0 | S13: 1 | T13: =AVERAGE($U$9:U13) -> #DIV/0!
A14: =Headcount!A15 -> 9 | B14: =$D$5 -> 0 | C14: =$C$9-D13 -> 0 | D14: =D13+$D$5 -> 0 | E14: =IF(E13=0,0,E13+F14) -> 0 | F14: =G14+H14+I14 -> 0 | H14: 0 | I14: 0 | J14: =L14+M14+N14 -> 0 | K14: =IF(J14=0,0,J14/(J14+F14)) -> 0 | L14: 0 | M14: 0 | N14: 0 | P14: =[1]Munka3!$E10 -> 0 | Q14: 8 | R14: =$E$5 -> 0 | S14: 1 | T14: =AVERAGE($U$9:U14) -> #DIV/0!
A15: =Headcount!A16 -> 10 | B15: =$D$5 -> 0 | C15: =$C$9-D14 -> 0 | D15: =D14+$D$5 -> 0 | E15: =IF(E14=0,0,E14+F15) -> 0 | F15: =G15+H15+I15 -> 0 | H15: 0 | I15: 0 | J15: =L15+M15+N15 -> 0 | K15: =IF(J15=0,0,J15/(J15+F15)) -> 0 | L15: 0 | M15: 0 | N15: 0 | P15: =[1]Munka3!$E11 -> 0 | Q15: 8 | R15: =$E$5 -> 0 | S15: 1 | T15: =AVERAGE($U$9:U15) -> #DIV/0!
A16: =Headcount!A17 -> 11 | B16: =$D$5 -> 0 | C16: =$C$9-D15 -> 0 | D16: =D15+$D$5 -> 0 | E16: =IF(E15=0,0,E15+F16) -> 0 | F16: =G16+H16+I16 -> 0 | H16: 0 | I16: 0 | J16: =L16+M16+N16 -> 0 | K16: =IF(J16=0,0,J16/(J16+F16)) -> 0 | L16: 0 | M16: 0 | N16: 0 | P16: =[1]Munka3!$E12 -> 0 | Q16: 8 | R16: =$E$5 -> 0 | S16: 1 | T16: =AVERAGE($U$9:U16) -> #DIV/0!
A17: =Headcount!A18 -> 12 | B17: =$D$5 -> 0 | C17: =$C$9-D16 -> 0 | D17: =D16+$D$5 -> 0 | E17: =IF(E16=0,0,E16+F17) -> 0 | F17: =G17+H17+I17 -> 0 | H17: 0 | I17: 0 | J17: =L17+M17+N17 -> 0 | K17: =IF(J17=0,0,J17/(J17+F17)) -> 0 | L17: 0 | M17: 0 | N17: 0 | P17: =[1]Munka3!$E13 -> 0 | Q17: 8 | R17: =$E$5 -> 0 | S17: 1 | T17: =AVERAGE($U$9:U17) -> #DIV/0!
A18: =Headcount!A19 -> 13 | B18: =$D$5 -> 0 | C18: =$C$9-D17 -> 0 | D18: =D17+$D$5 -> 0 | E18: =IF(E17=0,0,E17+F18) -> 0 | F18: =G18+H18+I18 -> 0 | H18: 0 | I18: 0 | J18: =L18+M18+N18 -> 0 | K18: =IF(J18=0,0,J18/(J18+F18)) -> 0 | L18: 0 | M18: 0 | N18: 0 | P18: =[1]Munka3!$E14 -> 0 | Q18: 8 | R18: =$E$5 -> 0 | S18: 1 | T18: =AVERAGE($U$9:U18) -> #DIV/0!
A19: =Headcount!A20 -> 16 | B19: =$D$5 -> 0 | C19: =$C$9-D18 -> 0 | D19: =D18+$D$5 -> 0 | E19: =IF(E18=0,0,E18+F19) -> 0 | F19: =G19+H19+I19 -> 0 | H19: 0 | I19: 0 | J19: =L19+M19+N19 -> 0 | K19: =IF(J19=0,0,J19/(J19+F19)) -> 0 | L19: 0 | M19: 0 | N19: 0 | P19: =[1]Munka3!$E15 -> 0 | Q19: 8 | R19: =$E$5 -> 0 | S19: 1 | T19: =AVERAGE($U$9:U19) -> #DIV/0!
A20: =Headcount!A21 -> 17 | B20: =$D$5 -> 0 | C20: =$C$9-D19 -> 0 | D20: =D19+$D$5 -> 0 | E20: =IF(E19=0,0,E19+F20) -> 0 | F20: =G20+H20+I20 -> 0 | H20: 0 | I20: 0 | J20: =L20+M20+N20 -> 0 | K20: =IF(J20=0,0,J20/(J20+F20)) -> 0 | L20: 0 | M20: 0 | N20: 0 | P20: =[1]Munka3!$E16 -> 0 | Q20: 8 | R20: =$E$5 -> 0 | S20: 1 | T20: =AVERAGE($U$9:U20) -> #DIV/0!
A21: =Headcount!A22 -> 18 | B21: =$D$5 -> 0 | C21: =$C$9-D20 -> 0 | D21: =D20+$D$5 -> 0 | E21: =IF(E20=0,0,E20+F21) -> 0 | F21: =G21+H21+I21 -> 0 | H21: 0 | I21: 0 | J21: =L21+M21+N21 -> 0 | K21: =IF(J21=0,0,J21/(J21+F21)) -> 0 | L21: 0 | M21: 0 | N21: 0 | P21: =[1]Munka3!$E17 -> 0 | Q21: 8 | R21: =$E$5 -> 0 | S21: 1 | T21: =AVERAGE($U$9:U21) -> #DIV/0!
A22: =Headcount!A23 -> 19 | B22: =$D$5 -> 0 | C22: =$C$9-D21 -> 0 | D22: =D21+$D$5 -> 0 | E22: =IF(E21=0,0,E21+F22) -> 0 | F22: =G22+H22+I22 -> 0 | H22: 0 | I22: 0 | J22: =L22+M22+N22 -> 0 | K22: =IF(J22=0,0,J22/(J22+F22)) -> 0 | L22: 0 | M22: 0 | N22: 0 | P22: =[1]Munka3!$E18 -> 0 | Q22: 8 | R22: =$E$5 -> 0 | S22: 1 | T22: =AVERAGE($U$9:U22) -> #DIV/0!
A23: =Headcount!A24 -> 20 | B23: =$D$5 -> 0 | C23: =$C$9-D22 -> 0 | D23: =D22+$D$5 -> 0 | E23: =IF(E22=0,0,E22+F23) -> 0 | F23: =G23+H23+I23 -> 0 | H23: 0 | I23: 0 | J23: =L23+M23+N23 -> 0 | K23: =IF(J23=0,0,J23/(J23+F23)) -> 0 | L23: 0 | M23: 0 | N23: 0 | P23: =[1]Munka3!$E19 -> 0 | Q23: 8 | R23: =$E$5 -> 0 | S23: 1 | T23: =AVERAGE($U$9:U23) -> #DIV/0!
A27: Summ Line | D27: =D7*D5 -> 0 | F27: =SUM(F9:F25) -> 0 | L27: =SUM(L9:L26) -> 0 | M27: =SUM(M9:M26) -> 0 | N27: =SUM(N9:N26) -> 0 | O27: =SUM(L27:N27) -> 0

Sheet AD Auto PKY
A1: ADPKY | D1: Difference to the plan | H1: =F31-D31 -> 1761 | J1: NK: BD-s típus esetén 50mm alatti, valamint AD-s terméknél 60mm alatti I méretű kábelek esetén nem lehet visszahúzni.
D3: Mennyiség/ Quantity | E3: Óra/ Hours | F3: Gépszám
F4: 4 | L4: =C9/4600*8 -> 59.478261
B5: Napi Terv / Daily plan | D5: 2280 | E5: =D5/(4500*F4/8) -> 1.0133333 | F5: =E23/D23 -> 1.0514912 | L5: =4*D6*8 -> 480 | M5: =L4/L5 -> 0.12391304
C6: Workday | D6: =Headcount!F7 -> 15
C7: Actual day | D7: =Headcount!F8 -> 15 | F7: Out put daily good | J7: Reject
A8: Munkanap / Workdays | B8: Napi terv / Daily plan | C8: Hátralévő mennyiség | D8: Kumulált terv / Cumulative plan | E8: Kimenet (Kumulált) / Output (cumulative) | F8: Teljes kimenet / Total output | G8: Shift 1 | H8: Shift 2 | I8: Shift 3 | J8: Total (QTY) | K8: Total (Ratio) | L8: Shift 1 (Qty) | M8: Shift 2 (Qty) | N8: Shift 3 (Qty) | O8: AA hiba (HA ,F S 0374) Beszállítóval fizettetni! | P8: TO Reject | Q8: TST | R8: MAA | S8: Baáll. Selejt | T8: NK | U8: High reject item code / reject code | V8: Operating hours | W8: Available operation hours target | X8: Daily opeation hours plan target | Y8: Cél / Target | Z8: Hatékonyság (kumulált) / Efficiency (cumulative) | AA8: Hatékonyság / Efficiency
A9: =Headcount!A10 -> 2 | B9: =$D$5 -> 2280 | C9: =D5*D6 -> 34200 | D9: =D5 -> 2280 | E9: =F9 -> 1 | F9: =G9+H9+I9 -> 1 | G9: 1 | H9: 0 | I9: 0 | J9: =L9+M9+N9+S9+O9 -> 0 | K9: =IF(J9=0,0,J9/(J9+F9)) -> 0 | L9: 0 | M9: 0 | N9: 0 | O9: 0 | P9: 0 | Q9: 0 | R9: 0 | S9: 0 | T9: 0 | V9: =[1]Munka3!$C5 -> 0 | W9: 32 | X9: =$E$5 -> 1.0133333 | Y9: 1 | Z9: =AVERAGE($AA$9:AA9) -> #DIV/0! | AA9: -
A10: =Headcount!A11 -> 3 | B10: =$D$5 -> 2280 | C10: =$C$9-D9 -> 31920 | D10: =D9+$D$5 -> 4560 | E10: =IF(E9=0,0,E9+F10) -> 2 | F10: =G10+H10+I10 -> 1 | G10: 1 | H10: 0 | I10: 0 | J10: =L10+M10+N10+S10+O10 -> 0 | K10: =IF(J10=0,0,J10/(J10+F10)) -> 0 | L10: 0 | M10: 0 | N10: 0 | O10: 0 | P10: 0 | Q10: 0 | R10: 0 | S10: 0 | T10: 0 | V10: =[1]Munka3!$C6 -> 0 | W10: 32 | X10: =$E$5 -> 1.0133333 | Y10: 1 | Z10: =AVERAGE($AA$9:AA10) -> #DIV/0! | AA10: -
A11: =Headcount!A12 -> 4 | B11: =$D$5 -> 2280 | C11: =$C$9-D10 -> 29640 | D11: =D10+$D$5 -> 6840 | E11: =IF(E10=0,0,E10+F11) -> 8519 | F11: =G11+H11+I11 -> 8517 | G11: 8517 | H11: 0 | I11: 0 | J11: =L11+M11+N11+S11+O11 -> 72 | K11: =IF(J11=0,0,J11/(J11+F11)) -> 0.0083828152 | L11: 42 | M11: 0 | N11: 0 | O11: 0 | P11: 23 | Q11: 0 | R11: 1 | S11: 30 | T11: 10 | U11: - | V11: =[1]Munka3!$C7 -> 0 | W11: 32 | X11: =$E$5 -> 1.0133333 | Y11: 1 | Z11: =AVERAGE($AA$9:AA11) -> 1.0185 | AA11: 1.0185
A12: =Headcount!A13 -> 5 | B12: =$D$5 -> 2280 | C12: =$C$9-D11 -> 27360 | D12: =D11+$D$5 -> 9120 | E12: =IF(E11=0,0,E11+F12) -> 16487 | F12: =G12+H12+I12 -> 7968 | G12: 7968 | H12: 0 | I12: 0 | J12: =L12+M12+N12+S12+O12 -> 18 | K12: =IF(J12=0,0,J12/(J12+F12)) -> 0.0022539444 | L12: 18 | M12: 0 | N12: 0 | O12: 0 | P12: 29 | Q12: 0 | R12: 1 | S12: 0 | T12: 13 | U12: - | V12: =[1]Munka3!$C8 -> 0 | W12: 32 | X12: =$E$5 -> 1.0133333 | Y12: 1 | Z12: =AVERAGE($AA$9:AA12) -> 1.0137 | AA12: 1.0089
A13: =Headcount!A14 -> 6 | B13: =$D$5 -> 2280 | C13: =$C$9-D12 -> 25080 | D13: =D12+$D$5 -> 11400 | E13: =IF(E12=0,0,E12+F13) -> 20075 | F13: =G13+H13+I13 -> 3588 | G13: 3588 | H13: 0 | I13: 0 | J13: =L13+M13+N13+S13+O13 -> 6 | K13: =IF(J13=0,0,J13/(J13+F13)) -> 0.0016694491 | L13: 6 | M13: 0 | N13: 0 | O13: 0 | P13: 13 | Q13: 0 | R13: 0 | S13: 0 | T13: 11 | U13: - | V13: =[1]Munka3!$C9 -> 0 | W13: 32 | X13: =$E$5 -> 1.0133333 | Y13: 1 | Z13: =AVERAGE($AA$9:AA13) -> 1.0412667 | AA13: 1.0964
A14: =Headcount!A15 -> 9 | B14: =$D$5 -> 2280 | C14: =$C$9-D13 -> 22800 | D14: =D13+$D$5 -> 13680 | E14: =IF(E13=0,0,E13+F14) -> 20076 | F14: =G14+H14+I14 -> 1 | G14: 1 | H14: 0 | I14: 0 | J14: =L14+M14+N14+S14+O14 -> 0 | K14: =IF(J14=0,0,J14/(J14+F14)) -> 0 | L14: 0 | M14: 0 | N14: 0 | O14: 0 | P14: 0 | Q14: 0 | R14: 0 | S14: 0 | T14: 0 | U14: - | V14: =[1]Munka3!$C10 -> 0 | W14: 32 | X14: =$E$5 -> 1.0133333 | Y14: 1 | Z14: =AVERAGE($AA$9:AA14) -> 1.0412667 | AA14: -
A15: =Headcount!A16 -> 10 | B15: =$D$5 -> 2280 | C15: =$C$9-D14 -> 20520 | D15: =D14+$D$5 -> 15960 | E15: =IF(E14=0,0,E14+F15) -> 20077 | F15: =G15+H15+I15 -> 1 | G15: 1 | H15: 0 | I15: 0 | J15: =L15+M15+N15+S15+O15 -> 0 | K15: =IF(J15=0,0,J15/(J15+F15)) -> 0 | L15: 0 | M15: 0 | N15: 0 | O15: 0 | P15: 0 | Q15: 0 | R15: 0 | S15: 0 | T15: 0 | U15: - | V15: =[1]Munka3!$C11 -> 0 | W15: 32 | X15: =$E$5 -> 1.0133333 | Y15: 1 | Z15: =AVERAGE($AA$9:AA15) -> 1.0412667 | AA15: -
A16: =Headcount!A17 -> 11 | B16: =$D$5 -> 2280 | C16: =$C$9-D15 -> 18240 | D16: =D15+$D$5 -> 18240 | E16: =IF(E15=0,0,E15+F16) -> 20078 | F16: =G16+H16+I16 -> 1 | G16: 1 | H16: 0 | I16: 0 | J16: =L16+M16+N16+S16+O16 -> 0 | K16: =IF(J16=0,0,J16/(J16+F16)) -> 0 | L16: 0 | M16: 0 | N16: 0 | O16: 0 | P16: 0 | Q16: 0 | R16: 0 | S16: 0 | T16: 0 | U16: - | V16: =[1]Munka3!$C12 -> 0 | W16: 32 | X16: =$E$5 -> 1.0133333 | Y16: 1 | Z16: =AVERAGE($AA$9:AA16) -> 1.0412667 | AA16: -
A17: =Headcount!A18 -> 12 | B17: =$D$5 -> 2280 | C17: =$C$9-D16 -> 15960 | D17: =D16+$D$5 -> 20520 | E17: =IF(E16=0,0,E16+F17) -> 28429 | F17: =G17+H17+I17 -> 8351 | G17: 8351 | H17: 0 | I17: 0 | J17: =L17+M17+N17+S17+O17 -> 38 | K17: =IF(J17=0,0,J17/(J17+F17)) -> 0.0045297413 | L17: 29 | M17: 0 | N17: 0 | O17: 0 | P17: 51 | Q17: 0 | R17: 126 | S17: 9 | T17: 37 | U17: - | V17: =[1]Munka3!$C13 -> 0 | W17: 32 | X17: =$E$5 -> 1.0133333 | Y17: 1 | Z17: =AVERAGE($AA$9:AA17) -> 1.051925 | AA17: 1.0839
A18: =Headcount!A19 -> 13 | B18: =$D$5 -> 2280 | C18: =$C$9-D17 -> 13680 | D18: =D17+$D$5 -> 22800 | E18: =IF(E17=0,0,E17+F18) -> 34256 | F18: =G18+H18+I18 -> 5827 | G18: 5827 | H18: 0 | I18: 0 | J18: =L18+M18+N18+S18+O18 -> 17 | K18: =IF(J18=0,0,J18/(J18+F18)) -> 0.0029089665 | L18: 17 | M18: 0 | N18: 0 | O18: 0 | P18: 30 | Q18: 0 | R18: 36 | S18: 0 | T18: 20 | U18: - | V18: =[1]Munka3!$C14 -> 0 | W18: 32 | X18: =$E$5 -> 1.0133333 | Y18: 1 | Z18: =AVERAGE($AA$9:AA18) -> 1.0482 | AA18: 1.0333
A19: =Headcount!A20 -> 16 | B19: =$D$5 -> 2280 | C19: =$C$9-D18 -> 11400 | D19: =D18+$D$5 -> 25080 | E19: =IF(E18=0,0,E18+F19) -> 34257 | F19: =G19+H19+I19 -> 1 | G19: 1 | H19: 0 | I19: 0 | J19: =L19+M19+N19+S19+O19 -> 0 | K19: =IF(J19=0,0,J19/(J19+F19)) -> 0 | L19: 0 | M19: 0 | N19: 0 | O19: 0 | P19: 0 | Q19: 0 | R19: 0 | S19: 0 | T19: 0 | U19: - | V19: =[1]Munka3!$C15 -> 0 | W19: 32 | X19: =$E$5 -> 1.0133333 | Y19: 1 | Z19: =AVERAGE($AA$9:AA19) -> 1.0482 | AA19: -
A20: =Headcount!A21 -> 17 | B20: =$D$5 -> 2280 | C20: =$C$9-D19 -> 9120 | D20: =D19+$D$5 -> 27360 | E20: =IF(E19=0,0,E19+F20) -> 34258 | F20: =G20+H20+I20 -> 1 | G20: 1 | H20: 0 | I20: 0 | J20: =L20+M20+N20+S20+O20 -> 0 | K20: =IF(J20=0,0,J20/(J20+F20)) -> 0 | L20: 0 | M20: 0 | N20: 0 | O20: 0 | P20: 0 | Q20: 0 | R20: 0 | S20: 0 | T20: 0 | U20: - | V20: =[1]Munka3!$C16 -> 0 | W20: 32 | X20: =$E$5 -> 1.0133333 | Y20: 1 | Z20: =AVERAGE($AA$9:AA20) -> 1.0482 | AA20: -
A21: =Headcount!A22 -> 18 | B21: =$D$5 -> 2280 | C21: =$C$9-D20 -> 6840 | D21: =D20+$D$5 -> 29640 | E21: =IF(E20=0,0,E20+F21) -> 35959 | F21: =G21+H21+I21 -> 1701 | G21: 1701 | H21: 0 | I21: 0 | J21: =L21+M21+N21+S21+O21 -> 17 | K21: =IF(J21=0,0,J21/(J21+F21)) -> 0.009895227 | L21: 7 | M21: 0 | N21: 0 | O21: 0 | P21: 4 | Q21: 0 | R21: 10 | S21: 10 | T21: 5 | U21: - | V21: =[1]Munka3!$C17 -> 0 | W21: 32 | X21: =$E$5 -> 1.0133333 | Y21: 1 | Z21: =AVERAGE($AA$9:AA21) -> 1.0662833 | AA21: 1.1567
A22: =Headcount!A23 -> 19 | B22: =$D$5 -> 2280 | C22: =$C$9-D21 -> 4560 | D22: =D21+$D$5 -> 31920 | E22: =IF(E21=0,0,E21+F22) -> 35960 | F22: =G22+H22+I22 -> 1 | G22: 1 | H22: 0 | I22: 0 | J22: =L22+M22+N22+S22+O22 -> 0 | K22: =IF(J22=0,0,J22/(J22+F22)) -> 0 | L22: 0 | M22: 0 | N22: 0 | O22: 0 | P22: 0 | Q22: 0 | R22: 0 | S22: 0 | T22: 0 | U22: - | V22: =[1]Munka3!$C18 -> 0 | W22: 32 | X22: =$E$5 -> 1.0133333 | Y22: 1 | Z22: =AVERAGE($AA$9:AA22) -> 1.0662833 | AA22: -
A23: =Headcount!A24 -> 20 | B23: =$D$5 -> 2280 | C23: =$C$9-D22 -> 2280 | D23: =D22+$D$5 -> 34200 | E23: =IF(E22=0,0,E22+F23) -> 35961 | F23: =G23+H23+I23 -> 1 | G23: 1 | H23: 0 | I23: 0 | J23: =L23+M23+N23+S23+O23 -> 0 | K23: =IF(J23=0,0,J23/(J23+F23)) -> 0 | L23: 0 | M23: 0 | N23: 0 | O23: 0 | P23: 0 | Q23: 0 | R23: 0 | S23: 0 | T23: 0 | U23: - | V23: =[1]Munka3!$C19 -> 0 | W23: 32 | X23: =$E$5 -> 1.0133333 | Y23: 1 | Z23: =AVERAGE($AA$9:AA23) -> 1.0662833 | AA23: -
A31: Summ line | D31: =D7*D5 -> 34200 | F31: =SUM(F9:F29) -> 35961 | J31: =SUM(J9:J30) -> 168 | K31: =IF(J31=0,0,J31/(J31+F31)) -> 0.0046500042 | L31: =SUM(L9:L30) -> 119 | M31: =SUM(M9:M30) -> 0 | N31: =SUM(N9:N30) -> 0 | O31: =SUM(O9:O30) -> 0 | P31: =SUM(P9:P30) -> 150 | Q31: =SUM(Q9:Q30) -> 0 | R31: =SUM(R9:R30) -> 174 | S31: =SUM(S9:S30) -> 49 | T31: =SUM(T9:T30) -> 96
I33: 185 | L33: Srap with TO/AA | N33: =L31+M31+N31+P31+R31+S31+T31+O31 -> 588
I34: 257 | L34: Srap without TO/AA | N34: =L31+M31+N31+S31+T31 -> 264

Sheet Manual PKY
A1: MAN | C1: Difference to the plan | G1: =E33-C33 -> 0
A2: PKY
B5: Daily plan | C5: 0 | E5: =D18/C18 -> #DIV/0!
B6: Workday | C6: =Headcount!F7 -> 15
B7: Actual day | C7: =Headcount!F8 -> 15 | E7: Out put daily good | I7: Operator / day TTL
A8: Munkanap | B8: Hátralévő mennyiség | C8: Komulált terv | D8: Kimenet (Komulált) | E8: Total | F8: Shift 1 | G8: Shift 2 | H8: Shift 3 | I8: Op.Plan | J8: Op.Act | K8: Diff | L8: Qty/op | M8: Productivity (NAV) | N8: Difficult item's code | P8: Efficiency
A9: =Headcount!A10 -> 2 | B9: =C5*C6 -> 0 | C9: =C5 -> 0 | D9: =E9 -> 0 | E9: =F9+G9+H9 -> 0
A10: =Headcount!A11 -> 3 | B10: =$B$9-C10 -> 0 | C10: =C9+$C$5 -> 0 | D10: =IF(E10=0,0,D9+E10) -> 0 | E10: =F10+G10+H10 -> 0 | L10: =IF(E10=0,0,E10/J10) -> 0
A11: =Headcount!A12 -> 4 | B11: =$B$9-C11 -> 0 | C11: =C10+$C$5 -> 0 | D11: =IF(E11=0,0,D10+E11) -> 0 | E11: =F11+G11+H11 -> 0 | L11: =IF(E11=0,0,E11/J11) -> 0
A12: =Headcount!A13 -> 5 | B12: =$B$10-C11 -> 0 | C12: =C11+$C$5 -> 0 | D12: =IF(E12=0,0,D11+E12) -> 0 | E12: =F12+G12+H12 -> 0 | L12: =IF(E12=0,0,E12/J12) -> 0
A13: =Headcount!A14 -> 6 | B13: =$B$10-C12 -> 0 | C13: =C12+$C$5 -> 0 | D13: =IF(E13=0,0,D12+E13) -> 0 | E13: =F13+G13+H13 -> 0 | L13: =IF(E13=0,0,E13/J13) -> 0
A14: =Headcount!A15 -> 9 | B14: =$B$10-C13 -> 0 | C14: =C13+$C$5 -> 0 | D14: =IF(E14=0,0,D13+E14) -> 0 | E14: =F14+G14+H14 -> 0 | L14: =IF(E14=0,0,E14/J14) -> 0
A15: =Headcount!A16 -> 10 | B15: =$B$10-C14 -> 0 | C15: =C14+$C$5 -> 0 | D15: =IF(E15=0,0,D14+E15) -> 0 | E15: =F15+G15+H15 -> 0 | L15: =IF(E15=0,0,E15/J15) -> 0
A16: =Headcount!A17 -> 11 | B16: =$B$10-C15 -> 0 | C16: =C15+$C$5 -> 0 | D16: =IF(E16=0,0,D15+E16) -> 0 | E16: =F16+G16+H16 -> 0 | L16: =IF(E16=0,0,E16/J16) -> 0
A17: =Headcount!A18 -> 12 | B17: =$B$10-C16 -> 0 | C17: =C16+$C$5 -> 0 | D17: =IF(E17=0,0,D16+E17) -> 0 | E17: =F17+G17+H17 -> 0 | L17: =IF(E17=0,0,E17/J17) -> 0
A18: =Headcount!A19 -> 13 | B18: =$B$10-C17 -> 0 | C18: =C17+$C$5 -> 0 | D18: =IF(E18=0,0,D17+E18) -> 0 | E18: =F18+G18+H18 -> 0 | L18: =IF(E18=0,0,E18/J18) -> 0
A19: =Headcount!A20 -> 16 | B19: =$B$10-C18 -> 0 | C19: =C18+$C$5 -> 0 | D19: =IF(E19=0,0,D18+E19) -> 0 | E19: =F19+G19+H19 -> 0 | L19: =IF(E19=0,0,E19/J19) -> 0
A20: =Headcount!#REF! -> #REF! | B20: =$B$10-C19 -> 0 | C20: =C19+$C$5 -> 0 | D20: =IF(E20=0,0,D19+E20) -> 0 | E20: =F20+G20+H20 -> 0 | L20: =IF(E20=0,0,E20/J20) -> 0
A21: =Headcount!A21 -> 17 | B21: =$B$10-C20 -> 0 | C21: =C20+$C$5 -> 0 | D21: =IF(E21=0,0,D20+E21) -> 0 | E21: =F21+G21+H21 -> 0 | L21: =IF(E21=0,0,E21/J21) -> 0
A22: =Headcount!A22 -> 18 | B22: =$B$10-C21 -> 0 | C22: =C21+$C$5 -> 0 | D22: =IF(E22=0,0,D21+E22) -> 0 | E22: =F22+G22+H22 -> 0 | L22: =IF(E22=0,0,E22/J22) -> 0
A23: =Headcount!A23 -> 19 | B23: =$B$10-C22 -> 0 | C23: =C22+$C$5 -> 0 | D23: =IF(E23=0,0,D22+E23) -> 0 | E23: =F23+G23+H23 -> 0 | L23: =IF(E23=0,0,E23/J23) -> 0
E32: =F32+G32+H32 -> 0
A33: Summ line | C33: =C5*C7 -> 0 | E33: =SUM(E9:E32) -> 0

Sheet CYT
A1: CYT | D1: Difference to the plan | H1: =F31-D31 -> 5910
H2: ='AD Auto PKY'!H1:I1+CYT!H1 -> 7671
C3: Mennyiség/ Quantity | D3: Óra/ Hours | E3: Gépszám
E4: 2 | L4: =C9/4000*8 -> 150
A5: Daily Plan | C5: 5000 | D5: =C5/(4000*E4/8) -> 5 | F5: =E23/D23 -> 1.0788 | L5: =2*C6*8 -> 240 | M5: =L4/L5 -> 0.625
A6: Workday | C6: =Headcount!F7 -> 15
A7: Actual day | C7: =Headcount!F8 -> 15 | F7: Out put daily good | J7: Reject
A8: Munkanap / Workdays | B8: Napi terv / Daily plan | C8: Hátralévő mennyiség | D8: Kumulált terv / Cumulative plan | E8: Kimenet (Kumulált) / Output (cumulative) | F8: Teljes kimenet / Total output | G8: Shift 1 | H8: Shift 2 | I8: Shift 3 | J8: Total (QTY) | K8: Total (Ratio) | L8: Shift 1 (Qty) | M8: Shift 2 (Qty) | N8: Shift 3 (Qty) | O8: Setup reject | P8: AA hiba (HA ,F) Beszállítóval fizettetni! | Q8: TO | R8: MAA | S8: TST | T8: NK | U8: High reject item code / reject code | V8: Operating hours | W8: Available operation hours target | X8: Daily opeation hours plan target | Y8: Cél / Target | Z8: Hatékonyság (kumulált) / Efficiency (cumulative) | AA8: Hatékonyság / Efficiency
A9: =Headcount!A10 -> 2 | B9: =$C$5 -> 5000 | C9: =C5*C6 -> 75000 | D9: =C5 -> 5000 | E9: =F9 -> 6059 | F9: =G9+H9+I9 -> 6059 | G9: 6059 | H9: 0 | I9: 0 | J9: =L9+M9+N9+O9+P9 -> 189 | K9: =IF(J9=0,0,J9/(J9+F9)) -> 0.03024968 | L9: 166 | M9: 0 | N9: 0 | O9: 23 | P9: 0 | Q9: 9 | R9: 23 | S9: 0 | T9: 25 | U9: 12-1368 Elüti az S és MA méretet, sebbesség 5-re levéve. MA 70 db / S 20 db /E 20 db / BS 23 db | V9: =[1]Munka3!$G5 -> 8 | W9: =8*2 -> 16 | X9: =$D$5 -> 5 | Y9: 1 | Z9: =AVERAGE($AA$9:AA9) -> 0.8881 | AA9: 0.8881 | AB9: 12-1368
A10: =Headcount!A11 -> 3 | B10: =$C$5 -> 5000 | C10: =$C$9-D9 -> 70000 | D10: =D9+$C$5 -> 10000 | E10: =IF(E9=0,0,E9+F10) -> 11902 | F10: =G10+H10+I10 -> 5843 | G10: 5843 | H10: 0 | I10: 0 | J10: =L10+M10+N10+O10+P10 -> 164 | K10: =IF(J10=0,0,J10/(J10+F10)) -> 0.027301482 | L10: 144 | M10: 0 | N10: 0 | O10: 20 | P10: 0 | Q10: 16 | R10: 15 | S10: 0 | T10: 14 | U10: 1200-1368 MA 45 db / E 62 db / BS 11 db | V10: =[1]Munka3!$G6 -> 0 | W10: =8*2 -> 16 | X10: =$D$5 -> 5 | Y10: 1 | Z10: =AVERAGE($AA$9:AA10) -> 0.9316 | AA10: 0.9751 | AB10: 12-1368
A11: =Headcount!A12 -> 4 | B11: =$C$5 -> 5000 | C11: =$C$9-D10 -> 65000 | D11: =D10+$C$5 -> 15000 | E11: =IF(E10=0,0,E10+F11) -> 17485 | F11: =G11+H11+I11 -> 5583 | G11: 5583 | H11: 0 | I11: 0 | J11: =L11+M11+N11+O11+P11 -> 81 | K11: =IF(J11=0,0,J11/(J11+F11)) -> 0.014300847 | L11: 74 | M11: 0 | N11: 0 | O11: 7 | P11: 0 | Q11: 10 | R11: 166 | S11: 0 | T11: 7 | U11: 12-1323 MA 17 db 1201-1294 MA 13 db | V11: =[1]Munka3!$G7 -> 0 | W11: =8*2 -> 16 | X11: =$D$5 -> 5 | Y11: 1 | Z11: =AVERAGE($AA$9:AA11) -> 0.96383333 | AA11: 1.0283
A12: =Headcount!A13 -> 5 | B12: =$C$5 -> 5000 | C12: =$C$9-D11 -> 60000 | D12: =D11+$C$5 -> 20000 | E12: =IF(E11=0,0,E11+F12) -> 22823 | F12: =G12+H12+I12 -> 5338 | G12: 5338 | H12: 0 | I12: 0 | J12: =L12+M12+N12+O12+P12 -> 112 | K12: =IF(J12=0,0,J12/(J12+F12)) -> 0.020550459 | L12: 103 | M12: 0 | N12: 0 | O12: 9 | P12: 0 | Q12: 8 | R12: 138 | S12: 0 | T12: 19 | U12: 12-1368 J 23 db / SK 22 db / E 12 db / NK 14 db | V12: =[1]Munka3!$G8 -> 0 | W12: =8*2 -> 16 | X12: =$D$5 -> 5 | Y12: 1 | Z12: =AVERAGE($AA$9:AA12) -> 0.970575 | AA12: 0.9908 | AB12: 12-1368 88%
A13: =Headcount!A14 -> 6 | B13: =$C$5 -> 5000 | C13: =$C$9-D12 -> 55000 | D13: =D12+$C$5 -> 25000 | E13: =IF(E12=0,0,E12+F13) -> 29179 | F13: =G13+H13+I13 -> 6356 | G13: 6356 | H13: 0 | I13: 0 | J13: =L13+M13+N13+O13+P13 -> 85 | K13: =IF(J13=0,0,J13/(J13+F13)) -> 0.013196709 | L13: 85 | M13: 0 | N13: 0 | O13: 0 | P13: 0 | Q13: 15 | R13: 207 | S13: 0 | T13: 50 | U13: 12-1368 NK 45 db / J 34 db / E 10 db | V13: =[1]Munka3!$G9 -> 0 | W13: =8*2 -> 16 | X13: =$D$5 -> 5 | Y13: 1 | Z13: =AVERAGE($AA$9:AA13) -> 1.02584 | AA13: 1.2469
A14: =Headcount!A15 -> 9 | B14: =$C$5 -> 5000 | C14: =$C$9-D13 -> 50000 | D14: =D13+$C$5 -> 30000 | E14: =IF(E13=0,0,E13+F14) -> 34464 | F14: =G14+H14+I14 -> 5285 | G14: 5285 | H14: 0 | I14: 0 | J14: =L14+M14+N14+O14+P14 -> 97 | K14: =IF(J14=0,0,J14/(J14+F14)) -> 0.01802304 | L14: 75 | M14: 0 | N14: 0 | O14: 22 | P14: 0 | Q14: 13 | R14: 93 | S14: 0 | T14: 9 | U14: 12-1217 BS 7 db (kis db szám mellé) 12-1337 BS 15 db 12-1413 E 14 db | V14: =[1]Munka3!$G10 -> 0 | W14: =8*2 -> 16 | X14: =$D$5 -> 5 | Y14: 1 | Z14: =AVERAGE($AA$9:AA14) -> 1.0111333 | AA14: 0.9376 | AB14: 12-1217 44% (kis db szám 160 db)
A15: =Headcount!A16 -> 10 | B15: =$C$5 -> 5000 | C15: =$C$9-D14 -> 45000 | D15: =D14+$C$5 -> 35000 | E15: =IF(E14=0,0,E14+F15) -> 42376 | F15: =G15+H15+I15 -> 7912 | G15: 7912 | H15: 0 | I15: 0 | J15: =L15+M15+N15+O15+P15 -> 44 | K15: =IF(J15=0,0,J15/(J15+F15)) -> 0.0055304173 | L15: 31 | M15: 0 | N15: 0 | O15: 13 | P15: 0 | Q15: 12 | R15: 344 | S15: 0 | T15: 12 | U15: 12-1233 BS 13 db | V15: =[1]Munka3!$G11 -> 0 | W15: =8*2 -> 16 | X15: =$D$5 -> 5 | Y15: 1 | Z15: =AVERAGE($AA$9:AA15) -> 1.0186714 | AA15: 1.0639
A16: =Headcount!A17 -> 11 | B16: =$C$5 -> 5000 | C16: =$C$9-D15 -> 40000 | D16: =D15+$C$5 -> 40000 | E16: =IF(E15=0,0,E15+F16) -> 50128 | F16: =G16+H16+I16 -> 7752 | G16: 7752 | H16: 0 | I16: 0 | J16: =L16+M16+N16+O16+P16 -> 57 | K16: =IF(J16=0,0,J16/(J16+F16)) -> 0.0072992701 | L16: 57 | M16: 0 | N16: 0 | O16: 0 | P16: 0 | Q16: 51 | R16: 121 | S16: 0 | T16: 18 | U16: 12-1233 E 16 db | V16: =[1]Munka3!$G12 -> 0 | W16: =8*2 -> 16 | X16: =$D$5 -> 5 | Y16: 1 | Z16: =AVERAGE($AA$9:AA16) -> 1.014775 | AA16: 0.9875
A17: =Headcount!A18 -> 12 | B17: =$C$5 -> 5000 | C17: =$C$9-D16 -> 35000 | D17: =D16+$C$5 -> 45000 | E17: =IF(E16=0,0,E16+F17) -> 55914 | F17: =G17+H17+I17 -> 5786 | G17: 5786 | H17: 0 | I17: 0 | J17: =L17+M17+N17+O17+P17 -> 48 | K17: =IF(J17=0,0,J17/(J17+F17)) -> 0.0082276311 | L17: 45 | M17: 0 | N17: 0 | O17: 3 | P17: 0 | Q17: 153 | R17: 18 | S17: 0 | T17: 9 | U17: - | V17: =[1]Munka3!$G13 -> 0 | W17: =8*2 -> 16 | X17: =$D$5 -> 5 | Y17: 1 | Z17: =AVERAGE($AA$9:AA17) -> 1.0108222 | AA17: 0.9792
A18: =Headcount!A19 -> 13 | B18: =$C$5 -> 5000 | C18: =$C$9-D17 -> 30000 | D18: =D17+$C$5 -> 50000 | E18: =IF(E17=0,0,E17+F18) -> 62286 | F18: =G18+H18+I18 -> 6372 | G18: 6372 | H18: 0 | I18: 0 | J18: =L18+M18+N18+O18+P18 -> 82 | K18: =IF(J18=0,0,J18/(J18+F18)) -> 0.012705299 | L18: 61 | M18: 0 | N18: 0 | O18: 21 | P18: 0 | Q18: 142 | R18: 29 | S18: 0 | T18: 17 | U18: - | V18: =[1]Munka3!$G14 -> 0 | W18: =8*2 -> 16 | X18: =$D$5 -> 5 | Y18: 1 | Z18: =AVERAGE($AA$9:AA18) -> 1.00679 | AA18: 0.9705
A19: =Headcount!A20 -> 16 | B19: =$C$5 -> 5000 | C19: =$C$9-D18 -> 25000 | D19: =D18+$C$5 -> 55000 | E19: =IF(E18=0,0,E18+F19) -> 64007 | F19: =G19+H19+I19 -> 1721 | G19: 1721 | H19: 0 | I19: 0 | J19: =L19+M19+N19+O19+P19 -> 19 | K19: =IF(J19=0,0,J19/(J19+F19)) -> 0.01091954 | L19: 19 | M19: 0 | N19: 0 | O19: 0 | P19: 0 | Q19: 19 | R19: 29 | S19: 0 | T19: 3 | U19: - | V19: =[1]Munka3!$G15 -> 0 | W19: =8*2 -> 16 | X19: =$D$5 -> 5 | Y19: 1 | Z19: =AVERAGE($AA$9:AA19) -> 1.0057545 | AA19: 0.9954
A20: =Headcount!A21 -> 17 | B20: =$C$5 -> 5000 | C20: =$C$9-D19 -> 20000 | D20: =D19+$C$5 -> 60000 | E20: =IF(E19=0,0,E19+F20) -> 64008 | F20: =G20+H20+I20 -> 1 | G20: 1 | H20: 0 | I20: 0 | J20: =L20+M20+N20+O20+P20 -> 0 | K20: =IF(J20=0,0,J20/(J20+F20)) -> 0 | L20: 0 | M20: 0 | N20: 0 | O20: 0 | P20: 0 | Q20: 0 | R20: 0 | S20: 0 | T20: 0 | U20: - | V20: =[1]Munka3!$G16 -> 0 | W20: =8*2 -> 16 | X20: =$D$5 -> 5 | Y20: 1 | Z20: =AVERAGE($AA$9:AA20) -> 1.0057545 | AA20: -
A21: =Headcount!A22 -> 18 | B21: =$C$5 -> 5000 | C21: =$C$9-D20 -> 15000 | D21: =D20+$C$5 -> 65000 | E21: =IF(E20=0,0,E20+F21) -> 69757 | F21: =G21+H21+I21 -> 5749 | G21: 5749 | H21: 0 | I21: 0 | J21: =L21+M21+N21+O21+P21 -> 73 | K21: =IF(J21=0,0,J21/(J21+F21)) -> 0.012538647 | L21: 55 | M21: 0 | N21: 0 | O21: 18 | P21: 0 | Q21: 56 | R21: 2 | S21: 0 | T21: 5 | U21: 1200-1367 BS 14 db / MA 20 db | V21: =[1]Munka3!$G17 -> 0 | W21: =8*2 -> 16 | X21: =$D$5 -> 5 | Y21: 1 | Z21: =AVERAGE($AA$9:AA21) -> 1.0098083 | AA21: 1.0544
A22: =Headcount!A23 -> 19 | B22: =$C$5 -> 5000 | C22: =$C$9-D21 -> 10000 | D22: =D21+$C$5 -> 70000 | E22: =IF(E21=0,0,E21+F22) -> 76238 | F22: =G22+H22+I22 -> 6481 | G22: 6481 | H22: 0 | I22: 0 | J22: =L22+M22+N22+O22+P22 -> 30 | K22: =IF(J22=0,0,J22/(J22+F22)) -> 0.0046075872 | L22: 24 | M22: 0 | N22: 0 | O22: 6 | P22: 0 | Q22: 199 | R22: 8 | S22: 0 | T22: 6 | U22: - | V22: =[1]Munka3!$G18 -> 0 | W22: 16 | X22: =$D$5 -> 5 | Y22: 1 | Z22: =AVERAGE($AA$9:AA22) -> 1.0073538 | AA22: 0.9779
A23: =Headcount!A24 -> 20 | B23: =$C$5 -> 5000 | C23: =$C$9-D22 -> 5000 | D23: =D22+$C$5 -> 75000 | E23: =IF(E22=0,0,E22+F23) -> 80910 | F23: =G23+H23+I23 -> 4672 | G23: 4672 | H23: 0 | I23: 0 | J23: =L23+M23+N23+O23+P23 -> 34 | K23: =IF(J23=0,0,J23/(J23+F23)) -> 0.0072248194 | L23: 27 | M23: 0 | N23: 0 | O23: 7 | P23: 0 | Q23: 7 | R23: 26 | S23: 0 | T23: 6 | U23: - | V23: =[1]Munka3!$G19 -> 0 | W23: 16 | X23: =$D$5 -> 5 | Y23: 1 | Z23: =AVERAGE($AA$9:AA23) -> 1.0032286 | AA23: 0.9496
A31: Summ line | D31: =C7*C5 -> 75000 | F31: =SUM(F9:F29) -> 80910 | L31: =SUM(L9:L30) -> 966 | M31: =SUM(M9:M30) -> 0 | N31: =SUM(N9:N30) -> 0 | O31: =SUM(O9:O30) -> 149 | P31: =SUM(P9:P30) -> 0 | Q31: =SUM(Q9:Q30) -> 710 | R31: =SUM(R9:R30) -> 1219 | S31: =SUM(S9:S30) -> 0 | T31: =SUM(T9:T30) -> 200
L33: Scrap with TO/AA | N33: =L31+M31+N31+O31+Q31+R31+T31+P31 -> 3244
L34: Scrap without TO/AA | N34: =L31+M31+N31+O31+T31 -> 1315

Sheet Auto Bending
A1: Auto | C1: Difference to the plan | G1: =E31-C31 -> 0
A2: Bend
B5: Daily plan | C5: 0 | E5: =D9/C9 -> #DIV/0!
B6: Workday | C6: =Headcount!F7 -> 15
B7: Actual day | C7: =Headcount!F8 -> 15 | E7: Out put daily good | I7: Reject
A8: Munkanap | B8: Hátralévő mennyiség | C8: Komulált terv | D8: Kimenet (Komulált) | E8: Total | F8: Shift 1 | G8: Shift 2 | H8: Shift 3 | I8: Total (QTY) | J8: Total (Ratio) | K8: Shift 1 (Qty) | L8: Shift 2 (Qty) | M8: Shift 3 (Qty) | N8: High reject item code / reject code | O8: Efficiency
A9: =Headcount!A10 -> 2 | B9: =C5*C6 -> 0 | C9: =C5 -> 0 | D9: =E9 -> 0 | E9: =F9+G9+H9 -> 0 | G9: 0 | H9: 0 | I9: =K9+L9+M9 -> 0 | J9: =IF(I9=0,0,I9/(I9+E9)) -> 0 | L9: 0 | M9: 0
A10: =Headcount!A11 -> 3 | B10: =B9-$C$5 -> 0 | C10: =C9+$C$5 -> 0 | D10: =IF(E10=0,0,D9+E10) -> 0 | E10: =F10+G10+H10 -> 0 | G10: 0 | H10: 0 | I10: =K10+L10+M10 -> 0 | J10: =IF(I10=0,0,I10/(I10+E10)) -> 0 | L10: 0 | M10: 0
A11: =Headcount!A12 -> 4 | B11: =B10-$C$5 -> 0 | C11: =C10+$C$5 -> 0 | E11: =F11+G11+H11 -> 0 | G11: 0 | H11: 0 | I11: =K11+L11+M11 -> 0 | J11: =IF(I11=0,0,I11/(I11+E11)) -> 0 | L11: 0 | M11: 0
A12: =Headcount!A13 -> 5 | B12: =B11-$C$5 -> 0 | C12: =C11+$C$5 -> 0 | E12: =F12+G12+H12 -> 0 | G12: 0 | H12: 0 | I12: =K12+L12+M12 -> 0 | J12: =IF(I12=0,0,I12/(I12+E12)) -> 0 | L12: 0 | M12: 0
A13: =Headcount!A14 -> 6 | B13: =B12-$C$5 -> 0 | C13: =C12+$C$5 -> 0 | E13: =F13+G13+H13 -> 0 | G13: 0 | H13: 0 | I13: =K13+L13+M13 -> 0 | J13: =IF(I13=0,0,I13/(I13+E13)) -> 0 | L13: 0 | M13: 0
A14: =Headcount!A15 -> 9 | B14: =B13-$C$5 -> 0 | C14: =C13+$C$5 -> 0 | E14: =F14+G14+H14 -> 0 | G14: 0 | H14: 0 | I14: =K14+L14+M14 -> 0 | J14: 0 | L14: 0 | M14: 0
A15: =Headcount!A16 -> 10 | B15: =B14-$C$5 -> 0 | C15: =C14+$C$5 -> 0 | E15: =F15+G15+H15 -> 0 | G15: 0 | H15: 0 | I15: =K15+L15+M15 -> 0 | J15: =IF(I15=0,0,I15/(I15+E15)) -> 0 | L15: 0 | M15: 0
A16: =Headcount!A17 -> 11 | B16: =B15-$C$5 -> 0 | C16: =C15+$C$5 -> 0 | E16: =F16+G16+H16 -> 0 | G16: 0 | H16: 0 | I16: =K16+L16+M16 -> 0 | J16: =IF(I16=0,0,I16/(I16+E16)) -> 0 | L16: 0 | M16: 0
A17: =Headcount!A18 -> 12 | B17: =B16-$C$5 -> 0 | C17: =C16+$C$5 -> 0 | E17: =F17+G17+H17 -> 0 | G17: 0 | H17: 0 | I17: =K17+L17+M17 -> 0 | J17: =IF(I17=0,0,I17/(I17+E17)) -> 0 | L17: 0 | M17: 0
A18: =Headcount!A19 -> 13 | B18: =B17-$C$5 -> 0 | C18: =C17+$C$5 -> 0 | E18: =F18+G18+H18 -> 0 | G18: 0 | H18: 0 | I18: =K18+L18+M18 -> 0 | J18: =IF(I18=0,0,I18/(I18+E18)) -> 0 | L18: 0 | M18: 0
A19: =Headcount!A20 -> 16 | B19: =B18-$C$5 -> 0 | C19: =C18+$C$5 -> 0 | E19: =F19+G19+H19 -> 0 | G19: 0 | H19: 0 | I19: =K19+L19+M19 -> 0 | J19: =IF(I19=0,0,I19/(I19+E19)) -> 0 | L19: 0 | M19: 0
A20: =Headcount!A21 -> 17 | B20: =B19-$C$5 -> 0 | C20: =C19+$C$5 -> 0 | E20: =F20+G20+H20 -> 0 | G20: 0 | H20: 0 | I20: =K20+L20+M20 -> 0 | J20: =IF(I20=0,0,I20/(I20+E20)) -> 0 | L20: 0 | M20: 0
A21: =Headcount!A22 -> 18 | B21: =B20-$C$5 -> 0 | C21: =C20+$C$5 -> 0 | E21: =F21+G21+H21 -> 0 | G21: 0 | H21: 0 | I21: =K21+L21+M21 -> 0 | J21: =IF(I21=0,0,I21/(I21+E21)) -> 0 | L21: 0 | M21: 0
A22: =Headcount!A23 -> 19 | B22: =B21-$C$5 -> 0 | C22: =C21+$C$5 -> 0 | E22: =F22+G22+H22 -> 0 | G22: 0 | H22: 0 | I22: =K22+L22+M22 -> 0 | J22: =IF(I22=0,0,I22/(I22+E22)) -> 0 | L22: 0 | M22: 0
A23: =Headcount!A24 -> 20 | B23: =B22-$C$5 -> 0 | C23: =C22+$C$5 -> 0 | E23: =F23+G23+H23 -> 0 | G23: 0 | H23: 0 | I23: =K23+L23+M23 -> 0 | J23: =IF(I23=0,0,I23/(I23+E23)) -> 0 | L23: 0 | M23: 0
A24: =Headcount!A25 -> 0 | B24: =B23-$C$5 -> 0 | C24: =C23+$C$5 -> 0 | E24: =F24+G24+H24 -> 0 | G24: 0 | H24: 0 | I24: =K24+L24+M24 -> 0 | J24: =IF(I24=0,0,I24/(I24+E24)) -> 0 | L24: 0 | M24: 0
A25: =Headcount!A26 -> 0 | B25: =B24-$C$5 -> 0 | C25: =C24+$C$5 -> 0 | E25: =F25+G25+H25 -> 0 | G25: 0 | H25: 0 | I25: =K25+L25+M25 -> 0 | J25: =IF(I25=0,0,I25/(I25+E25)) -> 0 | L25: 0 | M25: 0
A26: =Headcount!A27 -> 0 | B26: =B25-$C$5 -> 0 | C26: =C25+$C$5 -> 0 | E26: =F26+G26+H26 -> 0 | G26: 0 | H26: 0 | I26: =K26+L26+M26 -> 0 | J26: =IF(I26=0,0,I26/(I26+E26)) -> 0 | L26: 0 | M26: 0
... A28: =Headcount!A29 -> 0 | B28: =B27-$C$5 -> 0 | C28: =C27+$C$5 -> 0 | E28: =F28+G28+H28 -> 0 | G28: 0 | H28: 0 | I28: =K28+L28+M28 -> 0 | J28: =IF(I28=0,0,I28/(I28+E28)) -> 0 | L28: 0 | M28: 0
A31: Summ line | C31: =C7*C5 -> 0 | E31: =SUM(E9:E29) -> 0 | K31: =SUM(K9:K30) -> 0 | L31: =SUM(L9:L30) -> 0 | M31: =SUM(M9:M30) -> 0 | N31: =SUM(K31:M31) -> 0

Sheet SS Auto Bending
A1: SS Auto | D1: Difference to the plan | H1: =F32-D32 -> 54.05
A2: Bend
M4: =C9/2000*8 -> 24.7998
C5: Daily plan | D5: 413.33 | E5: =D5/(2000/8) -> 1.65332 | F5: =E23/D23 -> 1.0087178 | M5: =1*D6*8 -> 120 | N5: =M4/M5 -> 0.206665
C6: Workday | D6: =Headcount!F7 -> 15
C7: Actual day | D7: =Headcount!F8 -> 15 | F7: Out put daily good | J7: Reject
A8: Munkanap | B8: Napi terv / Daily plan | C8: Hátralévő mennyiség | D8: Komulált terv | E8: Kimenet (Komulált) | F8: Total | G8: Shift 1 | H8: Shift 2 | I8: Shift 3 | J8: Total (QTY) | K8: Total (Ratio) | L8: Shift 1 (Qty) | M8: Shift 2 (Qty) | N8: Shift 3 (Qty) | O8: High reject item code / reject code | P8: Operating hours | Q8: Operation hours target | R8: Daily opeation hours plan target | S8: Cél / Target | T8: Hatékonyság (kumulált) / Efficiency (cumulative) | U8: Efficiency
A9: =Headcount!A10 -> 2 | B9: =$D$5 -> 413.33 | C9: =D5*D6 -> 6199.95 | D9: =D5 -> 413.33 | E9: =F9 -> 1 | F9: =G9+H9+I9 -> 1 | G9: 1 | H9: 0 | I9: 0 | J9: =L9+M9+N9 -> 0 | K9: =IF(J9=0,0,J9/(J9+F9)) -> 0 | L9: 0 | M9: 0 | N9: 0 | P9: =[1]Munka3!$H5 -> 0 | Q9: 8 | R9: =$E$5 -> 1.65332 | S9: 1 | T9: =AVERAGE(U$9:$U9) -> #DIV/0! | U9: -
A10: =Headcount!A11 -> 3 | B10: =$D$5 -> 413.33 | C10: =C9-$D$5 -> 5786.62 | D10: =D9+$D$5 -> 826.66 | E10: =IF(F10=0,0,E9+F10) -> 2 | F10: =G10+H10+I10 -> 1 | G10: 1 | H10: 0 | I10: 0 | J10: =L10+M10+N10 -> 0 | K10: =IF(J10=0,0,J10/(J10+F10)) -> 0 | L10: 0 | M10: 0 | N10: 0 | P10: =[1]Munka3!$H6 -> 0 | Q10: 8 | R10: =$E$5 -> 1.65332 | S10: 1 | T10: =AVERAGE(U$9:$U10) -> #DIV/0! | U10: -
A11: =Headcount!A12 -> 4 | B11: =$D$5 -> 413.33 | C11: =C10-$D$5 -> 5373.29 | D11: =D10+$D$5 -> 1239.99 | E11: =IF(F11=0,0,E10+F11) -> 15 | F11: =G11+H11+I11 -> 13 | G11: 13 | H11: 0 | I11: 0 | J11: =L11+M11+N11 -> 9 | K11: =IF(J11=0,0,J11/(J11+F11)) -> 0.40909091 | L11: 9 | M11: 0 | N11: 0 | O11: Program készítésből adódó selejt. | P11: =[1]Munka3!$H7 -> 0 | Q11: 8 | R11: =$E$5 -> 1.65332 | S11: 1 | T11: =AVERAGE(U$9:$U11) -> 1.0737 | U11: 1.0737
A12: =Headcount!A13 -> 5 | B12: =$D$5 -> 413.33 | C12: =C11-$D$5 -> 4959.96 | D12: =D11+$D$5 -> 1653.32 | E12: =IF(F12=0,0,E11+F12) -> 1237 | F12: =G12+H12+I12 -> 1222 | G12: 1222 | H12: 0 | I12: 0 | J12: =L12+M12+N12 -> 2 | K12: =IF(J12=0,0,J12/(J12+F12)) -> 0.0016339869 | L12: 2 | M12: 0 | N12: 0 | P12: =[1]Munka3!$H8 -> 0 | Q12: 8 | R12: =$E$5 -> 1.65332 | S12: 1 | T12: =AVERAGE(U$9:$U12) -> 1.07735 | U12: 1.081
A13: =Headcount!A14 -> 6 | B13: =$D$5 -> 413.33 | C13: =C12-$D$5 -> 4546.63 | D13: =D12+$D$5 -> 2066.65 | E13: =IF(F13=0,0,E12+F13) -> 2073 | F13: =G13+H13+I13 -> 836 | G13: 836 | H13: 0 | I13: 0 | J13: =L13+M13+N13 -> 13 | K13: =IF(J13=0,0,J13/(J13+F13)) -> 0.015312132 | L13: 13 | M13: 0 | N13: 0 | P13: =[1]Munka3!$H9 -> 0 | Q13: 8 | R13: =$E$5 -> 1.65332 | S13: 1 | T13: =AVERAGE(U$9:$U13) -> 1.0148 | U13: 0.8897
A14: =Headcount!A15 -> 9 | B14: =$D$5 -> 413.33 | C14: =C13-$D$5 -> 4133.3 | D14: =D13+$D$5 -> 2479.98 | E14: =IF(F14=0,0,E13+F14) -> 3583 | F14: =G14+H14+I14 -> 1510 | G14: 1510 | H14: 0 | I14: 0 | J14: =L14+M14+N14 -> 16 | K14: =IF(J14=0,0,J14/(J14+F14)) -> 0.010484928 | L14: 16 | M14: 0 | N14: 0 | P14: =[1]Munka3!$H10 -> 0 | Q14: 8 | R14: =$E$5 -> 1.65332 | S14: 1 | T14: =AVERAGE(U$9:$U14) -> 0.9654 | U14: 0.8172
A15: =Headcount!A16 -> 10 | B15: =$D$5 -> 413.33 | C15: =C14-$D$5 -> 3719.97 | D15: =D14+$D$5 -> 2893.31 | E15: =IF(F15=0,0,E14+F15) -> 4948 | F15: =G15+H15+I15 -> 1365 | G15: 1365 | H15: 0 | I15: 0 | J15: =L15+M15+N15 -> 7 | K15: =IF(J15=0,0,J15/(J15+F15)) -> 0.0051020408 | L15: 7 | M15: 0 | N15: 0 | P15: =[1]Munka3!$H11 -> 0 | Q15: 8 | R15: =$E$5 -> 1.65332 | S15: 1 | T15: =AVERAGE(U$9:$U15) -> 0.9319 | U15: 0.7979
A16: =Headcount!A17 -> 11 | B16: =$D$5 -> 413.33 | C16: =C15-$D$5 -> 3306.64 | D16: =D15+$D$5 -> 3306.64 | E16: =IF(F16=0,0,E15+F16) -> 5017 | F16: =G16+H16+I16 -> 69 | G16: 69 | H16: 0 | I16: 0 | J16: =L16+M16+N16 -> 0 | K16: =IF(J16=0,0,J16/(J16+F16)) -> 0 | L16: 0 | M16: 0 | N16: 0 | P16: =[1]Munka3!$H12 -> 0 | Q16: 8 | R16: =$E$5 -> 1.65332 | S16: 1 | T16: =AVERAGE(U$9:$U16) -> 0.9319 | U16: -
A17: =Headcount!A18 -> 12 | B17: =$D$5 -> 413.33 | C17: =C16-$D$5 -> 2893.31 | D17: =D16+$D$5 -> 3719.97 | E17: =IF(F17=0,0,E16+F17) -> 5018 | F17: =G17+H17+I17 -> 1 | G17: 1 | H17: 0 | I17: 0 | J17: =L17+M17+N17 -> 0 | K17: =IF(J17=0,0,J17/(J17+F17)) -> 0 | L17: 0 | M17: 0 | N17: 0 | P17: =[1]Munka3!$H13 -> 0 | Q17: 8 | R17: =$E$5 -> 1.65332 | S17: 1 | T17: =AVERAGE(U$9:$U17) -> 0.9319 | U17: -
A18: =Headcount!A19 -> 13 | B18: =$D$5 -> 413.33 | C18: =C17-$D$5 -> 2479.98 | D18: =D17+$D$5 -> 4133.3 | E18: =IF(F18=0,0,E17+F18) -> 5019 | F18: =G18+H18+I18 -> 1 | G18: 1 | H18: 0 | I18: 0 | J18: =L18+M18+N18 -> 0 | K18: =IF(J18=0,0,J18/(J18+F18)) -> 0 | L18: 0 | M18: 0 | N18: 0 | P18: =[1]Munka3!$H14 -> 0 | Q18: 8 | R18: =$E$5 -> 1.65332 | S18: 1 | T18: =AVERAGE(U$9:$U18) -> 0.9319 | U18: -
A19: =Headcount!A20 -> 16 | B19: =$D$5 -> 413.33 | C19: =C18-$D$5 -> 2066.65 | D19: =D18+$D$5 -> 4546.63 | E19: =IF(F19=0,0,E18+F19) -> 5867 | F19: =G19+H19+I19 -> 848 | G19: 848 | H19: 0 | I19: 0 | J19: =L19+M19+N19 -> 7 | K19: =IF(J19=0,0,J19/(J19+F19)) -> 0.0081871345 | L19: 7 | M19: 0 | N19: 0 | P19: =[1]Munka3!$H15 -> 0 | Q19: 8 | R19: =$E$5 -> 1.65332 | S19: 1 | T19: =AVERAGE(U$9:$U19) -> 0.91306667 | U19: 0.8189
A20: =Headcount!A21 -> 17 | B20: =$D$5 -> 413.33 | C20: =C19-$D$5 -> 1653.32 | D20: =D19+$D$5 -> 4959.96 | E20: =IF(F20=0,0,E19+F20) -> 6251 | F20: =G20+H20+I20 -> 384 | G20: 384 | H20: 0 | I20: 0 | J20: =L20+M20+N20 -> 0 | K20: =IF(J20=0,0,J20/(J20+F20)) -> 0 | L20: 0 | M20: 0 | N20: 0 | P20: =[1]Munka3!$H16 -> 0 | Q20: 8 | R20: =$E$5 -> 1.65332 | S20: 1 | T20: =AVERAGE(U$9:$U20) -> 0.93731429 | U20: 1.0828
A21: =Headcount!A22 -> 18 | B21: =$D$5 -> 413.33 | C21: =C20-$D$5 -> 1239.99 | D21: =D20+$D$5 -> 5373.29 | E21: =IF(F21=0,0,E20+F21) -> 6252 | F21: =G21+H21+I21 -> 1 | G21: 1 | H21: 0 | I21: 0 | J21: =L21+M21+N21 -> 0 | K21: =IF(J21=0,0,J21/(J21+F21)) -> 0 | L21: 0 | M21: 0 | N21: 0 | P21: =[1]Munka3!$H17 -> 0 | Q21: 8 | R21: =$E$5 -> 1.65332 | S21: 1 | T21: =AVERAGE(U$9:$U21) -> 0.93731429 | U21: -
A22: =Headcount!A23 -> 19 | B22: =$D$5 -> 413.33 | C22: =C21-$D$5 -> 826.66 | D22: =D21+$D$5 -> 5786.62 | E22: =IF(F22=0,0,E21+F22) -> 6253 | F22: =G22+H22+I22 -> 1 | G22: 1 | H22: 0 | I22: 0 | J22: =L22+M22+N22 -> 0 | K22: =IF(J22=0,0,J22/(J22+F22)) -> 0 | L22: 0 | M22: 0 | N22: 0 | P22: =[1]Munka3!$H18 -> 0 | Q22: 8 | R22: =$E$5 -> 1.65332 | S22: 1 | T22: =AVERAGE(U$9:$U22) -> 0.93731429 | U22: -
A23: =Headcount!A24 -> 20 | B23: =$D$5 -> 413.33 | C23: =C22-$D$5 -> 413.33 | D23: =D22+$D$5 -> 6199.95 | E23: =IF(F23=0,0,E22+F23) -> 6254 | F23: =G23+H23+I23 -> 1 | G23: 1 | H23: 0 | I23: 0 | J23: =L23+M23+N23 -> 0 | K23: =IF(J23=0,0,J23/(J23+F23)) -> 0 | L23: 0 | M23: 0 | N23: 0 | P23: =[1]Munka3!$H19 -> 0 | Q23: 8 | R23: =$E$5 -> 1.65332 | S23: 1 | T23: =AVERAGE(U$9:$U23) -> 0.93731429 | U23: -
A32: Summ line | D32: =D7*D5 -> 6199.95 | F32: =SUM(F9:F31) -> 6254 | L32: =SUM(L9:L31) -> 54 | M32: =SUM(M9:M31) -> 0 | N32: =SUM(N9:N31) -> 0 | O32: =SUM(L32:N32) -> 54 | U32: =AVERAGE(U9:U31) -> 0.93731429

Sheet APIM
A1: APIM | D1: Difference to the plan | H1: =F31-D31 -> 108 | J1: Items transfer from coil in-jet to APIM
D3: Mennyiség/ Quantity | E3: Óra/ Hours | F3: Gépszám
F4: 2 | L4: =C9/2200*8 -> 48
C5: Daily plan | D5: 880 | E5: =D5/(2000*F4/8) -> 1.76 | F5: =E21/D21 -> 1.1631119 | L5: =2*D6*8 -> 240 | M5: =L4/L5 -> 0.2
C6: Workday | D6: =Headcount!F7 -> 15
C7: Actual day | D7: =Headcount!F8 -> 15 | F7: Out put daily good | J7: Reject
A8: Munkanap / Workdays | B8: Napi terv / Daily plan | C8: Hátralévő mennyiség | D8: Kumulált terv / Cumulative plan | E8: Kimenet (Kumulált) / Output (cumulative) | F8: Teljes kimenet / Total output | G8: Shift 1 | H8: Shift 2 | I8: Shift 3 | J8: Total (QTY) | K8: Total (Ratio) | L8: Shift 1 (Qty) | M8: Shift 2 (Qty) | N8: Shift 3 (Qty) | O8: Operating hours | P8: Operation hours target | Q8: Daily opeation hours plan target | R8: Cél / Target | S8: Hatékonyság (kumulált) / Efficiency (cumulative) | T8: Hatékonyság / Efficiency
A9: =Headcount!A10 -> 2 | B9: =$D$5 -> 880 | C9: =D5*D6 -> 13200 | D9: =D5 -> 880 | E9: =F9 -> 1 | F9: =G9+H9+I9 -> 1 | G9: 1 | H9: 0 | I9: 0 | J9: =L9+M9+N9 -> 0 | K9: =IF(J9=0,0,J9/(J9+F9)) -> 0 | L9: 0 | M9: 0 | N9: 0 | O9: =[1]Munka3!$D5 -> 6 | P9: =8*2 -> 16 | Q9: =$E$5 -> 1.76 | R9: 1 | S9: =AVERAGE($T$9:T9) -> #DIV/0! | T9: -
A10: =Headcount!A11 -> 3 | B10: =$D$5 -> 880 | C10: =$C$9-D9 -> 12320 | D10: =D9+$D$5 -> 1760 | E10: =IF(E9=0,0,E9+F10) -> 2 | F10: =G10+H10+I10 -> 1 | G10: 1 | H10: 0 | I10: 0 | J10: =L10+M10+N10 -> 0 | K10: =IF(J10=0,0,J10/(J10+F10)) -> 0 | L10: 0 | M10: 0 | N10: 0 | O10: =[1]Munka3!$D6 -> 0 | P10: =8*2 -> 16 | Q10: =$E$5 -> 1.76 | R10: 1 | S10: =AVERAGE($T$9:T10) -> #DIV/0! | T10: -
A11: =Headcount!A12 -> 4 | B11: =$D$5 -> 880 | C11: =$C$9-D10 -> 11440 | D11: =D10+$D$5 -> 2640 | E11: =IF(E10=0,0,E10+F11) -> 1782 | F11: =G11+H11+I11 -> 1780 | G11: 1780 | H11: 0 | I11: 0 | J11: =L11+M11+N11 -> 2 | K11: =IF(J11=0,0,J11/(J11+F11)) -> 0.0011223345 | L11: 2 | M11: 0 | N11: 0 | O11: =[1]Munka3!$D7 -> 0 | P11: =8*2 -> 16 | Q11: =$E$5 -> 1.76 | R11: 1 | S11: =AVERAGE($T$9:T11) -> 0.6688 | T11: 0.6688
A12: =Headcount!A13 -> 5 | B12: =$D$5 -> 880 | C12: =$C$9-D11 -> 10560 | D12: =D11+$D$5 -> 3520 | E12: =IF(E11=0,0,E11+F12) -> 5327 | F12: =G12+H12+I12 -> 3545 | G12: 3545 | H12: 0 | I12: 0 | J12: =L12+M12+N12 -> 3 | K12: =IF(J12=0,0,J12/(J12+F12)) -> 0.00084554679 | L12: 3 | M12: 0 | N12: 0 | O12: =[1]Munka3!$D8 -> 0 | P12: =8*2 -> 16 | Q12: =$E$5 -> 1.76 | R12: 1 | S12: =AVERAGE($T$9:T12) -> 0.79195 | T12: 0.9151
A13: =Headcount!A14 -> 6 | B13: =$D$5 -> 880 | C13: =$C$9-D12 -> 9680 | D13: =D12+$D$5 -> 4400 | E13: =IF(E12=0,0,E12+F13) -> 8624 | F13: =G13+H13+I13 -> 3297 | G13: 3297 | H13: 0 | I13: 0 | J13: =L13+M13+N13 -> 2 | K13: =IF(J13=0,0,J13/(J13+F13)) -> 0.00060624432 | L13: 2 | M13: 0 | N13: 0 | O13: =[1]Munka3!$D9 -> 0 | P13: =8*2 -> 16 | Q13: =$E$5 -> 1.76 | R13: 1 | S13: =AVERAGE($T$9:T13) -> 0.85243333 | T13: 0.9734
A14: =Headcount!A15 -> 9 | B14: =$D$5 -> 880 | C14: =$C$9-D13 -> 8800 | D14: =D13+$D$5 -> 5280 | E14: =IF(E13=0,0,E13+F14) -> 12101 | F14: =G14+H14+I14 -> 3477 | G14: 3477 | H14: 0 | I14: 0 | J14: =L14+M14+N14 -> 4 | K14: =IF(J14=0,0,J14/(J14+F14)) -> 0.0011490951 | L14: 4 | M14: 0 | N14: 0 | O14: =[1]Munka3!$D10 -> 0 | P14: =8*2 -> 16 | Q14: =$E$5 -> 1.76 | R14: 1 | S14: =AVERAGE($T$9:T14) -> 0.863975 | T14: 0.8986
A15: =Headcount!A16 -> 10 | B15: =$D$5 -> 880 | C15: =$C$9-D14 -> 7920 | D15: =D14+$D$5 -> 6160 | E15: =IF(E14=0,0,E14+F15) -> 12102 | F15: =G15+H15+I15 -> 1 | G15: 1 | H15: 0 | I15: 0 | J15: =L15+M15+N15 -> 0 | K15: =IF(J15=0,0,J15/(J15+F15)) -> 0 | L15: 0 | M15: 0 | N15: 0 | O15: =[1]Munka3!$D11 -> 0 | P15: =8*2 -> 16 | Q15: =$E$5 -> 1.76 | R15: 1 | S15: =AVERAGE($T$9:T15) -> 0.863975 | T15: -
A16: =Headcount!A17 -> 11 | B16: =$D$5 -> 880 | C16: =$C$9-D15 -> 7040 | D16: =D15+$D$5 -> 7040 | E16: =IF(E15=0,0,E15+F16) -> 12103 | F16: =G16+H16+I16 -> 1 | G16: 1 | H16: 0 | I16: 0 | J16: =L16+M16+N16 -> 0 | K16: =IF(J16=0,0,J16/(J16+F16)) -> 0 | L16: 0 | M16: 0 | N16: 0 | O16: =[1]Munka3!$D12 -> 0 | P16: =8*2 -> 16 | Q16: =$E$5 -> 1.76 | R16: 1 | S16: =AVERAGE($T$9:T16) -> 0.863975 | T16: -
A17: =Headcount!A18 -> 12 | B17: =$D$5 -> 880 | C17: =$C$9-D16 -> 6160 | D17: =D16+$D$5 -> 7920 | E17: =IF(E16=0,0,E16+F17) -> 12104 | F17: =G17+H17+I17 -> 1 | G17: 1 | H17: 0 | I17: 0 | J17: =L17+M17+N17 -> 0 | K17: =IF(J17=0,0,J17/(J17+F17)) -> 0 | L17: 0 | M17: 0 | N17: 0 | O17: =[1]Munka3!$D13 -> 0 | P17: =8*2 -> 16 | Q17: =$E$5 -> 1.76 | R17: 1 | S17: =AVERAGE($T$9:T17) -> 0.863975 | T17: -
A18: =Headcount!A19 -> 13 | B18: =$D$5 -> 880 | C18: =$C$9-D17 -> 5280 | D18: =D17+$D$5 -> 8800 | E18: =IF(E17=0,0,E17+F18) -> 12704 | F18: =G18+H18+I18 -> 600 | G18: 600 | H18: 0 | I18: 0 | J18: =L18+M18+N18 -> 1 | K18: =IF(J18=0,0,J18/(J18+F18)) -> 0.0016638935 | L18: 1 | M18: 0 | N18: 0 | O18: =[1]Munka3!$D14 -> 0 | P18: =8*2 -> 16 | Q18: =$E$5 -> 1.76 | R18: 1 | S18: =AVERAGE($T$9:T18) -> 0.88936 | T18: 0.9909
A19: =Headcount!A20 -> 16 | B19: =$D$5 -> 880 | C19: =$C$9-D18 -> 4400 | D19: =D18+$D$5 -> 9680 | E19: =IF(E18=0,0,E18+F19) -> 13304 | F19: =G19+H19+I19 -> 600 | G19: 600 | H19: 0 | I19: 0 | J19: =L19+M19+N19 -> 1 | K19: =IF(J19=0,0,J19/(J19+F19)) -> 0.0016638935 | L19: 1 | M19: 0 | N19: 0 | O19: =[1]Munka3!$D15 -> 0 | P19: =8*2 -> 16 | Q19: =$E$5 -> 1.76 | R19: 1 | S19: =AVERAGE($T$9:T19) -> 0.86958333 | T19: 0.7707
A20: =Headcount!A21 -> 17 | B20: =$D$5 -> 880 | C20: =$C$9-D19 -> 3520 | D20: =D19+$D$5 -> 10560 | E20: =IF(E19=0,0,E19+F20) -> 13305 | F20: =G20+H20+I20 -> 1 | G20: 1 | H20: 0 | I20: 0 | J20: =L20+M20+N20 -> 0 | K20: =IF(J20=0,0,J20/(J20+F20)) -> 0 | L20: 0 | M20: 0 | N20: 0 | O20: =[1]Munka3!$D16 -> 0 | P20: =8*2 -> 16 | Q20: =$E$5 -> 1.76 | R20: 1 | S20: =AVERAGE($T$9:T20) -> 0.86958333 | T20: -
A21: =Headcount!A22 -> 18 | B21: =$D$5 -> 880 | C21: =$C$9-D20 -> 2640 | D21: =D20+$D$5 -> 11440 | E21: =IF(E20=0,0,E20+F21) -> 13306 | F21: =G21+H21+I21 -> 1 | G21: 1 | H21: 0 | I21: 0 | J21: =L21+M21+N21 -> 0 | K21: =IF(J21=0,0,J21/(J21+F21)) -> 0 | L21: 0 | M21: 0 | N21: 0 | O21: =[1]Munka3!$D17 -> 0 | P21: =8*2 -> 16 | Q21: =$E$5 -> 1.76 | R21: 1 | S21: =AVERAGE($T$9:T21) -> 0.86958333 | T21: -
A22: =Headcount!A23 -> 19 | B22: =$D$5 -> 880 | C22: =$C$9-D21 -> 1760 | D22: =D21+$D$5 -> 12320 | E22: =IF(E21=0,0,E21+F22) -> 13307 | F22: =G22+H22+I22 -> 1 | G22: 1 | H22: 0 | I22: 0 | J22: =L22+M22+N22 -> 0 | K22: =IF(J22=0,0,J22/(J22+F22)) -> 0 | L22: 0 | M22: 0 | N22: 0 | O22: =[1]Munka3!$D18 -> 0 | P22: 16 | Q22: =$E$5 -> 1.76 | R22: 1 | S22: =AVERAGE($T$9:T22) -> 0.86958333 | T22: -
A23: =Headcount!A24 -> 20 | B23: =$D$5 -> 880 | C23: =$C$9-D22 -> 880 | D23: =D22+$D$5 -> 13200 | E23: =IF(E22=0,0,E22+F23) -> 13308 | F23: =G23+H23+I23 -> 1 | G23: 1 | H23: 0 | I23: 0 | J23: =L23+M23+N23 -> 0 | K23: =IF(J23=0,0,J23/(J23+F23)) -> 0 | L23: 0 | M23: 0 | N23: 0 | O23: =[1]Munka3!$D19 -> 0 | P23: 16 | Q23: =$E$5 -> 1.76 | R23: 1 | S23: =AVERAGE($T$9:T23) -> 0.86958333 | T23: -
A31: Summ line | D31: =D5*D7 -> 13200 | F31: =SUM(F9:F29) -> 13308 | L31: =SUM(L9:L30) -> 13 | M31: =SUM(M9:M30) -> 0 | N31: =SUM(N9:N30) -> 0

Sheet Visual Inspection
A1: Visual Inspection | C1: Difference to the plan | G1: =E31-C31 -> 16
B5: Daily plan | C5: 1200 | E5: =D23/C23 -> 1.0008889
B6: Workdays | C6: =Headcount!F7 -> 15
B7: Actual day | C7: =Headcount!F8 -> 15 | E7: Out put daily good | I7: Reject
A8: Munkanap | B8: Hátralévő mennyiség | C8: Komulált terv | D8: Kimenet (Komulált) | E8: Total | F8: Shift 1 | G8: Shift 2 | H8: Shift 3 | I8: Total (QTY) | J8: Total (Ratio) | K8: Shift 1 (Qty) | L8: AA hiba (HA ,F, KÉK, Stb...) Beszállítóval fizettetni! | M8: High reject item code / reject code
A9: =Headcount!A10 -> 2 | B9: =C5*C6 -> 18000 | C9: =C5 -> 1200 | D9: =E9 -> 1 | E9: =F9+G9+H9 -> 1 | F9: 1 | G9: 0 | H9: 0 | I9: =K9+L9 -> 0 | J9: =IF(I9=0,0,I9/(I9+E9)) -> 0 | K9: 0 | L9: 0 | M9: -
A10: =Headcount!A11 -> 3 | B10: =$B$9-C9 -> 16800 | C10: =$C$5+C9 -> 2400 | D10: =IF(E10=0,0,D9+E10) -> 5134 | E10: =F10+G10+H10 -> 5133 | F10: 5133 | G10: 0 | H10: 0 | I10: =K10+L10 -> 7 | J10: =IF(I10=0,0,I10/(I10+E10)) -> 0.0013618677 | K10: 1 | L10: 6 | M10: 1201-1294 Korr. 5 db / Szig.rf. 1 db / SK 1 db
A11: =Headcount!A12 -> 4 | B11: =$B$9-C10 -> 15600 | C11: =$C$5+C10 -> 3600 | D11: =IF(E11=0,0,D10+E11) -> 7453 | E11: =F11+G11+H11 -> 2319 | F11: 2319 | G11: 0 | H11: 0 | I11: =K11+L11 -> 15 | J11: =IF(I11=0,0,I11/(I11+E11)) -> 0.0064267352 | K11: 15 | L11: 0 | M11: 1200-1283 SK 15 db
A12: =Headcount!A13 -> 5 | B12: =$B$9-C11 -> 14400 | C12: =$C$5+C11 -> 4800 | D12: =IF(E12=0,0,D11+E12) -> 9304 | E12: =F12+G12+H12 -> 1851 | F12: 1851 | G12: 0 | H12: 0 | I12: =K12+L12 -> 19 | J12: =IF(I12=0,0,I12/(I12+E12)) -> 0.010160428 | K12: 18 | L12: 1 | M12: 2701-0328 JSZ 3 db / J 1 db / R 3 db / SZ 5 db / SK 6 db / Besz. Fólia 1 db
A13: =Headcount!A14 -> 6 | B13: =$B$9-C12 -> 13200 | C13: =$C$5+C12 -> 6000 | D13: =IF(E13=0,0,D12+E13) -> 10715 | E13: =F13+G13+H13 -> 1411 | F13: 1411 | G13: 0 | H13: 0 | I13: =K13+L13 -> 26 | J13: =IF(I13=0,0,I13/(I13+E13)) -> 0.01809325 | K13: 18 | L13: 8 | M13: 1201-1294 Besz. Támszalag 8 db / SK 2 db / SZ 6 db 2701-0328 R 10 db
A14: =Headcount!A15 -> 9 | B14: =$B$9-C13 -> 12000 | C14: =$C$5+C13 -> 7200 | D14: =IF(E14=0,0,D13+E14) -> 10716 | E14: =F14+G14+H14 -> 1 | F14: 1 | G14: 0 | H14: 0 | I14: =K14+L14 -> 0 | J14: =IF(I14=0,0,I14/(I14+E14)) -> 0 | K14: 0 | L14: 0 | M14: -
A15: =Headcount!A16 -> 10 | B15: =$B$9-C14 -> 10800 | C15: =$C$5+C14 -> 8400 | D15: =IF(E15=0,0,D14+E15) -> 11833 | E15: =F15+G15+H15 -> 1117 | F15: 1117 | G15: 0 | H15: 0 | I15: =K15+L15 -> 2 | J15: =IF(I15=0,0,I15/(I15+E15)) -> 0.0017873101 | K15: 2 | L15: 0 | M15: 1200-1337 SK 2 db
A16: =Headcount!A17 -> 11 | B16: =$B$9-C15 -> 9600 | C16: =$C$5+C15 -> 9600 | D16: =IF(E16=0,0,D15+E16) -> 15848 | E16: =F16+G16+H16 -> 4015 | F16: 4015 | G16: 0 | H16: 0 | I16: =K16+L16 -> 11 | J16: =IF(I16=0,0,I16/(I16+E16)) -> 0.0027322404 | K16: 11 | L16: 0 | M16: 1200-1337 SK 9 db/ SZ2 db
A17: =Headcount!A18 -> 12 | B17: =$B$9-C16 -> 8400 | C17: =$C$5+C16 -> 10800 | D17: =IF(E17=0,0,D16+E17) -> 16035 | E17: =F17+G17+H17 -> 187 | F17: 187 | G17: 0 | H17: 0 | I17: =K17+L17 -> 0 | J17: =IF(I17=0,0,I17/(I17+E17)) -> 0 | K17: 0 | L17: 0 | M17: -
A18: =Headcount!A19 -> 13 | B18: =$B$9-C17 -> 7200 | C18: =$C$5+C17 -> 12000 | D18: =IF(E18=0,0,D17+E18) -> 16036 | E18: =F18+G18+H18 -> 1 | F18: 1 | G18: 0 | H18: 0 | I18: =K18+L18 -> 0 | J18: =IF(I18=0,0,I18/(I18+E18)) -> 0 | K18: 0 | L18: 0 | M18: -
A19: =Headcount!A20 -> 16 | B19: =$B$9-C18 -> 6000 | C19: =$C$5+C18 -> 13200 | D19: =IF(E19=0,0,D18+E19) -> 17420 | E19: =F19+G19+H19 -> 1384 | F19: 1384 | G19: 0 | H19: 0 | I19: =K19+L19 -> 1 | J19: =IF(I19=0,0,I19/(I19+E19)) -> 0.00072202166 | K19: 1 | L19: 0 | M19: 2701-0328 H 1 db
A20: =Headcount!A21 -> 17 | B20: =$B$9-C19 -> 4800 | C20: =$C$5+C19 -> 14400 | D20: =IF(E20=0,0,D19+E20) -> 18013 | E20: =F20+G20+H20 -> 593 | F20: 593 | G20: 0 | H20: 0 | I20: =K20+L20 -> 1 | J20: =IF(I20=0,0,I20/(I20+E20)) -> 0.0016835017 | K20: 0 | L20: 1 | M20: 2701-0328 Beszállítói fólia 1 db
A21: =Headcount!A22 -> 18 | B21: =$B$9-C20 -> 3600 | C21: =$C$5+C20 -> 15600 | D21: =IF(E21=0,0,D20+E21) -> 18014 | E21: =F21+G21+H21 -> 1 | F21: 1 | G21: 0 | H21: 0 | I21: =K21+L21 -> 0 | J21: =IF(I21=0,0,I21/(I21+E21)) -> 0 | K21: 0 | L21: 0 | M21: -
... A23: =Headcount!A24 -> 20 | B23: =$B$9-C22 -> 1200 | C23: =$C$5+C22 -> 18000 | D23: =IF(E23=0,0,D22+E23) -> 18016 | E23: =F23+G23+H23 -> 1 | F23: 1 | G23: 0 | H23: 0 | I23: =K23+L23 -> 0 | J23: =IF(I23=0,0,I23/(I23+E23)) -> 0 | K23: 0 | L23: 0 | M23: -
A31: Summ Line | C31: =C7*C5 -> 18000 | E31: =SUM(E9:E29) -> 18016 | K31: =SUM(K9:K30) -> 66 | L31: =SUM(L9:L30) -> 16 | M31: =SUM(K31:K31) -> 66
I33: Scrap with HA/F/RR | K33: =L31+K31 -> 82
I34: Scrap without HA/F/RR | K34: =K31 -> 66

Sheet USB
A1: USB | C1: Difference to the plan | G1: =E31-C31 -> 8363.5 | I1: Gyártási 3%-nál kielemzés a selejt fajtáiból!
B5: Daily plan | C5: 8062.5 | E5: =D24/C24 -> 1.0023333
B6: Workdays | C6: =Headcount!F7 -> 15
B7: Actual day | C7: =Headcount!F8 -> 15 | E7: Out put daily good | I7: Reject
A8: Munkanap | B8: Hátralévő mennyiség | C8: Komulált terv | D8: Kimenet (Komulált) | E8: Total | F8: Shift 1 | G8: Shift 2 | H8: Shift 3 | I8: Total (QTY) | J8: Total (Ratio) | K8: Shift 1 (Qty) | L8: Shift 2 (Qty) | M8: Shift 3 (Qty) | N8: AA hiba (HA ,F, Stb..) Beszállítóval fizettetni! | O8: High reject item code / reject code
A9: =Headcount!A10 -> 2 | B9: =C5*C6 -> 120937.5 | C9: =C5 -> 8062.5 | D9: =E9 -> 1232 | E9: =F9+G9+H9 -> 1232 | F9: 1232 | G9: 0 | H9: 0 | I9: =K9+L9+M9+N9 -> 0 | J9: =IF(I9=0,0,I9/(I9+E9)) -> 0 | K9: 0 | L9: 0 | M9: 0 | N9: 0 | O9: -
A10: =Headcount!A11 -> 3 | B10: =$B$9-C9 -> 112875 | C10: =$C$5+C9 -> 16125 | D10: =IF(E10=0,0,D9+E10) -> 1233 | E10: =F10+G10+H10 -> 1 | F10: 1 | G10: 0 | H10: 0 | I10: =K10+L10+M10+N10 -> 0 | J10: =IF(I10=0,0,I10/(I10+E10)) -> 0 | K10: 0 | L10: 0 | M10: 0 | N10: 0 | O10: -
A11: =Headcount!A12 -> 4 | B11: =$B$9-C10 -> 104812.5 | C11: =$C$5+C10 -> 24187.5 | D11: =IF(E11=0,0,D10+E11) -> 1234 | E11: =F11+G11+H11 -> 1 | F11: 1 | G11: 0 | H11: 0 | I11: =K11+L11+M11+N11 -> 0 | J11: =IF(I11=0,0,I11/(I11+E11)) -> 0 | K11: 0 | L11: 0 | M11: 0 | N11: 0 | O11: -
A12: =Headcount!A13 -> 5 | B12: =$B$9-C11 -> 96750 | C12: =$C$5+C11 -> 32250 | D12: =IF(E12=0,0,D11+E12) -> 1235 | E12: =F12+G12+H12 -> 1 | F12: 1 | G12: 0 | H12: 0 | I12: =K12+L12+M12+N12 -> 0 | J12: =IF(I12=0,0,I12/(I12+E12)) -> 0 | K12: 0 | L12: 0 | M12: 0 | N12: 0 | O12: -
A13: =Headcount!A14 -> 6 | B13: =$B$9-C12 -> 88687.5 | C13: =$C$5+C12 -> 40312.5 | D13: =IF(E13=0,0,D12+E13) -> 3620 | E13: =F13+G13+H13 -> 2385 | F13: 2385 | G13: 0 | H13: 0 | I13: =K13+L13+M13+N13 -> 18 | J13: =IF(I13=0,0,I13/(I13+E13)) -> 0.0074906367 | K13: 10 | L13: 0 | M13: 0 | N13: 8 | O13: 1201-1221 18 db E 8 db (Korr. 3 db / Besz. SZ 5 db) SK 5 db / J 1 db / JSZ 4 db
A14: =Headcount!A15 -> 9 | B14: =$B$9-C13 -> 80625 | C14: =$C$5+C13 -> 48375 | D14: =IF(E14=0,0,D13+E14) -> 3621 | E14: =F14+G14+H14 -> 1 | F14: 1 | G14: 0 | H14: 0 | I14: =K14+L14+M14+N14 -> 0 | J14: =IF(I14=0,0,I14/(I14+E14)) -> 0 | K14: 0 | L14: 0 | M14: 0 | N14: 0 | O14: -
A15: =Headcount!A16 -> 10 | B15: =$B$9-C14 -> 72562.5 | C15: =$C$5+C14 -> 56437.5 | D15: =IF(E15=0,0,D14+E15) -> 3622 | E15: =F15+G15+H15 -> 1 | F15: 1 | G15: 0 | H15: 0 | I15: =K15+L15+M15+N15 -> 0 | J15: =IF(I15=0,0,I15/(I15+E15)) -> 0 | K15: 0 | L15: 0 | M15: 0 | N15: 0 | O15: -
A16: =Headcount!A17 -> 11 | B16: =$B$9-C15 -> 64500 | C16: =$C$5+C15 -> 64500 | D16: =IF(E16=0,0,D15+E16) -> 9992 | E16: =F16+G16+H16 -> 6370 | F16: 6370 | G16: 0 | H16: 0 | I16: =K16+L16+M16+N16 -> 50 | J16: =IF(I16=0,0,I16/(I16+E16)) -> 0.007788162 | K16: 50 | L16: 0 | M16: 0 | N16: 0 | O16: Átellenőrzés: 2701-0429 SZ 9 db / SK 15 db 2701-0430 SZ 12 db / SK 14 db
A17: =Headcount!A18 -> 12 | B17: =$B$9-C16 -> 56437.5 | C17: =$C$5+C16 -> 72562.5 | D17: =IF(E17=0,0,D16+E17) -> 14897 | E17: =F17+G17+H17 -> 4905 | F17: 4905 | G17: 0 | H17: 0 | I17: =K17+L17+M17+N17 -> 23 | J17: =IF(I17=0,0,I17/(I17+E17)) -> 0.0046672078 | K17: 22 | L17: 0 | M17: 0 | N17: 1 | O17: 2701-0374 23 db E 1 db (Korr. 1 db) SK 1 db / SZ 20 db / R 1 db Átellenőrzés: 2701-0430 SZ 1 db / SK 15 db
A18: =Headcount!A19 -> 13 | B18: =$B$9-C17 -> 48375 | C18: =$C$5+C17 -> 80625 | D18: =IF(E18=0,0,D17+E18) -> 30845 | E18: =F18+G18+H18 -> 15948 | F18: 7930 | G18: 8018 | H18: 0 | I18: =K18+L18+M18+N18 -> 138 | J18: =IF(I18=0,0,I18/(I18+E18)) -> 0.0085788885 | K18: 108 | L18: 28 | M18: 0 | N18: 2 | O18: Átellenőrzés: 2701-0429 SZ 15 db / SK 49 db 2701-0430 SZ 11 db / SK 45 db 2701-0374 18 db E 2 db (Besz. SZ 2 db) SK 8 db / SZ 8 db
A19: 14 | B19: =$B$9-C18 -> 40312.5 | C19: =$C$5+C18 -> 88687.5 | D19: =IF(E19=0,0,D18+E19) -> 46189 | E19: =F19+G19+H19 -> 15344 | F19: 7510 | G19: 7834 | H19: 0 | I19: =K19+L19+M19+N19 -> 155 | J19: =IF(I19=0,0,I19/(I19+E19)) -> 0.010000645 | K19: 97 | L19: 58 | M19: 0 | N19: 0 | O19: Átellenőrzés: 2701-0429 SZ 19 db / SK 38 db 2701-0430 SZ 21 db / SK 66 db
A20: 16 | B20: =$B$9-C19 -> 32250 | C20: =$C$5+C19 -> 96750 | D20: =IF(E20=0,0,D19+E20) -> 67026 | E20: =F20+G20+H20 -> 20837 | F20: 11207 | G20: 9630 | H20: 0 | I20: =K20+L20+M20+N20 -> 154 | J20: =IF(I20=0,0,I20/(I20+E20)) -> 0.0073364775 | K20: 95 | L20: 54 | M20: 0 | N20: 5 | O20: Rendes gyártásból: 2701-0430 SK 55 db / SZ 3 db 2701-0429 SK 38 db / SZ 13 db 2701-0374 29 db E 5 db (SR 1 db / Besz. SZ 4 db) SK 5 db / R 12 db / J 2 db / SZ 5 db Átellenőrzésből: 2701-0430 SK 14 db / SZ 3 db
A21: 17 | B21: =$B$9-C20 -> 24187.5 | C21: =$C$5+C20 -> 104812.5 | D21: =IF(E21=0,0,D20+E21) -> 87516 | E21: =F21+G21+H21 -> 20490 | F21: 11543 | G21: 8947 | H21: 0 | I21: =K21+L21+M21+N21 -> 110 | J21: =IF(I21=0,0,I21/(I21+E21)) -> 0.0053398058 | K21: 52 | L21: 56 | M21: 0 | N21: 2 | O21: Rendes gyártásból: 1201-1221 6 db SK 5 db / SZ 1 db 2701-0374 51 db E 2 db (SR 1 db / Besz. SZ 1 db) SK 8 db / SZ 11 db / J 8 db / R 22 db / 2701-0430 SK 3 db Átellenőrzésből: 2701-0429 SK 15 db / SZ 7 db 2701-0430 SK 18 db / SZ 4 db 2701-0431 SK 3 db / SZ 1 db 2701-0432 SK 3 db
A22: 18 | B22: =$B$9-C21 -> 16125 | C22: =$C$5+C21 -> 112875 | D22: =IF(E22=0,0,D21+E22) -> 107112 | E22: =F22+G22+H22 -> 19596 | F22: 11497 | G22: 8099 | H22: 0 | I22: =K22+L22+M22+N22 -> 66 | J22: =IF(I22=0,0,I22/(I22+E22)) -> 0.0033567287 | K22: 28 | L22: 37 | M22: 0 | N22: 1 | O22: Rendes gyártásból: 2701-0374 5 db E 1 db (Korr. 1 db) SK 1 db / R 1 db / J 2 db 1201-1221 8 db SK 7 db / J 1 db Átellenőrzésből: 2701-0429 SK 11 db 2701-0430 SK 9 db / SZ 3 db 2701-0431 SK 16 db / SZ 1 db 2701-0432 SK 13 db
A23: 19 | B23: =$B$9-C22 -> 8062.5 | C23: =$C$5+C22 -> 120937.5 | D23: =IF(E23=0,0,D22+E23) -> 126029 | E23: =F23+G23+H23 -> 18917 | F23: 10801 | G23: 8116 | H23: 0 | I23: =K23+L23+M23+N23 -> 57 | J23: =IF(I23=0,0,I23/(I23+E23)) -> 0.0030041109 | K23: 48 | L23: 9 | M23: 0 | N23: 0 | O23: Átellenőrzésből: 2701-0430 SK 22 db 2701-0431 SK 18 db / SZ 1 db 2701-0429 SK 12 db / SZ 1 db Rendes gyártásból: 2701-0432 SK 6 db
A24: 20 | B24: =$B$9-C23 -> 0 | C24: =$C$5+C23 -> 129000 | D24: =IF(E24=0,0,D23+E24) -> 129301 | E24: =F24+G24+H24 -> 3272 | F24: 3272 | G24: 0 | H24: 0 | I24: =K24+L24+M24+N24 -> 8 | J24: =IF(I24=0,0,I24/(I24+E24)) -> 0.0024390244 | K24: 8 | L24: 0 | M24: 0 | N24: 0 | O24: Átellenőrzésből: 2701-0430 SK 7 db / SZ 1 db
A31: Summ line | C31: =C7*C5 -> 120937.5 | E31: =SUM(E9:E29) -> 129301 | K31: =SUM(K9:K30) -> 518 | L31: =SUM(L9:L30) -> 242 | M31: =SUM(M9:M30) -> 0 | N31: =SUM(N9:N30) -> 19 | P31: =SUM(P9:P30) -> 0
I33: Scrap with HA/F/RR | K33: =K31+L31+M31+N31 -> 779
I34: Scrap without HA/F/RR/JSZ | K34: =K31+L31+M31 -> 760

Sheet Conti Final Insp
A1: Conti Final Insp. | C1: Difference to the plan | G1: =E31-C31 -> 269
B5: Daily plan | C5: 1133 | E5: =D23/C23 -> 1.0158282
B6: Workdays | C6: =Headcount!F7 -> 15
B7: Actual day | C7: =Headcount!F8 -> 15 | E7: Out put daily good | I7: Reject
A8: Munkanap | B8: Hátralévő mennyiség | C8: Komulált terv | D8: Kimenet (Komulált) | E8: Total | F8: Shift 1 | G8: Shift 2 | H8: Shift 3 | I8: Total (QTY) | J8: Total (Ratio) | K8: Shift 1 (Qty) | L8: AA hiba (HA ,F, KÉK, Stb...) Beszállítóval fizettetni! | M8: High reject item code / reject code
A9: =Headcount!A10 -> 2 | B9: =C5*C6 -> 16995 | C9: =C5 -> 1133 | D9: =E9 -> 1 | E9: =F9+G9+H9 -> 1 | F9: 1 | G9: 0 | H9: 0 | I9: =K9+L9 -> 0 | J9: =IF(I9=0,0,I9/(I9+E9)) -> 0 | K9: 0 | L9: 0 | M9: -
A10: =Headcount!A11 -> 3 | B10: =$B$9-C9 -> 15862 | C10: =$C$5+C9 -> 2266 | D10: =IF(E10=0,0,D9+E10) -> 2 | E10: =F10+G10+H10 -> 1 | F10: 1 | G10: 0 | H10: 0 | I10: =K10+L10 -> 0 | J10: =IF(I10=0,0,I10/(I10+E10)) -> 0 | K10: 0 | L10: 0 | M10: -
A11: =Headcount!A12 -> 4 | B11: =$B$9-C10 -> 14729 | C11: =$C$5+C10 -> 3399 | D11: =IF(E11=0,0,D10+E11) -> 3931 | E11: =F11+G11+H11 -> 3929 | F11: 3929 | G11: 0 | H11: 0 | I11: =K11+L11 -> 15 | J11: =IF(I11=0,0,I11/(I11+E11)) -> 0.0038032454 | K11: 15 | L11: 0 | M11: 1200-1368 SK 15 db
A12: =Headcount!A13 -> 5 | B12: =$B$9-C11 -> 13596 | C12: =$C$5+C11 -> 4532 | D12: =IF(E12=0,0,D11+E12) -> 5877 | E12: =F12+G12+H12 -> 1946 | F12: 1946 | G12: 0 | H12: 0 | I12: =K12+L12 -> 7 | J12: =IF(I12=0,0,I12/(I12+E12)) -> 0.0035842294 | K12: 7 | L12: 0 | M12: 1200-1368 SK 7 db
A13: =Headcount!A14 -> 6 | B13: =$B$9-C12 -> 12463 | C13: =$C$5+C12 -> 5665 | D13: =IF(E13=0,0,D12+E13) -> 5878 | E13: =F13+G13+H13 -> 1 | F13: 1 | G13: 0 | H13: 0 | I13: =K13+L13 -> 0 | J13: =IF(I13=0,0,I13/(I13+E13)) -> 0 | K13: 0 | L13: 0 | M13: -
A14: =Headcount!A15 -> 9 | B14: =$B$9-C13 -> 11330 | C14: =$C$5+C13 -> 6798 | D14: =IF(E14=0,0,D13+E14) -> 10120 | E14: =F14+G14+H14 -> 4242 | F14: 4242 | G14: 0 | H14: 0 | I14: =K14+L14 -> 48 | J14: =IF(I14=0,0,I14/(I14+E14)) -> 0.011188811 | K14: 48 | L14: 0 | M14: 1200-1368 SK 48 db
A15: =Headcount!A16 -> 10 | B15: =$B$9-C14 -> 10197 | C15: =$C$5+C14 -> 7931 | D15: =IF(E15=0,0,D14+E15) -> 13731 | E15: =F15+G15+H15 -> 3611 | F15: 3611 | G15: 0 | H15: 0 | I15: =K15+L15 -> 50 | J15: =IF(I15=0,0,I15/(I15+E15)) -> 0.013657471 | K15: 50 | L15: 0 | M15: 1200-1368 SK 47 db / SZ 3 db | N15: Ádámnak átadva 1368 SK
A16: =Headcount!A17 -> 11 | B16: =$B$9-C15 -> 9064 | C16: =$C$5+C15 -> 9064 | D16: =IF(E16=0,0,D15+E16) -> 13732 | E16: =F16+G16+H16 -> 1 | F16: 1 | G16: 0 | H16: 0 | I16: =K16+L16 -> 0 | J16: =IF(I16=0,0,I16/(I16+E16)) -> 0 | K16: 0 | L16: 0 | M16: -
A17: =Headcount!A18 -> 12 | B17: =$B$9-C16 -> 7931 | C17: =$C$5+C16 -> 10197 | D17: =IF(E17=0,0,D16+E17) -> 14732 | E17: =F17+G17+H17 -> 1000 | F17: 1000 | G17: 0 | H17: 0 | I17: =K17+L17 -> 0 | J17: =IF(I17=0,0,I17/(I17+E17)) -> 0 | K17: 0 | L17: 0 | M17: -
A18: =Headcount!A19 -> 13 | B18: =$B$9-C17 -> 6798 | C18: =$C$5+C17 -> 11330 | D18: =IF(E18=0,0,D17+E18) -> 17259 | E18: =F18+G18+H18 -> 2527 | F18: 2527 | G18: 0 | H18: 0 | I18: =K18+L18 -> 1 | J18: =IF(I18=0,0,I18/(I18+E18)) -> 0.00039556962 | K18: 1 | L18: 0 | M18: 2700-0422 JSZ 1 db
A19: =Headcount!A20 -> 16 | B19: =$B$9-C18 -> 5665 | C19: =$C$5+C18 -> 12463 | D19: =IF(E19=0,0,D18+E19) -> 17260 | E19: =F19+G19+H19 -> 1 | F19: 1 | G19: 0 | H19: 0 | I19: =K19+L19 -> 0 | J19: =IF(I19=0,0,I19/(I19+E19)) -> 0 | K19: 0 | L19: 0 | M19: -
A20: =Headcount!A21 -> 17 | B20: =$B$9-C19 -> 4532 | C20: =$C$5+C19 -> 13596 | D20: =IF(E20=0,0,D19+E20) -> 17261 | E20: =F20+G20+H20 -> 1 | F20: 1 | G20: 0 | H20: 0 | I20: =K20+L20 -> 0 | J20: =IF(I20=0,0,I20/(I20+E20)) -> 0 | K20: 0 | L20: 0 | M20: -
A21: =Headcount!A22 -> 18 | B21: =$B$9-C20 -> 3399 | C21: =$C$5+C20 -> 14729 | D21: =IF(E21=0,0,D20+E21) -> 17262 | E21: =F21+G21+H21 -> 1 | F21: 1 | G21: 0 | H21: 0 | I21: =K21+L21 -> 0 | J21: =IF(I21=0,0,I21/(I21+E21)) -> 0 | K21: 0 | L21: 0 | M21: -
A22: =Headcount!A23 -> 19 | B22: =$B$9-C21 -> 2266 | C22: =$C$5+C21 -> 15862 | D22: =IF(E22=0,0,D21+E22) -> 17263 | E22: =F22+G22+H22 -> 1 | F22: 1 | G22: 0 | H22: 0 | I22: =K22+L22 -> 0 | J22: =IF(I22=0,0,I22/(I22+E22)) -> 0 | K22: 0 | L22: 0 | M22: -
A23: =Headcount!A24 -> 20 | B23: =$B$9-C22 -> 1133 | C23: =$C$5+C22 -> 16995 | D23: =IF(E23=0,0,D22+E23) -> 17264 | E23: =F23+G23+H23 -> 1 | F23: 1 | G23: 0 | H23: 0 | I23: =K23+L23 -> 0 | J23: =IF(I23=0,0,I23/(I23+E23)) -> 0 | K23: 0 | L23: 0 | M23: -
A31: Summ Line | C31: =C7*C5 -> 16995 | E31: =SUM(E9:E28) -> 17264 | K31: =SUM(K9:K30) -> 121 | L31: =SUM(L9:L30) -> 0 | M31: =SUM(K31:K31) -> 121
I33: Scrap with HA/F/RR | K33: =L31+K31 -> 121
I34: Scrap without HA/F/RR | K34: =K31 -> 121

Sheet Hot Stamp
A1: Hot Stamp | C1: Difference to the plan | G1: =E31-C31 -> 48.1
B5: Daily plan | C5: 166.66 | E5: =D23/C23 -> 1.0192408
B6: Workdays | C6: =Headcount!F7 -> 15
B7: Actual day | C7: =Headcount!F8 -> 15 | E7: Out put daily good | I7: Reject
A8: Munkanap | B8: Hátralévő mennyiség | C8: Komulált terv | D8: Kimenet (Komulált) | E8: Total | F8: Shift 1 | I8: Total (QTY) | J8: Total (Ratio) | K8: BS Scrap | L8: Manufactuirng Scrap | M8: High reject item code / reject code
A9: =Headcount!A10 -> 2 | B9: =C5*C6 -> 2499.9 | C9: =C5 -> 166.66 | D9: =E9 -> 1425 | E9: =F9 -> 1425 | F9: 1425 | I9: =L9 -> 0 | J9: =IF(I9=0,0,I9/(I9+E9)) -> 0 | K9: 0 | L9: 0
A10: =Headcount!A11 -> 3 | B10: =$B$9-C9 -> 2333.24 | C10: =$C$5+C9 -> 333.32 | D10: =IF(E10=0,0,D9+E10) -> 1426 | E10: =F10 -> 1 | F10: 1 | I10: =L10 -> 0 | J10: =IF(I10=0,0,I10/(I10+E10)) -> 0 | K10: 0 | L10: 0
A11: =Headcount!A12 -> 4 | B11: =$B$9-C10 -> 2166.58 | C11: =$C$5+C10 -> 499.98 | D11: =IF(E11=0,0,D10+E11) -> 1427 | E11: =F11 -> 1 | F11: 1 | I11: =L11 -> 0 | J11: =IF(I11=0,0,I11/(I11+E11)) -> 0 | K11: 0 | L11: 0
A12: =Headcount!A13 -> 5 | B12: =$B$9-C11 -> 1999.92 | C12: =$C$5+C11 -> 666.64 | D12: =IF(E12=0,0,D11+E12) -> 2537 | E12: =F12 -> 1110 | F12: 1110 | I12: =L12 -> 0 | J12: =IF(I12=0,0,I12/(I12+E12)) -> 0 | K12: 0 | L12: 0
A13: =Headcount!A14 -> 6 | B13: =$B$9-C12 -> 1833.26 | C13: =$C$5+C12 -> 833.3 | D13: =IF(E13=0,0,D12+E13) -> 2538 | E13: =F13 -> 1 | F13: 1 | I13: =L13 -> 0 | J13: =IF(I13=0,0,I13/(I13+E13)) -> 0 | K13: 0 | L13: 0
A14: =Headcount!A15 -> 9 | B14: =$B$9-C13 -> 1666.6 | C14: =$C$5+C13 -> 999.96 | D14: =IF(E14=0,0,D13+E14) -> 2539 | E14: =F14 -> 1 | F14: 1 | I14: =L14 -> 0 | J14: =IF(I14=0,0,I14/(I14+E14)) -> 0 | K14: 0 | L14: 0
A15: =Headcount!A16 -> 10 | B15: =$B$9-C14 -> 1499.94 | C15: =$C$5+C14 -> 1166.62 | D15: =IF(E15=0,0,D14+E15) -> 2540 | E15: =F15 -> 1 | F15: 1 | I15: =L15 -> 0 | J15: =IF(I15=0,0,I15/(I15+E15)) -> 0 | K15: 0 | L15: 0
A16: =Headcount!A17 -> 11 | B16: =$B$9-C15 -> 1333.28 | C16: =$C$5+C15 -> 1333.28 | D16: =IF(E16=0,0,D15+E16) -> 2541 | E16: =F16 -> 1 | F16: 1 | I16: =L16 -> 0 | J16: =IF(I16=0,0,I16/(I16+E16)) -> 0 | K16: 0 | L16: 0
A17: =Headcount!A18 -> 12 | B17: =$B$9-C16 -> 1166.62 | C17: =$C$5+C16 -> 1499.94 | D17: =IF(E17=0,0,D16+E17) -> 2542 | E17: =F17 -> 1 | F17: 1 | I17: =L17 -> 0 | J17: =IF(I17=0,0,I17/(I17+E17)) -> 0 | K17: 0 | L17: 0
A18: =Headcount!A19 -> 13 | B18: =$B$9-C17 -> 999.96 | C18: =$C$5+C17 -> 1666.6 | D18: =IF(E18=0,0,D17+E18) -> 2543 | E18: =F18 -> 1 | F18: 1 | I18: =L18 -> 0 | J18: =IF(I18=0,0,I18/(I18+E18)) -> 0 | K18: 0 | L18: 0
A19: =Headcount!A20 -> 16 | B19: =$B$9-C18 -> 833.3 | C19: =$C$5+C18 -> 1833.26 | D19: =IF(E19=0,0,D18+E19) -> 2544 | E19: =F19 -> 1 | F19: 1 | I19: 0 | J19: =IF(I19=0,0,I19/(I19+E19)) -> 0 | K19: 0 | L19: 0
A20: =Headcount!A21 -> 17 | B20: =$B$9-C19 -> 666.64 | C20: =$C$5+C19 -> 1999.92 | D20: =IF(E20=0,0,D19+E20) -> 2545 | E20: =F20 -> 1 | F20: 1 | I20: =L20 -> 0 | J20: =IF(I20=0,0,I20/(I20+E20)) -> 0 | K20: 0 | L20: 0
A21: =Headcount!A22 -> 18 | B21: =$B$9-C20 -> 499.98 | C21: =$C$5+C20 -> 2166.58 | D21: =IF(E21=0,0,D20+E21) -> 2546 | E21: =F21 -> 1 | F21: 1 | I21: =L21 -> 0 | J21: =IF(I21=0,0,I21/(I21+E21)) -> 0 | K21: 0 | L21: 0
A22: =Headcount!A23 -> 19 | B22: =$B$9-C21 -> 333.32 | C22: =$C$5+C21 -> 2333.24 | D22: =IF(E22=0,0,D21+E22) -> 2547 | E22: =F22 -> 1 | F22: 1 | I22: =L22 -> 0 | J22: =IF(I22=0,0,I22/(I22+E22)) -> 0 | K22: 0 | L22: 0
A23: =Headcount!A24 -> 20 | B23: =$B$9-C22 -> 166.66 | C23: =$C$5+C22 -> 2499.9 | D23: =IF(E23=0,0,D22+E23) -> 2548 | E23: =F23 -> 1 | F23: 1 | I23: =L23 -> 0 | J23: =IF(I23=0,0,I23/(I23+E23)) -> 0 | K23: 0 | L23: 0
I24: =L24 -> 0 | J24: =IF(I24=0,0,I24/(I24+E24)) -> 0
I25: =L25 -> 0 | J25: =IF(I25=0,0,I25/(I25+E25)) -> 0
I26: =L26 -> 0 | J26: =IF(I26=0,0,I26/(I26+E26)) -> 0
I27: =L27 -> 0 | J27: =IF(I27=0,0,I27/(I27+E27)) -> 0
I28: =L28 -> 0 | J28: =IF(I28=0,0,I28/(I28+E28)) -> 0
A31: Summ Line | C31: =C7*C5 -> 2499.9 | E31: =SUM(E9:E29) -> 2548 | K31: =SUM(K9:K30) -> 0 | L31: =SUM(L9:L30) -> 0 | M31: =SUM(K31:L31) -> 0

Sheet Shielding
A1: Shield | C1: Difference to the plan | G1: =E31-C31 -> 8 | I1: Recovery plan ( recovery ) recovery period must indicate green cells
B5: Daily plan | C5: 88 | E5: =D23/C23 -> 1.0060606
B6: Workday | C6: =Headcount!F7 -> 15
B7: Actual day | C7: =Headcount!F8 -> 15 | E7: Out put daily good | I7: Operator / day TTL
A8: Day | B8: Remain Qty | C8: Plan | D8: Output(Comulative) | E8: Total | F8: Shift 1 | G8: Shift 2 | H8: Shift 3 | I8: Op.Plan | J8: Op.Act | K8: Diff | L8: Qty/op | M8: Productivity (NAV) | N8: BS Scrap | O8: Manufacturing Scrap | P8: Difficult item's code
A9: =Headcount!A10 -> 2 | B9: =C5*C6 -> 1320 | C9: =C5 -> 88 | D9: =E9 -> 205 | E9: =F9+G9+H9 -> 205 | F9: 205 | G9: 0 | H9: 0 | M9: 1.0516 | N9: 1 | O9: 0
A10: =Headcount!A11 -> 3 | B10: =$B$9-C9 -> 1232 | C10: =C9+$C$5 -> 176 | D10: =IF(E10=0,0,D9+E10) -> 206 | E10: =F10+G10+H10 -> 1 | F10: 1 | G10: 0 | H10: 0 | M10: - | N10: 0 | O10: 0
A11: =Headcount!A12 -> 4 | B11: =$B$9-C10 -> 1144 | C11: =C10+$C$5 -> 264 | D11: =IF(E11=0,0,D10+E11) -> 207 | E11: =F11+G11+H11 -> 1 | F11: 1 | G11: 0 | H11: 0 | M11: - | N11: 0 | O11: 0
A12: =Headcount!A13 -> 5 | B12: =$B$9-C11 -> 1056 | C12: =C11+$C$5 -> 352 | D12: =IF(E12=0,0,D11+E12) -> 1317 | E12: =F12+G12+H12 -> 1110 | F12: 1110 | G12: 0 | H12: 0 | M12: 1.2986 | N12: 0 | O12: 0
A13: =Headcount!A14 -> 6 | B13: =$B$9-C12 -> 968 | C13: =C12+$C$5 -> 440 | D13: =IF(E13=0,0,D12+E13) -> 1318 | E13: =F13+G13+H13 -> 1 | F13: 1 | G13: 0 | H13: 0 | M13: - | N13: 0 | O13: 0
A14: =Headcount!A15 -> 9 | B14: =$B$9-C13 -> 880 | C14: =C13+$C$5 -> 528 | D14: =IF(E14=0,0,D13+E14) -> 1319 | E14: =F14+G14+H14 -> 1 | F14: 1 | G14: 0 | H14: 0 | M14: - | N14: 0 | O14: 0
A15: =Headcount!A16 -> 10 | B15: =$B$9-C14 -> 792 | C15: =C14+$C$5 -> 616 | D15: =IF(E15=0,0,D14+E15) -> 1320 | E15: =F15+G15+H15 -> 1 | F15: 1 | G15: 0 | H15: 0 | M15: - | N15: 0 | O15: 0
A16: =Headcount!A17 -> 11 | B16: =$B$9-C15 -> 704 | C16: =C15+$C$5 -> 704 | D16: =IF(E16=0,0,D15+E16) -> 1321 | E16: =F16+G16+H16 -> 1 | F16: 1 | G16: 0 | H16: 0 | M16: - | N16: 0 | O16: 0
A17: =Headcount!A18 -> 12 | B17: =$B$9-C16 -> 616 | C17: =C16+$C$5 -> 792 | D17: =IF(E17=0,0,D16+E17) -> 1322 | E17: =F17+G17+H17 -> 1 | F17: 1 | G17: 0 | H17: 0 | M17: - | N17: 0 | O17: 0
A18: =Headcount!A19 -> 13 | B18: =$B$9-C17 -> 528 | C18: =C17+$C$5 -> 880 | D18: =IF(E18=0,0,D17+E18) -> 1323 | E18: =F18+G18+H18 -> 1 | F18: 1 | G18: 0 | H18: 0 | M18: - | N18: 0 | O18: 0
A19: =Headcount!A20 -> 16 | B19: =$B$9-C18 -> 440 | C19: =C18+$C$5 -> 968 | D19: =IF(E19=0,0,D18+E19) -> 1324 | E19: =F19+G19+H19 -> 1 | F19: 1 | G19: 0 | H19: 0 | M19: - | N19: 0 | O19: 0
A20: =Headcount!A21 -> 17 | B20: =$B$9-C19 -> 352 | C20: =C19+$C$5 -> 1056 | D20: =IF(E20=0,0,D19+E20) -> 1325 | E20: =F20+G20+H20 -> 1 | F20: 1 | G20: 0 | H20: 0 | M20: - | N20: 0 | O20: 0
A21: =Headcount!A22 -> 18 | B21: =$B$9-C20 -> 264 | C21: =C20+$C$5 -> 1144 | D21: =IF(E21=0,0,D20+E21) -> 1326 | E21: =F21+G21+H21 -> 1 | F21: 1 | G21: 0 | H21: 0 | M21: - | N21: 0 | O21: 0
A22: =Headcount!A23 -> 19 | B22: =$B$9-C21 -> 176 | C22: =C21+$C$5 -> 1232 | D22: =IF(E22=0,0,D21+E22) -> 1327 | E22: =F22+G22+H22 -> 1 | F22: 1 | G22: 0 | H22: 0 | M22: - | N22: 0 | O22: 0
A23: =Headcount!A24 -> 20 | B23: =$B$9-C22 -> 88 | C23: =C22+$C$5 -> 1320 | D23: =IF(E23=0,0,D22+E23) -> 1328 | E23: =F23+G23+H23 -> 1 | F23: 1 | G23: 0 | H23: 0 | M23: - | N23: 0 | O23: 0
A31: Summ line | C31: =C7*C5 -> 1320 | E31: =SUM(E9:E29) -> 1328 | M31: =AVERAGE(M9:M30) -> 1.1751 | N31: =SUM(N9:N30) -> 1 | O31: =SUM(O9:O30) -> 0 | P31: =SUM(N31:O31) -> 1

Sheet Bending
A1: BEND | C1: Difference to the plan | G1: =E31-C31 -> 349.05
B5: Daily plan | C5: 3733.33 | E5: =D23/C23 -> 1.006233
B6: Workday | C6: =Headcount!F7 -> 15
B7: Actual day | C7: =Headcount!F8 -> 15 | I7: Operator / day TTL | O7: KFT operation
A8: Day | B8: Remain Qty | C8: Plan | D8: Output(Comulative) | E8: Total | F8: Output Daily | G8: Subcon out | H8: Incoming from MV | I8: Op.Plan | J8: Op.Act | K8: Diff | L8: AA hiba (HA ,F, KÉK, Stb...) Beszállítóval fizettetni! | M8: BS Scrap | N8: Manufacturing Scrap | O8: Productivity Total (BC) | P8: Difficult item's code | Q8: Productivity LP (BC) | R8: Difficult item's code | T8: =C28-D28 -> 0
A9: =Headcount!A10 -> 2 | B9: =C5*C6 -> 55999.95 | C9: =C5 -> 3733.33 | D9: =E9 -> 1 | E9: =F9+G9 -> 1 | F9: 1 | G9: 0 | H9: 0 | K9: =J9-I9 -> 0 | L9: 0 | M9: 0 | N9: 0 | O9: -
A10: =Headcount!A11 -> 3 | B10: =$B$9-C9 -> 52266.62 | C10: =C9+$C$5 -> 7466.66 | D10: =IF(E10="",0,D9+E10) -> 2 | E10: =F10+G10 -> 1 | F10: 1 | G10: 0 | H10: 0 | K10: =J10-I10 -> 0 | L10: 0 | M10: 0 | N10: 0 | O10: -
A11: =Headcount!A12 -> 4 | B11: =$B$9-C10 -> 48533.29 | C11: =C10+$C$5 -> 11199.99 | D11: =IF(E11="",0,D10+E11) -> 5316 | E11: =F11+G11 -> 5314 | F11: 5314 | G11: 0 | H11: 0 | K11: =J11-I11 -> 0 | L11: 0 | M11: 3 | N11: 19 | O11: 0.9217
A12: =Headcount!A13 -> 5 | B12: =$B$9-C11 -> 44799.96 | C12: =C11+$C$5 -> 14933.32 | D12: =IF(E12="",0,D11+E12) -> 15103 | E12: =F12+G12 -> 9787 | F12: 9787 | G12: 0 | H12: 0 | K12: =J12-I12 -> 0 | L12: 0 | M12: 4 | N12: 4 | O12: 0.9474
A13: =Headcount!A14 -> 6 | B13: =$B$9-C12 -> 41066.63 | C13: =C12+$C$5 -> 18666.65 | D13: =IF(E13="",0,D12+E13) -> 20311 | E13: =F13+G13 -> 5208 | F13: 5208 | G13: 0 | H13: 0 | K13: =J13-I13 -> 0 | L13: 0 | M13: 2 | N13: 3 | O13: 0.9597
A14: =Headcount!A15 -> 9 | B14: =$B$9-C13 -> 37333.3 | C14: =C13+$C$5 -> 22399.98 | D14: =IF(E14="",0,D13+E14) -> 32175 | E14: =F14+G14 -> 11864 | F14: 11864 | G14: 0 | H14: 0 | K14: =J14-I14 -> 0 | L14: 3 | M14: 6 | N14: 4 | O14: 0.8379
A15: =Headcount!A16 -> 10 | B15: =$B$9-C14 -> 33599.97 | C15: =C14+$C$5 -> 26133.31 | D15: =IF(E15="",0,D14+E15) -> 44663 | E15: =F15+G15 -> 12488 | F15: 12488 | G15: 0 | H15: 0 | K15: =J15-I15 -> 0 | L15: 1 | M15: 6 | N15: 11 | O15: 0.9792
A16: =Headcount!A17 -> 11 | B16: =$B$9-C15 -> 29866.64 | C16: =C15+$C$5 -> 29866.64 | D16: =IF(E16="",0,D15+E16) -> 46414 | E16: =F16+G16 -> 1751 | F16: 1751 | G16: 0 | H16: 0 | K16: =J16-I16 -> 0 | L16: 0 | M16: 0 | N16: 3 | O16: 1.569
A17: =Headcount!A18 -> 12 | B17: =$B$9-C16 -> 26133.31 | C17: =C16+$C$5 -> 33599.97 | D17: =IF(E17="",0,D16+E17) -> 47812 | E17: =F17+G17 -> 1398 | F17: 1398 | G17: 0 | H17: 0 | K17: =J17-I17 -> 0 | L17: 0 | M17: 2 | N17: 0 | O17: 1.0333
A18: =Headcount!A19 -> 13 | B18: =$B$9-C17 -> 22399.98 | C18: =C17+$C$5 -> 37333.3 | D18: =IF(E18="",0,D17+E18) -> 47972 | E18: =F18+G18 -> 160 | F18: 160 | G18: 0 | H18: 0 | K18: =J18-I18 -> 0 | L18: 0 | M18: 0 | N18: 0 | O18: 1.3808
A19: =Headcount!A20 -> 16 | B19: =$B$9-C18 -> 18666.65 | C19: =C18+$C$5 -> 41066.63 | D19: =IF(E19="",0,D18+E19) -> 47973 | E19: =F19+G19 -> 1 | F19: 1 | G19: 0 | H19: 0 | K19: =J19-I19 -> 0 | L19: 0 | M19: 0 | N19: 0 | O19: -
A20: =Headcount!A21 -> 17 | B20: =$B$9-C19 -> 14933.32 | C20: =C19+$C$5 -> 44799.96 | D20: =IF(E20="",0,D19+E20) -> 47974 | E20: =F20+G20 -> 1 | F20: 1 | G20: 0 | H20: 0 | K20: =J20-I20 -> 0 | L20: 0 | M20: 0 | N20: 0 | O20: -
A21: =Headcount!A22 -> 18 | B21: =$B$9-C20 -> 11199.99 | C21: =C20+$C$5 -> 48533.29 | D21: =IF(E21="",0,D20+E21) -> 47975 | E21: =F21+G21 -> 1 | F21: 1 | G21: 0 | H21: 0 | K21: =J21-I21 -> 0 | L21: 0 | M21: 0 | N21: 0 | O21: -
A22: =Headcount!A23 -> 19 | B22: =$B$9-C21 -> 7466.66 | C22: =C21+$C$5 -> 52266.62 | D22: =IF(E22="",0,D21+E22) -> 50022 | E22: =F22+G22 -> 2047 | F22: 2047 | G22: 0 | H22: 0 | K22: =J22-I22 -> 0 | L22: 0 | M22: 3 | N22: 0 | O22: 0.8705
A23: =Headcount!A24 -> 20 | B23: =$B$9-C22 -> 3733.33 | C23: =C22+$C$5 -> 55999.95 | D23: =IF(E23="",0,D22+E23) -> 56349 | E23: =F23+G23 -> 6327 | F23: 6327 | G23: 0 | H23: 0 | K23: =J23-I23 -> 0 | L23: 1 | M23: 5 | N23: 15 | O23: 0.9418
A31: Summ line | C31: =C7*C5 -> 55999.95 | E31: =SUM(E9:E29) -> 56349 | L31: =SUM(L9:L30) -> 5 | M31: =SUM(M9:M30) -> 31 | N31: =SUM(N9:N30) -> 59 | O31: =AVERAGE(O9:O30) -> 1.04413 | Q31: =AVERAGE(Q9:Q30) -> #DIV/0!
M32: =M31+N31 -> 90

Sheet Attach Tape
A1: TAPE | C1: Difference to the plan | G1: =E31-C31 -> 642.05
B5: Daily plan | C5: 6533.33 | E5: =D23/C23 -> 1.0065515
B6: Workday | C6: =Headcount!F7 -> 15
B7: Actual day | C7: =Headcount!F8 -> 15 | I7: Operator / day TTL | O7: KFT operation | Q7: Subcon
A8: Day | B8: Remain Qty | C8: Plan | D8: Output(Comulative) | E8: Total | F8: Output Daily | G8: Subcon out | H8: Incoming from MV | I8: Op.Plan | J8: Op.Act | K8: Diff | L8: AA hiba (HA ,F, KÉK, Stb...) Beszállítóval fizettetni! | M8: BS Scrap | N8: Manufacturing scrap | O8: Productivity Total (BC) | P8: Difficult item's code | Q8: Productivity LP (BC) | R8: Difficult item's code
A9: =Headcount!A10 -> 2 | B9: =C5*C6 -> 97999.95 | C9: =C5 -> 6533.33 | D9: =E9 -> 8520 | E9: =F9+G9 -> 8520 | F9: 8520 | G9: 0 | H9: 0 | K9: =J9-I9 -> 0 | L9: 0 | M9: 8 | N9: 2 | O9: 0.6759 | P9: 2701-0374 Q+N
A10: =Headcount!A11 -> 3 | B10: =$B$9-C9 -> 91466.62 | C10: =C9+$C$5 -> 13066.66 | D10: =IF(E10="",0,D9+E10) -> 17061 | E10: =F10+G10 -> 8541 | F10: 8541 | G10: 0 | H10: 0 | K10: =J10-I10 -> 0 | L10: 0 | M10: 2 | N10: 3 | O10: 1.0796
A11: =Headcount!A12 -> 4 | B11: =$B$9-C10 -> 84933.29 | C11: =C10+$C$5 -> 19599.99 | D11: =IF(E11="",0,D10+E11) -> 37991 | E11: =F11+G11 -> 20930 | F11: 20930 | G11: 0 | H11: 0 | K11: =J11-I11 -> 0 | L11: 0 | M11: 7 | N11: 2 | O11: 1.006
A12: =Headcount!A13 -> 5 | B12: =$B$9-C11 -> 78399.96 | C12: =C11+$C$5 -> 26133.32 | D12: =IF(E12="",0,D11+E12) -> 41165 | E12: =F12+G12 -> 3174 | F12: 3174 | G12: 0 | H12: 0 | K12: =J12-I12 -> 0 | L12: 0 | M12: 0 | N12: 0 | O12: 1.0397
A13: =Headcount!A14 -> 6 | B13: =$B$9-C12 -> 71866.63 | C13: =C12+$C$5 -> 32666.65 | D13: =IF(E13="",0,D12+E13) -> 42151 | E13: =F13+G13 -> 986 | F13: 986 | G13: 0 | H13: 0 | K13: =J13-I13 -> 0 | L13: 0 | M13: 0 | N13: 2 | O13: 1.0661
A14: =Headcount!A15 -> 9 | B14: =$B$9-C13 -> 65333.3 | C14: =C13+$C$5 -> 39199.98 | D14: =IF(E14="",0,D13+E14) -> 45178 | E14: =F14+G14 -> 3027 | F14: 3027 | G14: 0 | H14: 0 | K14: =J14-I14 -> 0 | L14: 0 | M14: 0 | N14: 0 | O14: 1.021
A15: =Headcount!A16 -> 10 | B15: =$B$9-C14 -> 58799.97 | C15: =C14+$C$5 -> 45733.31 | D15: =IF(E15="",0,D14+E15) -> 47805 | E15: =F15+G15 -> 2627 | F15: 2627 | G15: 0 | H15: 0 | K15: =J15-I15 -> 0 | L15: 0 | M15: 3 | N15: 0 | O15: 0.7688 | P15: M.Cs. 56% / B. Á 56% / T. Cs. 48%
A16: =Headcount!A17 -> 11 | B16: =$B$9-C15 -> 52266.64 | C16: =C15+$C$5 -> 52266.64 | D16: =IF(E16="",0,D15+E16) -> 57711 | E16: =F16+G16 -> 9906 | F16: 9906 | G16: 0 | H16: 0 | K16: =J16-I16 -> 0 | L16: 0 | M16: 1 | N16: 2 | O16: 0.8761 | P16: M.Cs. 77% / B. Á 76% / O.S. 39% / Á.L 60 %
A17: =Headcount!A18 -> 12 | B17: =$B$9-C16 -> 45733.31 | C17: =C16+$C$5 -> 58799.97 | D17: =IF(E17="",0,D16+E17) -> 69628 | E17: =F17+G17 -> 11917 | F17: 11917 | G17: 0 | H17: 0 | K17: =J17-I17 -> 0 | L17: 0 | M17: 16 | N17: 1 | O17: 0.9005
A18: =Headcount!A19 -> 13 | B18: =$B$9-C17 -> 39199.98 | C18: =C17+$C$5 -> 65333.3 | D18: =IF(E18="",0,D17+E18) -> 73873 | E18: =F18+G18 -> 4245 | F18: 4245 | G18: 0 | H18: 0 | K18: =J18-I18 -> 0 | L18: 0 | M18: 1 | N18: 0 | O18: 0.7773
A19: =Headcount!A20 -> 16 | B19: =$B$9-C18 -> 32666.65 | C19: =C18+$C$5 -> 71866.63 | D19: =IF(E19="",0,D18+E19) -> 74253 | E19: =F19+G19 -> 380 | F19: 380 | G19: 0 | H19: 0 | K19: =J19-I19 -> 0 | L19: 0 | M19: 0 | N19: 0 | O19: 1.0757
A20: =Headcount!A21 -> 17 | B20: =$B$9-C19 -> 26133.32 | C20: =C19+$C$5 -> 78399.96 | D20: =IF(E20="",0,D19+E20) -> 75874 | E20: =F20+G20 -> 1621 | F20: 1621 | G20: 0 | H20: 0 | K20: =J20-I20 -> 0 | L20: 0 | M20: 1 | N20: 0 | O20: 1.1986
A21: =Headcount!A22 -> 18 | B21: =$B$9-C20 -> 19599.99 | C21: =C20+$C$5 -> 84933.29 | D21: =IF(E21="",0,D20+E21) -> 77423 | E21: =F21+G21 -> 1549 | F21: 1549 | G21: 0 | H21: 0 | K21: =J21-I21 -> 0 | L21: 0 | M21: 1 | N21: 0 | O21: 1.0376
A22: =Headcount!A23 -> 19 | B22: =$B$9-C21 -> 13066.66 | C22: =C21+$C$5 -> 91466.62 | D22: =IF(E22="",0,D21+E22) -> 89253 | E22: =F22+G22 -> 11830 | F22: 11830 | G22: 0 | H22: 0 | K22: =J22-I22 -> 0 | L22: 0 | M22: 22 | N22: 0 | O22: 0.9068
A23: =Headcount!A24 -> 20 | B23: =$B$9-C22 -> 6533.33 | C23: =C22+$C$5 -> 97999.95 | D23: =IF(E23="",0,D22+E23) -> 98642 | E23: =F23+G23 -> 9389 | F23: 9389 | G23: 0 | H23: 0 | K23: =J23-I23 -> 0 | L23: 0 | M23: 4 | N23: 0 | O23: 0.8857
A31: Summ line | C31: =C7*C5 -> 97999.95 | E31: =SUM(E9:E29) -> 98642 | L31: =SUM(L9:L30) -> 0 | M31: =SUM(M9:M30) -> 66 | N31: =SUM(N9:N30) -> 12 | O31: =AVERAGE(O9:O30) -> 0.95436 | Q31: =AVERAGE(Q9:Q30) -> #DIV/0!
M32: =M31+N31 -> 78

Sheet Bending+ATT(Kombi sablon)
A1: BEND + | C1: Difference to the plan | G1: =E31-C31 -> 38
A2: ATT (Kombi sablon)
B5: Daily plan | C5: 3600 | E5: =D23/C23 -> 1.0007037
B6: Workday | C6: =Headcount!F7 -> 15
B7: Actual day | C7: =Headcount!F8 -> 15 | I7: Operator / day TTL | O7: KFT operation
A8: Day | B8: Remain Qty | C8: Plan | D8: Output(Comulative) | E8: Total | F8: Output Daily | G8: Subcon out | H8: Incoming from MV | I8: Op.Plan | J8: Op.Act | K8: Diff | L8: AA hiba (HA ,F, KÉK, Stb...) Beszállítóval fizettetni! | M8: BS Scrap | N8: Manufacturing scrap | O8: Productivity Total (BC) | P8: Difficult item's code
A9: =Headcount!A10 -> 2 | B9: =C5*C6 -> 54000 | C9: =C5 -> 3600 | D9: =E9 -> 2910 | E9: =F9+G9 -> 2910 | F9: 2910 | G9: 0 | H9: 0 | K9: =J9-I9 -> 0 | L9: 0 | M9: 1 | N9: 2 | O9: 1.0229
A10: =Headcount!A11 -> 3 | B10: =$B$9-C9 -> 50400 | C10: =C9+$C$5 -> 7200 | D10: =IF(E10="",0,D9+E10) -> 7324 | E10: =F10+G10 -> 4414 | F10: 4414 | G10: 0 | H10: 0 | K10: =J10-I10 -> 0 | L10: 0 | M10: 1 | N10: 2 | O10: 1.053
A11: =Headcount!A12 -> 4 | B11: =$B$9-C10 -> 46800 | C11: =C10+$C$5 -> 10800 | D11: =IF(E11="",0,D10+E11) -> 11180 | E11: =F11+G11 -> 3856 | F11: 3856 | G11: 0 | H11: 0 | K11: =J11-I11 -> 0 | L11: 0 | M11: 5 | N11: 5 | O11: 0.9263 | P11: 1200-1398 109,66% 1200-1184 75,60% (Cz. É.)
A12: =Headcount!A13 -> 5 | B12: =$B$9-C11 -> 43200 | C12: =C11+$C$5 -> 14400 | D12: =IF(E12="",0,D11+E12) -> 15292 | E12: =F12+G12 -> 4112 | F12: 4112 | G12: 0 | H12: 0 | K12: =J12-I12 -> 0 | L12: 0 | M12: 0 | N12: 2 | O12: 1.0018
A13: =Headcount!A14 -> 6 | B13: =$B$9-C12 -> 39600 | C13: =C12+$C$5 -> 18000 | D13: =IF(E13="",0,D12+E13) -> 20804 | E13: =F13+G13 -> 5512 | F13: 5512 | G13: 0 | H13: 0 | K13: =J13-I13 -> 0 | L13: 2 | M13: 0 | N13: 1 | O13: 1.0078
A14: =Headcount!A15 -> 9 | B14: =$B$9-C13 -> 36000 | C14: =C13+$C$5 -> 21600 | D14: =IF(E14="",0,D13+E14) -> 26783 | E14: =F14+G14 -> 5979 | F14: 5979 | G14: 0 | H14: 0 | K14: =J14-I14 -> 0 | L14: 0 | M14: 0 | N14: 1 | O14: 1.0633
A15: =Headcount!A16 -> 10 | B15: =$B$9-C14 -> 32400 | C15: =C14+$C$5 -> 25200 | D15: =IF(E15="",0,D14+E15) -> 33288 | E15: =F15+G15 -> 6505 | F15: 6505 | G15: 0 | H15: 0 | K15: =J15-I15 -> 0 | L15: 0 | M15: 0 | N15: 5 | O15: 1.0926
A16: =Headcount!A17 -> 11 | B16: =$B$9-C15 -> 28800 | C16: =C15+$C$5 -> 28800 | D16: =IF(E16="",0,D15+E16) -> 38335 | E16: =F16+G16 -> 5047 | F16: 5047 | G16: 0 | H16: 0 | K16: =J16-I16 -> 0 | L16: 1 | M16: 0 | N16: 2 | O16: 1.0767
A17: =Headcount!A18 -> 12 | B17: =$B$9-C16 -> 25200 | C17: =C16+$C$5 -> 32400 | D17: =IF(E17="",0,D16+E17) -> 41153 | E17: =F17+G17 -> 2818 | F17: 2818 | G17: 0 | H17: 0 | K17: =J17-I17 -> 0 | L17: 0 | M17: 0 | N17: 3 | O17: 0.8687
A18: =Headcount!A19 -> 13 | B18: =$B$9-C17 -> 21600 | C18: =C17+$C$5 -> 36000 | D18: =IF(E18="",0,D17+E18) -> 43407 | E18: =F18+G18 -> 2254 | F18: 2254 | G18: 0 | H18: 0 | K18: =J18-I18 -> 0 | L18: 0 | M18: 4 | N18: 1 | O18: 0.9554
A19: =Headcount!A20 -> 16 | B19: =$B$9-C18 -> 18000 | C19: =C18+$C$5 -> 39600 | D19: =IF(E19="",0,D18+E19) -> 45747 | E19: =F19+G19 -> 2340 | F19: 2340 | G19: 0 | H19: 0 | K19: =J19-I19 -> 0 | L19: 0 | M19: 1 | N19: 5 | O19: 0.8102
A20: =Headcount!A21 -> 17 | B20: =$B$9-C19 -> 14400 | C20: =C19+$C$5 -> 43200 | D20: =IF(E20="",0,D19+E20) -> 50033 | E20: =F20+G20 -> 4286 | F20: 4286 | G20: 0 | H20: 0 | K20: =J20-I20 -> 0 | L20: 0 | M20: 3 | N20: 2 | O20: 0.8866
A21: =Headcount!A22 -> 18 | B21: =$B$9-C20 -> 10800 | C21: =C20+$C$5 -> 46800 | D21: =IF(E21="",0,D20+E21) -> 52873 | E21: =F21+G21 -> 2840 | F21: 2840 | G21: 0 | H21: 0 | K21: =J21-I21 -> 0 | L21: 0 | M21: 9 | N21: 9 | O21: 0.8891
A22: =Headcount!A23 -> 19 | B22: =$B$9-C21 -> 7200 | C22: =C21+$C$5 -> 50400 | D22: =IF(E22="",0,D21+E22) -> 54037 | E22: =F22+G22 -> 1164 | F22: 1164 | G22: 0 | H22: 0 | K22: =J22-I22 -> 0 | L22: 0 | M22: 1 | N22: 1 | O22: 0.9185
A23: =Headcount!A24 -> 20 | B23: =$B$9-C22 -> 3600 | C23: =C22+$C$5 -> 54000 | D23: =IF(E23="",0,D22+E23) -> 54038 | E23: =F23+G23 -> 1 | F23: 1 | G23: 0 | H23: 0 | K23: =J23-I23 -> 0 | L23: 0 | M23: 0 | N23: 0 | O23: -
A31: Summ line | C31: =C7*C5 -> 54000 | E31: =SUM(E9:E29) -> 54038 | L31: =SUM(L9:L30) -> 3 | M31: =SUM(M9:M30) -> 25 | N31: =SUM(N9:N30) -> 41 | O31: =AVERAGE(O9:O30) -> 0.96949286
M32: =M31+N31 -> 66

Sheet Hand L.mark
A1: MAN | C1: Difference to the plan | G1: =E31-C31 -> 58.1
A2: LINE
B5: Daily plan | C5: 526.66 | E5: =D23/C23 -> 1.0073545
B6: Workday | C6: =Headcount!F7 -> 15
B7: Actual day | C7: =Headcount!F8 -> 15 | H7: Operator / day TTL | O7: KFT operation | Q7: Subcon
A8: Day | B8: Remain Qty | C8: Plan | D8: Output(Comulative) | E8: Total | F8: Output Daily | G8: Subcon out | H8: Op.Plan | I8: Op.Act | J8: Diff | K8: Qty/op | L8: BS Scrap | M8: Manufacturing scrap | N8: Subcon | O8: Productivity (NAV) | P8: Difficult item's code | Q8: Productivity (NAV) | R8: Difficult item's code
A9: =Headcount!A10 -> 2 | B9: =C5*C6 -> 7899.9 | C9: =C5 -> 526.66 | D9: =F9 -> 4397 | E9: =F9+G9 -> 4397 | F9: 4397 | G9: 0 | H9: 1 | J9: =I9-H9 -> -1 | L9: 2 | M9: 0 | O9: 1.0039
A10: =Headcount!A11 -> 3 | B10: =$B$9-C9 -> 7373.24 | C10: =C9+$C$5 -> 1053.32 | D10: =IF(F10="",0,D9+F10) -> 5597 | E10: =F10+G10 -> 1200 | F10: 1200 | G10: 0 | H10: 1 | J10: =I10-H10 -> -1 | L10: 0 | M10: 0 | O10: 1.0097
A11: =Headcount!A12 -> 4 | B11: =$B$9-C10 -> 6846.58 | C11: =C10+$C$5 -> 1579.98 | D11: =IF(F11="",0,D10+F11) -> 6797 | E11: =F11+G11 -> 1200 | F11: 1200 | G11: 0 | H11: 1 | J11: =I11-H11 -> -1 | L11: 0 | M11: 0 | O11: 1.0097
A12: =Headcount!A13 -> 5 | B12: =$B$9-C11 -> 6319.92 | C12: =C11+$C$5 -> 2106.64 | D12: =IF(F12="",0,D11+F12) -> 7947 | E12: =F12+G12 -> 1150 | F12: 1150 | G12: 0 | H12: 1 | J12: =I12-H12 -> -1 | L12: 0 | M12: 0 | O12: 1.0066
A13: =Headcount!A14 -> 6 | B13: =$B$9-C12 -> 5793.26 | C13: =C12+$C$5 -> 2633.3 | D13: =IF(F13="",0,D12+F13) -> 7948 | E13: =F13+G13 -> 1 | F13: 1 | G13: 0 | H13: 1 | J13: =I13-H13 -> -1 | L13: 0 | M13: 0 | O13: -
A14: =Headcount!A15 -> 9 | B14: =$B$9-C13 -> 5266.6 | C14: =C13+$C$5 -> 3159.96 | D14: =IF(F14="",0,D13+F14) -> 7949 | E14: =F14+G14 -> 1 | F14: 1 | G14: 0 | H14: 1 | J14: =I14-H14 -> -1 | L14: 0 | M14: 0 | O14: -
A15: =Headcount!A16 -> 10 | B15: =$B$9-C14 -> 4739.94 | C15: =C14+$C$5 -> 3686.62 | D15: =IF(F15="",0,D14+F15) -> 7950 | E15: =F15+G15 -> 1 | F15: 1 | G15: 0 | H15: 1 | J15: =I15-H15 -> -1 | L15: 0 | M15: 0 | O15: -
A16: =Headcount!A17 -> 11 | B16: =$B$9-C15 -> 4213.28 | C16: =C15+$C$5 -> 4213.28 | D16: =IF(F16="",0,D15+F16) -> 7951 | E16: =F16+G16 -> 1 | F16: 1 | G16: 0 | H16: 1 | J16: =I16-H16 -> -1 | L16: 0 | M16: 0 | O16: -
A17: =Headcount!A18 -> 12 | B17: =$B$9-C16 -> 3686.62 | C17: =C16+$C$5 -> 4739.94 | D17: =IF(F17="",0,D16+F17) -> 7952 | E17: =F17+G17 -> 1 | F17: 1 | G17: 0 | H17: 1 | J17: =I17-H17 -> -1 | L17: 0 | M17: 0 | O17: -
A18: =Headcount!A19 -> 13 | B18: =$B$9-C17 -> 3159.96 | C18: =C17+$C$5 -> 5266.6 | D18: =IF(F18="",0,D17+F18) -> 7953 | E18: =F18+G18 -> 1 | F18: 1 | G18: 0 | H18: 1 | J18: =I18-H18 -> -1 | L18: 0 | M18: 0 | O18: -
A19: =Headcount!A20 -> 16 | B19: =$B$9-C18 -> 2633.3 | C19: =C18+$C$5 -> 5793.26 | D19: =IF(F19="",0,D18+F19) -> 7954 | E19: =F19+G19 -> 1 | F19: 1 | G19: 0 | H19: 1 | J19: =I19-H19 -> -1 | L19: 0 | M19: 0 | O19: -
A20: =Headcount!A21 -> 17 | B20: =$B$9-C19 -> 2106.64 | C20: =C19+$C$5 -> 6319.92 | D20: =IF(F20="",0,D19+F20) -> 7955 | E20: =F20+G20 -> 1 | F20: 1 | G20: 0 | H20: 1 | J20: =I20-H20 -> -1 | L20: 0 | M20: 0 | O20: -
A21: =Headcount!A22 -> 18 | B21: =$B$9-C20 -> 1579.98 | C21: =C20+$C$5 -> 6846.58 | D21: =IF(F21="",0,D20+F21) -> 7956 | E21: =F21+G21 -> 1 | F21: 1 | G21: 0 | H21: 1 | J21: =I21-H21 -> -1 | L21: 0 | M21: 0 | O21: -
A22: =Headcount!A23 -> 19 | B22: =$B$9-C21 -> 1053.32 | C22: =C21+$C$5 -> 7373.24 | D22: =IF(F22="",0,D21+F22) -> 7957 | E22: =F22+G22 -> 1 | F22: 1 | G22: 0 | H22: 1 | J22: =I22-H22 -> -1 | L22: 0 | M22: 0 | O22: -
A23: =Headcount!A24 -> 20 | B23: =$B$9-C22 -> 526.66 | C23: =C22+$C$5 -> 7899.9 | D23: =IF(F23="",0,D22+F23) -> 7958 | E23: =F23+G23 -> 1 | F23: 1 | G23: 0 | H23: 1 | J23: =I23-H23 -> -1 | L23: 0 | M23: 0 | O23: -
A31: Summ line | C31: =C7*C5 -> 7899.9 | E31: =SUM(E9:E28) -> 7958 | L31: =SUM(L9:L30) -> 2 | M31: =SUM(M9:N30) -> 0 | O31: =AVERAGE(O9:O30) -> 1.007475
L32: =L31+M31 -> 2

Sheet KFT Output_Bundling
A1: BUND | D1: Difference to the plan | I1: =F31-D31 -> 9220 | K1: Recovery plan ( recovery ) recovery period must indicate green cells
D5: Napi terv / Daily plan | E5: =('PlanFollow (Factory out)'!B34*1000)/'KFT Output_Bundling'!E6 -> 16410.733 | H5: =E23/D23 -> 1.0374552
D6: Workday | E6: =Headcount!F7 -> 15
D7: Actual day | E7: =Headcount!F8 -> 15
A8: Munkanap | B8: =D5 -> Napi terv / Daily plan | C8: Remain Qty | D8: Terv / Plan | E8: Kimenet (kumulált) / Output (cumulative) | F8: Teljes / Total | G8: 2701-0374 | H8: Output Daily Bundling
A9: =Headcount!A10 -> 2 | B9: =$E$5 -> 16410.733 | C9: =E5*E6 -> 246161 | D9: =E5 -> 16410.733 | E9: =F9 -> 7174 | F9: =H9+G9 -> 7174 | G9: 0 | H9: 7174
A10: =Headcount!A11 -> 3 | B10: =$E$5 -> 16410.733 | C10: =$C$9-D9 -> 229750.27 | D10: =D9+$E$5 -> 32821.467 | E10: =IF(E9=0,0,F9+F10) -> 13274 | F10: =H10+G10 -> 6100 | G10: 0 | H10: 6100
A11: =Headcount!A12 -> 4 | B11: =$E$5 -> 16410.733 | C11: =$C$9-D10 -> 213339.53 | D11: =D10+$E$5 -> 49232.2 | E11: =IF(E10="",0,E10+F11) -> 30903 | F11: =H11+G11 -> 17629 | G11: 0 | H11: 17629
A12: =Headcount!A13 -> 5 | B12: =$E$5 -> 16410.733 | C12: =$C$9-D11 -> 196928.8 | D12: =D11+$E$5 -> 65642.933 | E12: =IF(E11="",0,E11+F12) -> 56009 | F12: =H12+G12 -> 25106 | G12: 0 | H12: 25106
A13: =Headcount!A14 -> 6 | B13: =$E$5 -> 16410.733 | C13: =$C$9-D12 -> 180518.07 | D13: =D12+$E$5 -> 82053.667 | E13: =IF(E12="",0,E12+F13) -> 69783 | F13: =H13+G13 -> 13774 | G13: 0 | H13: 13774
A14: =Headcount!A15 -> 9 | B14: =$E$5 -> 16410.733 | C14: =$C$9-D13 -> 164107.33 | D14: =D13+$E$5 -> 98464.4 | E14: =IF(E13="",0,E13+F14) -> 99018 | F14: =H14+G14 -> 29235 | G14: 0 | H14: 29235
A15: =Headcount!A16 -> 10 | B15: =$E$5 -> 16410.733 | C15: =$C$9-D14 -> 147696.6 | D15: =D14+$E$5 -> 114875.13 | E15: =IF(E14="",0,E14+F15) -> 126387 | F15: =H15+G15 -> 27369 | G15: 0 | H15: 27369
A16: =Headcount!A17 -> 11 | B16: =$E$5 -> 16410.733 | C16: =$C$9-D15 -> 131285.87 | D16: =D15+$E$5 -> 131285.87 | E16: =IF(E15="",0,E15+F16) -> 154964 | F16: =H16+G16 -> 28577 | G16: 0 | H16: 28577
A17: =Headcount!A18 -> 12 | B17: =$E$5 -> 16410.733 | C17: =$C$9-D16 -> 114875.13 | D17: =D16+$E$5 -> 147696.6 | E17: =IF(E16="",0,E16+F17) -> 178199 | F17: =H17+G17 -> 23235 | G17: 1075 | H17: 22160
A18: =Headcount!A19 -> 13 | B18: =$E$5 -> 16410.733 | C18: =$C$9-D17 -> 98464.4 | D18: =D17+$E$5 -> 164107.33 | E18: =IF(E17="",0,E17+F18) -> 205337 | F18: =H18+G18 -> 27138 | G18: 1768 | H18: 25370
A19: =Headcount!A20 -> 16 | B19: =$E$5 -> 16410.733 | C19: =$C$9-D18 -> 82053.667 | D19: =D18+$E$5 -> 180518.07 | E19: =IF(E18="",0,E18+F19) -> 218872 | F19: =H19+G19 -> 13535 | G19: 1974 | H19: 11561
A20: =Headcount!A21 -> 17 | B20: =$E$5 -> 16410.733 | C20: =$C$9-D19 -> 65642.933 | D20: =D19+$E$5 -> 196928.8 | E20: =IF(E19="",0,E19+F20) -> 225906 | F20: =H20+G20 -> 7034 | G20: 1900 | H20: 5134
A21: =Headcount!A22 -> 18 | B21: =$E$5 -> 16410.733 | C21: =$C$9-D20 -> 49232.2 | D21: =D20+$E$5 -> 213339.53 | E21: =IF(E20="",0,E20+F21) -> 236735 | F21: =H21+G21 -> 10829 | G21: 596 | H21: 10233 | X21: 0.35416667
A22: =Headcount!A23 -> 19 | B22: =$E$5 -> 16410.733 | C22: =$C$9-D21 -> 32821.467 | D22: =D21+$E$5 -> 229750.27 | E22: =IF(E21="",0,E21+F22) -> 245027 | F22: =H22+G22 -> 8292 | G22: 0 | H22: 8292
A23: =Headcount!A24 -> 20 | B23: =$E$5 -> 16410.733 | C23: =$C$9-D22 -> 16410.733 | D23: =D22+$E$5 -> 246161 | E23: =IF(E22="",0,E22+F23) -> 255381 | F23: =H23+G23 -> 10354 | G23: 0 | H23: 10354
J28: =53100/6 -> 8850
A31: Summ line | D31: =E7*E5 -> 246161 | F31: =SUM(F9:F30) -> 255381 | G31: =SUM(G9:G30) -> 7313 | H31: =SUM(H9:H30) -> 248068

Sheet KFT Output packaging
A1: PACK | D1: Difference to the plan | H1: =G33-D33 -> 58 | J1: Recovery plan ( recovery ) recovery period must indicate green cells
D5: Napi terv / Daily plan | E5: =(('PlanFollow (Factory out)'!B34+'PlanFollow (Finished)'!B34)*1000)/'KFT Output packaging'!E6 -> 32225.067 | G5: =E23/D23 -> 1.00012
D6: Workday | E6: =Headcount!F7 -> 15
D7: Actual day | E7: =Headcount!F8 -> 15
A8: Day | B8: =D5 -> Napi terv / Daily plan | C8: Remain Qty | D8: Terv / Plan | E8: Kimenet (kumulált) / Output (cumulative) | F8: Teljes / Total | G8: Output Daily
A9: =Headcount!A10 -> 2 | B9: =$E$5 -> 32225.067 | C9: =E5*E6 -> 483376 | D9: =E5 -> 32225.067 | E9: =G9 -> 32800 | F9: =G9 -> 32800 | G9: 32800
A10: =Headcount!A11 -> 3 | B10: =$E$5 -> 32225.067 | C10: =$C$9-D9 -> 451150.93 | D10: =D9+$E$5 -> 64450.133 | E10: =IF(G10="",0,E9+G10) -> 57600 | F10: =IF(G10="",0,F9+G10) -> 57600 | G10: 24800
A11: =Headcount!A12 -> 4 | B11: =$E$5 -> 32225.067 | C11: =$C$9-D10 -> 418925.87 | D11: =D10+$E$5 -> 96675.2 | E11: =IF(G11="",0,E10+G11) -> 100000 | F11: =IF(G11="",0,F10+G11) -> 100000 | G11: 42400
A12: =Headcount!A13 -> 5 | B12: =$E$5 -> 32225.067 | C12: =$C$9-D11 -> 386700.8 | D12: =D11+$E$5 -> 128900.27 | E12: =IF(G12="",0,E11+G12) -> 142400 | F12: =IF(G12="",0,F11+G12) -> 142400 | G12: 42400
A13: =Headcount!A14 -> 6 | B13: =$E$5 -> 32225.067 | C13: =$C$9-D12 -> 354475.73 | D13: =D12+$E$5 -> 161125.33 | E13: =IF(G13="",0,E12+G13) -> 171400 | F13: =IF(G13="",0,F12+G13) -> 171400 | G13: 29000
A14: =Headcount!A15 -> 9 | B14: =$E$5 -> 32225.067 | C14: =$C$9-D13 -> 322250.67 | D14: =D13+$E$5 -> 193350.4 | E14: =IF(G14="",0,E13+G14) -> 220036 | F14: =IF(G14="",0,F13+G14) -> 220036 | G14: 48636
A15: =Headcount!A16 -> 10 | B15: =$E$5 -> 32225.067 | C15: =$C$9-D14 -> 290025.6 | D15: =D14+$E$5 -> 225575.47 | E15: =IF(G15="",0,E14+G15) -> 252736 | F15: =IF(G15="",0,F14+G15) -> 252736 | G15: 32700
A16: =Headcount!A17 -> 11 | B16: =$E$5 -> 32225.067 | C16: =$C$9-D15 -> 257800.53 | D16: =D15+$E$5 -> 257800.53 | E16: =IF(G16="",0,E15+G16) -> 289736 | F16: =IF(G16="",0,F15+G16) -> 289736 | G16: 37000
A17: =Headcount!A18 -> 12 | B17: =$E$5 -> 32225.067 | C17: =$C$9-D16 -> 225575.47 | D17: =D16+$E$5 -> 290025.6 | E17: =IF(G17="",0,E16+G17) -> 332336 | F17: =IF(G17="",0,F16+G17) -> 332336 | G17: 42600
A18: =Headcount!A19 -> 13 | B18: =$E$5 -> 32225.067 | C18: =$C$9-D17 -> 193350.4 | D18: =D17+$E$5 -> 322250.67 | E18: =IF(G18="",0,E17+G18) -> 360836 | F18: =IF(G18="",0,F17+G18) -> 360836 | G18: 28500
A19: =Headcount!A20 -> 16 | B19: =$E$5 -> 32225.067 | C19: =$C$9-D18 -> 161125.33 | D19: =D18+$E$5 -> 354475.73 | E19: =IF(G19="",0,E18+G19) -> 403461 | F19: =IF(G19="",0,F18+G19) -> 403461 | G19: 42625
A20: =Headcount!A21 -> 17 | B20: =$E$5 -> 32225.067 | C20: =$C$9-D19 -> 128900.27 | D20: =D19+$E$5 -> 386700.8 | E20: =IF(G20="",0,E19+G20) -> 424976 | F20: =IF(G20="",0,F19+G20) -> 424976 | G20: 21515
A21: =Headcount!A22 -> 18 | B21: =$E$5 -> 32225.067 | C21: =$C$9-D20 -> 96675.2 | D21: =D20+$E$5 -> 418925.87 | E21: =IF(G21="",0,E20+G21) -> 443776 | F21: =IF(G21="",0,F20+G21) -> 443776 | G21: 18800
... A23: =Headcount!A24 -> 20 | B23: =$E$5 -> 32225.067 | C23: =$C$9-D22 -> 32225.067 | D23: =D22+$E$5 -> 483376 | E23: =IF(G23="",0,E22+G23) -> 483434 | F23: =IF(G23="",0,F22+G23) -> 483434 | G23: 23958
A33: Summ line | D33: =E7*E5 -> 483376 | G33: =SUM(G9:G31) -> 483434

Sheet Sales Qty
A1: SLS | C1: Difference to the plan | G1: =E32-C32 -> 10 | I1: Recovery plan ( recovery ) recovery period must indicate green cells
A2: QTY
B5: Daily plan | C5: 32462
B6: Ship days | C6: 15
B7: Actual day | C7: =Headcount!F8 -> 15
A8: Day | B8: Remain Amount | C8: Plan | D8: Sales(Comulative) | E8: Sales Daily (Pc.)
A9: 2 | B9: =C5*C6 -> 486930 | C9: =C5 -> 32462 | D9: =E9 -> 15664 | E9: 15664
A10: 3 | B10: =$B$9-C9 -> 454468 | C10: =C9+$C$5 -> 64924 | D10: =IF(E10="",0,D9+E10) -> 26664 | E10: 11000
A11: 4 | B11: =$B$9-C10 -> 422006 | C11: =C10+$C$5 -> 97386 | D11: =IF(E11="",0,D10+E11) -> 102664 | E11: 76000
A12: 5 | B12: =$B$9-C11 -> 389544 | C12: =C11+$C$5 -> 129848 | D12: =IF(E12="",0,D11+E12) -> 102664 | E12: 0
A13: 6 | B13: =$B$9-C12 -> 357082 | C13: =C12+$C$5 -> 162310 | D13: =IF(E13="",0,D12+E13) -> 131664 | E13: 29000
A14: 9 | B14: =$B$9-C13 -> 324620 | C14: =C13+$C$5 -> 194772 | D14: =IF(E14="",0,D13+E14) -> 131664 | E14: 0
A15: 10 | B15: =$B$9-C14 -> 292158 | C15: =C14+$C$5 -> 227234 | D15: =IF(E15="",0,D14+E15) -> 131664 | E15: 0
A16: 11 | B16: =$B$9-C15 -> 259696 | C16: =C15+$C$5 -> 259696 | D16: =IF(E16="",0,D15+E16) -> 183440 | E16: 51776
A17: 12 | B17: =$B$9-C16 -> 227234 | C17: =C16+$C$5 -> 292158 | D17: =IF(E17="",0,D16+E17) -> 225440 | E17: 42000
A18: 13 | B18: =$B$9-C17 -> 194772 | C18: =C17+$C$5 -> 324620 | D18: =IF(E18="",0,D17+E18) -> 225440 | E18: 0
A19: 16 | B19: =$B$9-C18 -> 162310 | C19: =C18+$C$5 -> 357082 | D19: =IF(E19="",0,D18+E19) -> 250440 | E19: 25000
A20: 17 | B20: =$B$9-C19 -> 129848 | C20: =C19+$C$5 -> 389544 | D20: =IF(E20="",0,D19+E20) -> 256440 | E20: 6000
A21: 18 | B21: =$B$9-C20 -> 97386 | C21: =C20+$C$5 -> 422006 | D21: =IF(E21="",0,D20+E21) -> 400440 | E21: 144000
... A23: 20 | B23: =$B$9-C22 -> 32462 | C23: =C22+$C$5 -> 486930 | D23: =IF(E23="",0,D22+E23) -> 486940 | E23: 53500
D24: =IF(E24="",0,D23+E24) -> 0
D25: =IF(E25="",0,D24+E25) -> 0
D26: =IF(E26="",0,D25+E26) -> 0
D27: =IF(E27="",0,D26+E27) -> 0
D28: =IF(E28="",0,D27+E28) -> 0
D29: =IF(E29="",0,D28+E29) -> 0
A32: Summ line | C32: =(C7)*C5 -> 486930 | E32: =SUM(E9:E31) -> 486940

Sheet Sales Amount
A1: SLS | C1: Difference to the plan | G1: =E33-C33 -> -5796.9256 | I1: Recovery plan ( recovery ) recovery period must indicate green cells
B5: Daily plan | C5: ='Prod.Output Summ'!O14/'Prod.Output Summ'!B2 -> 19468.667
B6: Ship days | C6: 14
B7: Actual day | C7: =Headcount!F8 -> 15
A8: Day | B8: Remain Amount | C8: Plan | D8: Sales(Comulative) | E8: Sales Daily
A9: 2 | B9: =C5*C6 -> 272561.33 | C9: =C5 -> 19468.667 | D9: =E9 -> 6604.804 | E9: 6604.804
A10: 3 | B10: =$B$9-C9 -> 253092.67 | C10: =C9+$C$5 -> 38937.333 | D10: =IF(E10="",0,D9+E10) -> 15360.804 | E10: 8756
A11: 4 | B11: =$B$9-C10 -> 233624 | C11: =C10+$C$5 -> 58406 | D11: =IF(E11="",0,D10+E11) -> 51679.944 | E11: 36319.14
A12: 5 | B12: =$B$9-C11 -> 214155.33 | C12: =C11+$C$5 -> 77874.667 | D12: =IF(E12="",0,D11+E12) -> 51679.944 | E12: 0
A13: 6 | B13: =$B$9-C12 -> 194686.67 | C13: =C12+$C$5 -> 97343.333 | D13: =IF(E13="",0,D12+E13) -> 73727.544 | E13: 22047.6
A14: 9 | B14: =$B$9-C13 -> 175218 | C14: =C13+$C$5 -> 116812 | D14: =IF(E14="",0,D13+E14) -> 73727.544 | E14: 0
A15: 10 | B15: =$B$9-C14 -> 155749.33 | C15: =C14+$C$5 -> 136280.67 | D15: =IF(E15="",0,D14+E15) -> 73727.544 | E15: 0
A16: 11 | B16: =$B$9-C15 -> 136280.67 | C16: =C15+$C$5 -> 155749.33 | D16: =IF(E16="",0,D15+E16) -> 88297.674 | E16: 14570.13
A17: 12 | B17: =$B$9-C16 -> 116812 | C17: =C16+$C$5 -> 175218 | D17: =IF(E17="",0,D16+E17) -> 111978.97 | E17: 23681.3
A18: 13 | B18: =$B$9-C17 -> 97343.333 | C18: =C17+$C$5 -> 194686.67 | D18: =IF(E18="",0,D17+E18) -> 111978.97 | E18: 0
A19: 16 | B19: =$B$9-C18 -> 77874.667 | C19: =C18+$C$5 -> 214155.33 | D19: =IF(E19="",0,D18+E19) -> 126836.97 | E19: 14858
A20: 17 | B20: =$B$9-C19 -> 58406 | C20: =C19+$C$5 -> 233624 | D20: =IF(E20="",0,D19+E20) -> 133481.19 | E20: 6644.22
A21: 18 | B21: =$B$9-C20 -> 38937.333 | C21: =C20+$C$5 -> 253092.67 | D21: =IF(E21="",0,D20+E21) -> 214610.83 | E21: 81129.64
... A23: 20 | B23: =$B$9-C22 -> 0 | C23: =C22+$C$5 -> 292030 | D23: =IF(E23="",0,D22+E23) -> 286233.07 | E23: 27513.54
D24: =IF(E24="",0,D23+E24) -> 0
D25: =IF(E25="",0,D24+E25) -> 0
D26: =IF(E26="",0,D25+E26) -> 0
D27: =IF(E27="",0,D26+E27) -> 0
D28: =IF(E28="",0,D27+E28) -> 0
D29: =IF(E29="",0,D28+E29) -> 0
A33: Summ line | C33: =(C7)*C5 -> 292030 | E33: =SUM(E9:E31) -> 286233.07

Sheet Sales_daily_plan_follow
AE3: 10000
AE6: =AF6-AF7 -> 40000 | AF6: 160000
B7: 45628 | C7: 45629 | D7: 45630 | E7: 45631 | F7: 45632 | G7: 45635 | H7: 45636 | I7: 45637 | J7: 45638 | K7: 45639 | L7: 45642 | M7: 45643 | N7: 45644 | O7: 45645 | P7: 45646 | AF7: 120000
A8: Draft Plan | B8: 305520.89 | C8: =279836+7391 -> 287227 | D8: 284385 | AB8: Original
A9: Sales Plan | B9: 292030 | AB9: TTL Sales plan | AC9: =B9+C3 -> 292030
A10: Sales EUR (actual) | B10: 6604.804 | C10: 8756 | D10: 36319.14 | E10: 0 | F10: 22047.6 | G10: 0 | H10: 0 | I10: 14570.13 | J10: 23681.3 | K10: 0 | L10: 14858 | M10: 6644.22 | N10: 81129.64 | O10: 44108.7 | P10: 27513.54 | AB10: TTL actual sales | AC10: =SUM(B10:AB10) -> 286233.07 | AE10: 128000
A11: Balance wo FG Stock | B11: =B10-B9 -> -285425.2 | C11: =B11+C10 -> -276669.2 | D11: =C11+D10-D9 -> -240350.06 | E11: =D11+E10-E9 -> -240350.06 | F11: =E11+F10-F9 -> -218302.46 | G11: =F11+G10-G9 -> -218302.46 | H11: =G11+H10-H9 -> -218302.46 | I11: =H11+I10-I9 -> -203732.33 | J11: =I11+J10-J9 -> -180051.03 | K11: =J11+K10-K9 -> -180051.03 | ... AA11: =Z11+AA10-AA9 -> -5796.9256 | AB11: Remaining sales | AC11: =AC9-AC10 -> 5796.9256
A12: FG Stock (ship out within this month) | B12: 194932.88 | C12: 186176.88 | D12: 171650.88 | E12: 187282.88 | F12: 163459.26 | G12: 164209.89 | H12: 164209.89 | I12: 148760.76 | J12: 132143.26 | K12: 149472.96 | L12: 141546.56 | M12: 138822.31 | N12: 98309.67 | O12: 54066.9 | P12: 42296.9 | AB12: Planned ship out from next month
A13: Balance with FG Stock | B13: =B11+B12 -> -90492.316 | C13: =C11+C12 -> -90492.316 | D13: =D11+D12 -> -68699.176 | E13: =E11+E12 -> -53067.176 | F13: =F11+F12 -> -54843.196 | G13: =G11+G12 -> -54092.566 | H13: =H11+H12 -> -54092.566 | I13: =I11+I12 -> -54971.566 | ... AA13: =AA11+AA12 -> -5796.9256 | AB13: FG increasement | AC13: =X14-B16 -> 0
A14: TTL FG Stock price | B14: 359554.72 | C14: 353773.72 | D14: 349760.76 | E14: 358061.56 | F14: 349591.46 | G14: 415291.47 | H14: 416241.47 | I14: 410192.34 | J14: 402401.94 | K14: 411487.56 | L14: 421781.3 | M14: 436581.06 | N14: 366633.19 | O14: 338817.18 | P14: 318261.61 | AB14: FG plan in end of month | AC14: =AC12+B16 -> 0
A15: Finished (Repack) | B15: 36709.18 | C15: 35804.18 | D15: 27792.08 | E15: 29502.08 | F15: 28805.48 | G15: 29752.04 | H15: 29752.04 | I15: 27590.54 | J15: 27335.54 | K15: 27335.54 | L15: 28694.54 | M15: 31144.54 | N15: 22824.9 | O15: 24714.9 | P15: 24868.18 | AB15: Production output | AC15: =AC13+AC10 -> 286233.07
A16: FG Open in sales price
A17: Finished FG Open in sales price
AF18: =8*805 -> 6440
X49: 29 1152 EUR | AA49: =X10-1152 -> -1152
X50: 30 4432 EUR | AA50: =Y10-4432 -> -4432
Q51: SPC | X51: 31 1610 | AA51: =AA10-1610 -> -1610
Q52: Construction

Sheet Summarise
B1: 43160 | C1: 43161 | D1: 43164 | E1: 43165 | F1: 43166 | G1: 43167 | H1: 43168 | I1: 43169
A2: Daily sales | B2: 69000 | C2: 15505 | D2: 53586 | E2: 16571
A3: Prod. Out. | B3: 79 | C3: 107 | D3: 105 | E3: 61 | F3: 64 | G3: 97 | H3: 72 | I3: 101
A4: Prod. Plan | B4: 93 | C4: 109 | D4: 77 | E4: 76 | F4: 60 | G4: 139 | H4: 81 | I4: 74
A5: Manual AVG Productivity | B5: 0.91 | C5: 0.849 | D5: 0.76 | E5: 0.85 | F5: 0.79 | G5: 0.64 | H5: 0.74 | I5: 0.81

Sheet Daily Production
B1: 43160 | E1: 43161 | H1: 43164 | K1: 43165 | N1: 43166 | Q1: 43167 | T1: 43168 | W1: 43169 | Z1: 43171 | AC1: 43172 | AE1: 43173 | AG1: 43178 | AI1: 43179 | AK1: 43180 | AM1: 43181 | AO1: 43182 | AQ1: 43185 | AS1: 43186 | AU1: 43187 | AW1: 43188
B2: Plan | C2: Output | D2: Diff. | E2: Plan | F2: Output | G2: Diff | H2: Plan | I2: Output | J2: Diff. | K2: Plan | L2: Output | M2: Diff | N2: Plan | O2: Output | P2: Diff | Q2: Plan | R2: Output | S2: Diff | T2: Plan | U2: Output | V2: Diff | W2: Plan | X2: Output | Y2: Diff | Z2: Plan | AA2: Output | AB2: Diff | AC2: Plan | AD2: Output | AE2: Plan | AF2: Output | AG2: Plan | AH2: Output | AI2: Plan | AJ2: Output | AK2: Plan | AL2: Output | AM2: Plan | AN2: Output | AO2: Plan | AP2: Output | AQ2: Plan | AR2: Output | AS2: Plan | AT2: Output | AU2: Plan | AV2: Output | AW2: Plan | AX2: Output
A3: 07-1200-0767H | B3: 1.5 | C3: 1.5 | D3: =C3-B3 -> 0 | E3: 1.5 | F3: 1.5 | G3: =F3-E3 -> 0 | H3: 1.5 | I3: 0 | J3: =I3-H3 -> -1.5 | K3: 1.5 | L3: 0 | M3: =L3-K3 -> -1.5 | N3: 1.5 | O3: 1.5 | P3: =O3-N3 -> 0 | Q3: 1.5 | R3: 0.5 | S3: =R3-Q3 -> -1 | T3: 1.5 | U3: 0 | V3: =U3-T3 -> -1.5 | W3: 1.5 | X3: 0 | Y3: =X3-W3 -> -1.5 | Z3: 1.5 | AA3: 0 | AB3: =AA3-Z3 -> -1.5 | AC3: 1.5 | AE3: 1.5 | AG3: 1.5 | AI3: 1.5 | AK3: 1.5 | AM3: 1.5 | AO3: 1.5 | AQ3: 1.5 | AS3: 1.5 | AU3: 1.5
A4: 07-1200-0787H | B4: 0 | C4: 0 | D4: =C4-B4 -> 0 | E4: 0 | G4: =F4-E4 -> 0 | H4: 1 | I4: 1 | J4: =I4-H4 -> 0 | K4: 2 | L4: 2 | M4: =L4-K4 -> 0 | N4: 2 | O4: 1.7 | P4: =O4-N4 -> -0.3 | Q4: 2 | R4: 0 | S4: =R4-Q4 -> -2 | T4: 2 | U4: 1.3 | V4: =U4-T4 -> -0.7 | W4: 2 | X4: 0 | Y4: =X4-W4 -> -2 | Z4: 2 | AA4: 2 | AB4: =AA4-Z4 -> 0 | AC4: 2 | AD4: 2 | AE4: 2 | AF4: 1 | AG4: 4 | AI4: 2 | AK4: 2 | AM4: 2 | AO4: 2 | AQ4: 2 | AS4: 2 | AU4: 2
A5: 07-1200-0937H | B5: 0 | C5: 0 | D5: =C5-B5 -> 0 | E5: 0 | G5: =F5-E5 -> 0 | H5: 4 | I5: 1.85 | J5: =I5-H5 -> -2.15 | K5: 4 | L5: 2.5 | M5: =L5-K5 -> -1.5 | N5: 4 | O5: 2.5 | P5: =O5-N5 -> -1.5 | Q5: 4 | R5: 0.5 | S5: =R5-Q5 -> -3.5 | T5: 2 | U5: 1.5 | V5: =U5-T5 -> -0.5 | W5: 2 | X5: 2 | Y5: =X5-W5 -> 0 | Z5: 2 | AA5: 2 | AB5: =AA5-Z5 -> 0 | AC5: 2 | AD5: 2 | AE5: 2 | AF5: 2 | AG5: 2 | AH5: 1 | AI5: 2 | AK5: 2 | AM5: 2 | AO5: 2 | AQ5: 2 | AS5: 2 | AU5: 2 | AW5: 2
A6: 07-1200-1040H | B6: 0 | C6: 0 | D6: =C6-B6 -> 0 | E6: 0 | G6: =F6-E6 -> 0 | H6: 0 | I6: 0 | J6: =I6-H6 -> 0 | K6: 0 | L6: 0 | M6: =L6-K6 -> 0 | N6: 0 | O6: 0 | P6: =O6-N6 -> 0 | Q6: 2.4 | R6: 1.9 | S6: =R6-Q6 -> -0.5 | T6: 2.4 | U6: 0 | V6: =U6-T6 -> -2.4 | W6: 2.4 | X6: 0 | Y6: =X6-W6 -> -2.4 | Z6: 1.2 | AA6: 1.2 | AB6: =AA6-Z6 -> 0 | AC6: 1.2 | AD6: 1.2 | AE6: 1.2 | AF6: 1.2 | AG6: 1.2 | AH6: 1.2 | AI6: 1.2 | AJ6: 0.1 | AK6: 1.2 | AM6: 1.2 | AO6: 1.2 | AQ6: 1.2 | AS6: 1.2 | AU6: 1.2 | AW6: 1.2
A7: 07-1200-1078H | B7: 0 | C7: 0 | D7: =C7-B7 -> 0 | E7: 0 | G7: =F7-E7 -> 0 | H7: 3.4 | I7: 3.4 | J7: =I7-H7 -> 0 | K7: 3.4 | L7: 2.6 | M7: =L7-K7 -> -0.8 | N7: 1.7 | O7: 0 | P7: =O7-N7 -> -1.7 | Q7: 1.7 | R7: 1.7 | S7: =R7-Q7 -> 0 | T7: 1.7 | U7: 1.7 | V7: =U7-T7 -> 0 | W7: 1.7 | X7: 1.7 | Y7: =X7-W7 -> 0 | Z7: 1.7 | AA7: 1.7 | AB7: =AA7-Z7 -> 0 | AC7: 1.7 | AD7: 1.2 | AE7: 1.7 | AG7: 1.7 | AI7: 1.7 | AK7: 1.7 | AM7: 1.7 | AO7: 1.7 | AQ7: 1.7 | AS7: 1.7 | AU7: 1.7 | AW7: 1.7
A8: 07-1200-1083H | B8: 2 | C8: 2 | D8: =C8-B8 -> 0 | E8: 2 | F8: 2 | G8: =F8-E8 -> 0 | H8: 2 | I8: 2 | J8: =I8-H8 -> 0 | K8: 2 | L8: 2 | M8: =L8-K8 -> 0 | N8: 2 | O8: 2 | P8: =O8-N8 -> 0 | Q8: 2 | R8: 2 | S8: =R8-Q8 -> 0 | T8: 2 | U8: 2 | V8: =U8-T8 -> 0 | W8: 2 | X8: 2 | Y8: =X8-W8 -> 0 | Z8: 2 | AA8: 2 | AB8: =AA8-Z8 -> 0 | AC8: 2 | AD8: 2 | AE8: 2 | AF8: 2 | AG8: 2 | AH8: 2 | AI8: 2 | AJ8: 1.2 | AK8: 2 | AM8: 2 | AO8: 2 | AQ8: 2 | AS8: 2 | AU8: 2 | AW8: 2
A9: 07-1200-1084H | B9: 2 | C9: 2 | D9: =C9-B9 -> 0 | E9: 2 | F9: 2 | G9: =F9-E9 -> 0 | H9: 2 | I9: 2 | J9: =I9-H9 -> 0 | K9: 2 | L9: 2 | M9: =L9-K9 -> 0 | N9: 2 | O9: 2 | P9: =O9-N9 -> 0 | Q9: 2 | R9: 2 | S9: =R9-Q9 -> 0 | T9: 2 | U9: 2 | V9: =U9-T9 -> 0 | W9: 2 | X9: 2 | Y9: =X9-W9 -> 0 | Z9: 2 | AA9: 2 | AB9: =AA9-Z9 -> 0 | AC9: 2 | AD9: 2 | AE9: 2 | AF9: 2 | AG9: 2 | AH9: 1.5 | AI9: 2 | AK9: 2 | AM9: 2 | AO9: 2 | AQ9: 2 | AS9: 2 | AU9: 2 | AW9: 2
A10: 07-1200-1100H | B10: 2 | C10: 2 | D10: =C10-B10 -> 0 | E10: 2 | F10: 2 | G10: =F10-E10 -> 0 | H10: 2 | I10: 2 | J10: =I10-H10 -> 0 | K10: 1 | L10: 1 | M10: =L10-K10 -> 0 | N10: 1 | O10: 1 | P10: =O10-N10 -> 0 | Q10: 1 | R10: 1 | S10: =R10-Q10 -> 0 | T10: 1 | U10: 1 | V10: =U10-T10 -> 0 | W10: 1 | X10: 1 | Y10: =X10-W10 -> 0 | Z10: 1 | AA10: 1 | AB10: =AA10-Z10 -> 0 | AC10: 1 | AD10: 1 | AE10: 1 | AF10: 1 | AG10: 1 | AH10: 1 | AI10: 1 | AJ10: 1 | AK10: 1 | AL10: 1 | AM10: 2 | AN10: 2 | AO10: 2 | AP10: 1.8 | AQ10: 2 | AS10: 2 | AU10: 2 | AW10: 2
A11: 07-1200-1125H | B11: 2 | C11: 2 | D11: =C11-B11 -> 0 | E11: 2 | F11: 2 | G11: =F11-E11 -> 0 | H11: 2 | I11: 0 | J11: =I11-H11 -> -2 | K11: 2 | L11: 0 | M11: =L11-K11 -> -2 | N11: 2 | O11: 0 | P11: =O11-N11 -> -2 | Q11: 2 | R11: 0 | S11: =R11-Q11 -> -2 | T11: 2 | U11: 0 | V11: =U11-T11 -> -2 | W11: 2 | X11: 0 | Y11: =X11-W11 -> -2 | Z11: 2 | AB11: =AA11-Z11 -> -2 | AC11: 2 | AE11: 2 | AG11: 2 | AI11: 2 | AK11: 2 | AM11: 2 | AO11: 2 | AQ11: 2 | AS11: 2 | AU11: 2 | AW11: 2
A12: 07-1200-1146H | B12: 1 | C12: 1 | D12: =C12-B12 -> 0 | E12: 1.5 | F12: 1.5 | G12: =F12-E12 -> 0 | H12: 1 | I12: 1 | J12: =I12-H12 -> 0 | K12: 0 | L12: 0 | M12: =L12-K12 -> 0 | N12: 0 | O12: 0 | P12: =O12-N12 -> 0 | Q12: 0 | R12: 3.5 | S12: =R12-Q12 -> 3.5 | T12: 0 | U12: 1 | V12: =U12-T12 -> 1 | W12: 0 | X12: 1 | Y12: =X12-W12 -> 1 | Z12: 0 | AB12: =AA12-Z12 -> 0 | AC12: 0 | AE12: 1 | AG12: 1 | AI12: 1 | AK12: 1 | AM12: 1 | AO12: 1 | AQ12: 1 | AS12: 1 | AU12: 1 | AW12: 1
A13: 07-1200-1147H | B13: 1.25 | C13: 1.25 | D13: =C13-B13 -> 0 | E13: 1.25 | F13: 1.25 | G13: =F13-E13 -> 0 | H13: 1.25 | I13: 1.25 | J13: =I13-H13 -> 0 | K13: 1.25 | L13: 1.25 | M13: =L13-K13 -> 0 | N13: 1.25 | O13: 1.25 | P13: =O13-N13 -> 0 | Q13: 1.25 | R13: 1.25 | S13: =R13-Q13 -> 0 | T13: 1.25 | U13: 1.25 | V13: =U13-T13 -> 0 | W13: 1.25 | X13: 1.25 | Y13: =X13-W13 -> 0 | Z13: 1.25 | AA13: 1.25 | AB13: =AA13-Z13 -> 0 | AC13: 1.25 | AD13: 1.15 | AE13: 1.25 | AG13: 1.25 | AI13: 1.25 | AK13: 1.25 | AM13: 1.25 | AO13: 1.25 | AQ13: 1.25 | AS13: 1.25 | AU13: 1.25 | AW13: 1.25
A14: 07-1200-1149H | B14: 6 | C14: 6 | D14: =C14-B14 -> 0 | E14: 6 | F14: 6 | G14: =F14-E14 -> 0 | H14: 6.5 | I14: 6.5 | J14: =I14-H14 -> 0 | K14: 6.5 | L14: 6.5 | M14: =L14-K14 -> 0 | N14: 6.5 | O14: 6.5 | P14: =O14-N14 -> 0 | Q14: 6.5 | R14: 6.5 | S14: =R14-Q14 -> 0 | T14: 6.5 | U14: 6.5 | V14: =U14-T14 -> 0 | W14: 6.5 | X14: 6.5 | Y14: =X14-W14 -> 0 | Z14: 6.5 | AA14: 6.28 | AB14: =AA14-Z14 -> -0.22 | AC14: 6.5 | AE14: 6.5 | AG14: 6.5 | AI14: 6.5 | AK14: 6.5 | AM14: 6.5 | AO14: 6.5 | AQ14: 6.5 | AS14: 6.5 | AU14: 6.5
A15: 07-1200-1175H | B15: 0.75 | C15: 0.75 | D15: =C15-B15 -> 0 | E15: 0.75 | F15: 0.75 | G15: =F15-E15 -> 0 | H15: 0.75 | I15: 0.75 | J15: =I15-H15 -> 0 | K15: 0.75 | L15: 0.75 | M15: =L15-K15 -> 0 | N15: 0.75 | O15: 0.75 | P15: =O15-N15 -> 0 | Q15: 0.75 | R15: 0.75 | S15: =R15-Q15 -> 0 | T15: 0.75 | U15: 0.75 | V15: =U15-T15 -> 0 | W15: 0.75 | X15: 0.75 | Y15: =X15-W15 -> 0 | Z15: 1 | AA15: 1 | AB15: =AA15-Z15 -> 0 | AC15: 1 | AD15: 1 | AE15: 1 | AF15: 1 | AG15: 1 | AH15: 1 | AI15: 1 | AJ15: 1 | AK15: 1 | AL15: 1 | AM15: 1 | AO15: 1 | AQ15: 1 | AS15: 1 | AU15: 1 | AW15: 1
A16: 07-1200-1177H | B16: 1.65 | C16: 1.65 | D16: =C16-B16 -> 0 | E16: 1.65 | F16: 1.65 | G16: =F16-E16 -> 0 | H16: 1.65 | I16: 1.2 | J16: =I16-H16 -> -0.45 | K16: 1.65 | L16: 0 | M16: =L16-K16 -> -1.65 | N16: 1.65 | O16: 0.6 | P16: =O16-N16 -> -1.05 | Q16: 1.65 | R16: 0.9 | S16: =R16-Q16 -> -0.75 | T16: 1.65 | U16: 0.9 | V16: =U16-T16 -> -0.75 | W16: 1.65 | X16: 0 | Y16: =X16-W16 -> -1.65 | Z16: 1.65 | AA16: 0 | AB16: =AA16-Z16 -> -1.65 | AC16: 1.65 | AE16: 1.65 | AG16: 1.65 | AI16: 1.65 | AK16: 1.65 | AM16: 1.65 | AO16: 1.65 | AQ16: 1.65 | AS16: 1.65 | AU16: 3.3
A17: 07-1200-1221H | B17: 0 | C17: 0 | D17: =C17-B17 -> 0 | E17: 0 | G17: =F17-E17 -> 0 | H17: 0 | I17: 0 | J17: =I17-H17 -> 0 | K17: 0 | L17: 0 | M17: =L17-K17 -> 0 | N17: 4 | O17: 2.2 | P17: =O17-N17 -> -1.8 | Q17: 4 | R17: 0 | S17: =R17-Q17 -> -4 | T17: 4 | U17: 1 | V17: =U17-T17 -> -3 | W17: 4 | X17: 0 | Y17: =X17-W17 -> -4 | Z17: 2 | AA17: 0 | AB17: =AA17-Z17 -> -2 | AC17: 2 | AE17: 2 | AG17: 2 | AI17: 2 | AK17: 2 | AM17: 2 | AO17: 2 | AQ17: 2 | AS17: 2 | AU17: 2 | AW17: 2
A18: 07-2700-0225H | B18: 2 | C18: 2 | D18: =C18-B18 -> 0 | E18: 2 | F18: 2 | G18: =F18-E18 -> 0 | H18: 2 | I18: 2 | J18: =I18-H18 -> 0 | K18: 2 | L18: 2 | M18: =L18-K18 -> 0 | N18: 2 | O18: 2 | P18: =O18-N18 -> 0 | Q18: 2 | R18: 2 | S18: =R18-Q18 -> 0 | T18: 2 | U18: 2 | V18: =U18-T18 -> 0 | W18: 2 | X18: 2 | Y18: =X18-W18 -> 0 | Z18: 2 | AA18: 2 | AB18: =AA18-Z18 -> 0 | AC18: 2 | AD18: 2 | AE18: 2 | AF18: 2 | AG18: 2 | AH18: 2 | AI18: 2 | AJ18: 2 | AK18: 2 | AL18: 1 | AM18: 2 | AO18: 2 | AQ18: 2 | AS18: 2 | AU18: 2 | AW18: 2
A19: 07-2700-0253H | B19: 0 | C19: 0 | D19: =C19-B19 -> 0 | E19: 0 | G19: =F19-E19 -> 0 | H19: 1.4 | I19: 0 | J19: =I19-H19 -> -1.4 | K19: 1.4 | L19: 0 | M19: =L19-K19 -> -1.4 | N19: 0.7 | O19: 0 | P19: =O19-N19 -> -0.7 | Q19: 0.7 | R19: 0 | S19: =R19-Q19 -> -0.7 | T19: 0.7 | U19: 0 | V19: =U19-T19 -> -0.7 | W19: 0.7 | X19: 0.7 | Y19: =X19-W19 -> 0 | Z19: 0.7 | AA19: 0.7 | AB19: =AA19-Z19 -> 0 | AC19: 0.7 | AD19: 0.6 | AE19: 0.7 | AG19: 0.7 | AI19: 0.7 | AK19: 0.7 | AM19: 0.7 | AO19: 0.7 | AQ19: 0.7 | AS19: 0.7 | AU19: 0.7 | AW19: 0.7
A20: 07-2700-0270H | B20: 0.75 | C20: 0.75 | D20: =C20-B20 -> 0 | E20: 0.75 | F20: 0.75 | G20: =F20-E20 -> 0 | H20: 0.75 | I20: 0.75 | J20: =I20-H20 -> 0 | K20: 0.75 | L20: 0.75 | M20: =L20-K20 -> 0 | N20: 0.75 | O20: 0.15 | P20: =O20-N20 -> -0.6 | Q20: 0.75 | R20: 0 | S20: =R20-Q20 -> -0.75 | T20: 0.75 | U20: 0 | V20: =U20-T20 -> -0.75 | W20: 0.75 | X20: 0.75 | Y20: =X20-W20 -> 0 | Z20: 0.75 | AA20: 0.75 | AB20: =AA20-Z20 -> 0 | AC20: 0.75 | AD20: 0.75 | AE20: 0.75 | AF20: 0.75 | AG20: 0.75 | AI20: 0.75 | AK20: 0.75 | AM20: 0.75 | AO20: 0.75 | AQ20: 0.75 | AS20: 0.75 | AU20: 0.75 | AW20: 0.75
A21: 07-2700-0282H | B21: 0.6 | C21: 0.6 | D21: =C21-B21 -> 0 | E21: 0.6 | F21: 0.6 | G21: =F21-E21 -> 0 | H21: 0.6 | I21: 0.6 | J21: =I21-H21 -> 0 | K21: 0.6 | L21: 0.6 | M21: =L21-K21 -> 0 | N21: 0.6 | O21: 0.17 | P21: =O21-N21 -> -0.43 | Q21: 0.6 | R21: 0.6 | S21: =R21-Q21 -> 0 | T21: 0.6 | U21: 0.6 | V21: =U21-T21 -> 0 | W21: 0.6 | X21: 0 | Y21: =X21-W21 -> -0.6 | Z21: 0.6 | AA21: 0.6 | AB21: =AA21-Z21 -> 0 | AC21: 0.6 | AE21: 0.6 | AG21: 0.6 | AI21: 0.6 | AK21: 0.6 | AM21: 0.6 | AO21: 0.6 | AQ21: 0.6 | AS21: 0.6 | AU21: 0.6 | AW21: 0.6
A22: 07-2700-0304H | B22: 0 | C22: 0 | D22: =C22-B22 -> 0 | E22: 0 | G22: =F22-E22 -> 0 | H22: 0 | I22: 0 | J22: =I22-H22 -> 0 | K22: 0 | L22: 0 | M22: =L22-K22 -> 0 | N22: 1 | O22: 0 | P22: =O22-N22 -> -1 | Q22: 1 | R22: 0 | S22: =R22-Q22 -> -1 | T22: 1 | U22: 0 | V22: =U22-T22 -> -1 | W22: 1 | X22: 0 | Y22: =X22-W22 -> -1 | Z22: 1 | AA22: 1 | AB22: =AA22-Z22 -> 0 | AC22: 1 | AD22: 1 | AE22: 1 | AG22: 1 | AI22: 1 | AK22: 1 | AM22: 1 | AO22: 1 | AQ22: 1 | AS22: 1 | AU22: 1 | AW22: 1
A23: 07-2700-0327H | B23: 1.8 | C23: 1.8 | D23: =C23-B23 -> 0 | G23: =F23-E23 -> 0 | J23: =I23-H23 -> 0 | L23: 0 | M23: =L23-K23 -> 0 | O23: 0 | P23: =O23-N23 -> 0 | Q23: 0.6 | R23: 0.6 | S23: =R23-Q23 -> 0 | U23: 0 | V23: =U23-T23 -> 0 | X23: 0 | Y23: =X23-W23 -> 0 | AA23: 0 | AB23: =AA23-Z23 -> 0 | AE23: 0.6 | AG23: 0.6 | AI23: 0.6 | AK23: 0.6 | AM23: 0.6 | AO23: 0.6 | AQ23: 0.6
A24: 07-2700-0332H | B24: 2 | C24: 2 | D24: =C24-B24 -> 0 | E24: 0 | G24: =F24-E24 -> 0 | H24: 0 | I24: 0 | J24: =I24-H24 -> 0 | K24: 0 | L24: 0 | M24: =L24-K24 -> 0 | N24: 0 | O24: 0 | P24: =O24-N24 -> 0 | Q24: 2 | R24: 2 | S24: =R24-Q24 -> 0 | T24: 2 | U24: 0 | V24: =U24-T24 -> -2 | W24: 2 | X24: 2 | Y24: =X24-W24 -> 0 | Z24: 2 | AA24: 0 | AB24: =AA24-Z24 -> -2 | AC24: 2 | AE24: 0 | AG24: 0 | AI24: 0 | AK24: 0 | AM24: 0 | AO24: 2 | AQ24: 2 | AS24: 2 | AU24: 2 | AW24: 2
A25: 07-2700-0333H | B25: 2 | C25: 2 | D25: =C25-B25 -> 0 | E25: 0 | G25: =F25-E25 -> 0 | H25: 0 | I25: 0 | J25: =I25-H25 -> 0 | K25: 0 | L25: 0 | M25: =L25-K25 -> 0 | N25: 2 | O25: 2 | P25: =O25-N25 -> 0 | Q25: 2 | R25: 2 | S25: =R25-Q25 -> 0 | T25: 2 | U25: 0 | V25: =U25-T25 -> -2 | W25: 2 | X25: 2 | Y25: =X25-W25 -> 0 | Z25: 2 | AA25: 0 | AB25: =AA25-Z25 -> -2 | AC25: 0 | AE25: 0 | AG25: 0 | AI25: 0 | AK25: 0 | AM25: 0 | AO25: 2 | AQ25: 2 | AS25: 2 | AU25: 2 | AW25: 2
A26: 07-2800-0420H | B26: 0 | C26: 0 | D26: =C26-B26 -> 0 | E26: 0 | G26: =F26-E26 -> 0 | H26: 2 | I26: 1.982 | J26: =I26-H26 -> -0.018 | K26: 2 | L26: 0 | M26: =L26-K26 -> -2 | N26: 1 | O26: 1 | P26: =O26-N26 -> 0 | Q26: 1 | R26: 0 | S26: =R26-Q26 -> -1 | T26: 1 | U26: 0 | V26: =U26-T26 -> -1 | W26: 1 | X26: 0 | Y26: =X26-W26 -> -1 | Z26: 1 | AA26: 0 | AB26: =AA26-Z26 -> -1 | AC26: 1 | AE26: 1 | AG26: 1 | AI26: 1 | AK26: 1 | AM26: 1 | AO26: 1 | AQ26: 1 | AS26: 1 | AU26: 1 | AW26: 1
A27: 07-2800-0455H | B27: 0 | C27: 0 | D27: =C27-B27 -> 0 | E27: 0 | G27: =F27-E27 -> 0 | H27: 2 | I27: 0 | J27: =I27-H27 -> -2 | K27: 2 | L27: 0 | M27: =L27-K27 -> -2 | N27: 1 | O27: 0 | P27: =O27-N27 -> -1 | Q27: 1 | R27: 0 | S27: =R27-Q27 -> -1 | T27: 1 | U27: 0 | V27: =U27-T27 -> -1 | W27: 1 | X27: 0 | Y27: =X27-W27 -> -1 | Z27: 1 | AA27: 0 | AB27: =AA27-Z27 -> -1 | AC27: 1 | AE27: 1 | AG27: 1 | AI27: 1 | AK27: 1 | AM27: 1 | AO27: 1.148
A28: 07-2800-0513H | B28: 6 | C28: 6 | D28: =C28-B28 -> 0 | E28: 6 | F28: 6 | G28: =F28-E28 -> 0 | H28: 6 | I28: 6 | J28: =I28-H28 -> 0 | K28: 6 | L28: 6 | M28: =L28-K28 -> 0 | N28: 6 | O28: 5.12 | P28: =O28-N28 -> -0.88 | Q28: 6 | R28: 6 | S28: =R28-Q28 -> 0 | T28: 6 | U28: 6 | V28: =U28-T28 -> 0 | W28: 6 | X28: 4 | Y28: =X28-W28 -> -2 | Z28: 6 | AA28: 6 | AB28: =AA28-Z28 -> 0 | AC28: 6 | AE28: 6 | AG28: 6 | AI28: 6 | AK28: 6 | AM28: 6 | AO28: 6 | AQ28: 6 | AS28: 6 | AU28: 6 | AW28: 6
A29: 07-2800-0518H | B29: 0 | C29: 0 | D29: =C29-B29 -> 0 | E29: 0 | G29: =F29-E29 -> 0 | H29: 2 | I29: 0 | J29: =I29-H29 -> -2 | K29: 2 | L29: 0 | M29: =L29-K29 -> -2 | N29: 1 | O29: 1 | P29: =O29-N29 -> 0 | Q29: 1 | R29: 0 | S29: =R29-Q29 -> -1 | T29: 1 | U29: 0 | V29: =U29-T29 -> -1 | W29: 1 | X29: 0 | Y29: =X29-W29 -> -1 | Z29: 1 | AA29: 0 | AB29: =AA29-Z29 -> -1 | AC29: 1 | AE29: 1 | AG29: 1 | AI29: 1 | AK29: 1 | AM29: 1 | AO29: 1 | AQ29: 1 | AS29: 1 | AU29: 1 | AW29: 1
A30: 07-2800-0555H | B30: 3 | C30: 3 | D30: =C30-B30 -> 0 | E30: 1.3 | F30: 1.3 | G30: =F30-E30 -> 0 | H30: 1.3 | I30: 1.3 | J30: =I30-H30 -> 0 | K30: 1.3 | L30: 1.3 | M30: =L30-K30 -> 0 | N30: 1.3 | O30: 1.3 | P30: =O30-N30 -> 0 | Q30: 1.3 | R30: 1.3 | S30: =R30-Q30 -> 0 | T30: 1.3 | U30: 0.746 | V30: =U30-T30 -> -0.554 | W30: 1.3 | X30: 1.3 | Y30: =X30-W30 -> 0 | Z30: 1.3 | AA30: 1.3 | AB30: =AA30-Z30 -> 0 | AC30: 1.3 | AD30: 1.3 | AE30: 1.3 | AF30: 1.3 | AG30: 1.3 | AH30: 0.2 | AI30: 1.3 | AK30: 1.3 | AM30: 1.3 | AO30: 1.3 | AQ30: 1.3 | AS30: 1.3 | AU30: 1.3 | AW30: 1.3

Sheet Sales_daily_plan_follow (2)
AB1: Workdays | AC1: 19
A2: 1. Plan must be increased ( 80kpcs daily bundling , 90kpcs packaging) | AB2: DC Stock daily increasement plan | AC2: =AC6/AC1 -> 0
B3: 12-31 záró | AE3: Sales + DC
AC4: Output | AD4: =AC7+AC9 -> 0 | AE4: =AC7+AC9 -> 0
B5: 45628 | C5: 45629 | D5: 45630 | E5: 45631 | F5: 45632 | G5: 45635 | H5: 45636 | I5: 45637 | J5: 45638 | K5: 45639 | L5: 45642 | M5: 45643 | N5: 45644 | O5: 45645 | P5: 45646 | AB5: Planned from next month (sales price) | AD5: =AC8+AC10 -> 286233.07 | AE5: =AD5 -> 286233.07
A6: Draft Plan | AB6: Planned from next month DC price | AE6: =AE5-AE4 -> 286233.07
A7: Sales Plan | AC7: =SUM(B7:AB7) -> 0
A8: Sales EUR (actual) | B8: 6604.804 | C8: 8756 | D8: 36319.14 | E8: 0 | F8: 22047.6 | G8: 0 | H8: 0 | I8: 14570.13 | J8: 23681.3 | K8: 0 | L8: 14858 | M8: 6644.22 | N8: 81129.64 | O8: 44108.7 | P8: 27513.54 | AC8: =SUM(B8:AB8) -> 286233.07 | AD8: On DC
A9: FG Stock Plan | AB9: Planned DC increasement | AC9: =X9-B12 -> 0 | AD9: =AC9-B12 -> 0
A10: FG Actual DC Robi | AB10: DC Stock increasement actual | AC10: =(X10-B12) -> 0 | AD10: =AC10 -> 0
A11: Actual FG stock PC. | B11: 565285 | C11: 559285 | D11: 540285 | E11: 562685 | F11: 562685 | G11: 643661 | H11: 648661 | I11: 631885 | J11: 638885 | K11: 657392 | L11: 684520 | M11: 706325 | N11: 572829 | O11: 560032 | P11: 518011 | AB11: Qty increasement | AC11: =X11-B13 -> 0
A12: Open in DC | AA12: =AA10-B12 -> 0 | AE12: =165+292 -> 457
A13: Open qtys.
X51: 29 1152 EUR | AA51: =X8-1152 -> -1152
X52: 30 4432 EUR | AA52: =Y8-4432 -> -4432
Q53: SPC | X53: 31 1610 | AA53: =AA8-1610 -> -1610
Q54: Construction

Sheet PlanFollow (Factory out)
A1: Production plan | F1: Completed | H1: =IF(C34=0,0,C34/B34) -> 1
A2: Follow | F2: Time prop. | H2: =IF(C35=0,0,C35/(B35*C7)) -> 1
B6: Workday | C6: =Headcount!F7 -> 15
B7: Actual day | C7: =Headcount!F8 -> 15
A8: Day | B8: Planned Qty | C8: Completed qty | D8: Difference
A10: 45628 | D10: =IF(C10="",0,C10-B10) -> 0
A11: 45629 | D11: =IF(C11="",0,C11-B11) -> 0
A12: 45630 | D12: =IF(C12="",0,C12-B12) -> 0
A13: 45631 | D13: =IF(C13="",0,C13-B13) -> 0
A14: 45632 | D14: =IF(C14="",0,C14-B14) -> 0
A15: 45633 | D15: =IF(C15="",0,C15-B15) -> 0
A16: 45634 | D16: =IF(C16="",0,C16-B16) -> 0
A17: 45635 | D17: =IF(C17="",0,C17-B17) -> 0
A18: 45636 | D18: =IF(C18="",0,C18-B18) -> 0
A19: 45637 | B19: 7.776 | C19: 7.776 | D19: =IF(C19="",0,C19-B19) -> 0
A20: 45638 | B20: 0.02 | C20: 0.02 | D20: =IF(C20="",0,C20-B20) -> 0
A21: 45639 | B21: 0.02 | C21: 0.02 | D21: =IF(C21="",0,C21-B21) -> 0
A22: 45640 | D22: =IF(C22="",0,C22-B22) -> 0
A23: 45641 | D23: =IF(C23="",0,C23-B23) -> 0
A24: 45642 | B24: 3.125 | C24: 3.125 | D24: =IF(C24="",0,C24-B24) -> 0
A25: 45643 | D25: =IF(C25="",0,C25-B25) -> 0
A26: 45644 | B26: 22.02 | C26: 22.02 | D26: =IF(C26="",0,C26-B26) -> 0
A27: 45645 | D27: =IF(C27="",0,C27-B27) -> 0
A28: 45646 | B28: 213.2 | C28: 213.2 | D28: =IF(C28="",0,C28-B28) -> 0
B34: =SUM(B10:B33) -> 246.161 | C34: =SUM(C10:C33) -> 246.161 | D34: =SUM(D10:D33) -> 0
B35: =B34/'Prod.Output Summ'!B2 -> 16.410733 | C35: =C34 -> 246.161

Sheet PlanFollow (Finished)
A1: Production plan | F1: Completed | H1: =IF(C34=0,0,C34/B34) -> 1
A2: Follow | F2: Time prop. | H2: =IF(C35=0,0,C35/(B35*C7)) -> 1
B6: Workday | C6: =Headcount!F7 -> 15
B7: Actual day | C7: =Headcount!F8 -> 15
A8: Day | B8: Planned Qty | C8: Completed qty | D8: Difference
A10: ='PlanFollow (Factory out)'!A10 -> 45628 | D10: =IF(C10="",0,C10-B10) -> 0
A11: ='PlanFollow (Factory out)'!A11 -> 45629 | D11: =IF(C11="",0,C11-B11) -> 0
A12: ='PlanFollow (Factory out)'!A12 -> 45630 | B12: 6.07 | C12: 6.07 | D12: =IF(C12="",0,C12-B12) -> 0
A13: ='PlanFollow (Factory out)'!A13 -> 45631 | D13: =IF(C13="",0,C13-B13) -> 0
A14: ='PlanFollow (Factory out)'!A14 -> 45632 | B14: 0.1 | C14: 0.1 | D14: =IF(C14="",0,C14-B14) -> 0
A15: ='PlanFollow (Factory out)'!A15 -> 45633 | D15: =IF(C15="",0,C15-B15) -> 0
A16: ='PlanFollow (Factory out)'!A16 -> 45634 | D16: =IF(C16="",0,C16-B16) -> 0
A17: ='PlanFollow (Factory out)'!A17 -> 45635 | B17: 6.43 | C17: 6.43 | D17: =IF(C17="",0,C17-B17) -> 0
A18: ='PlanFollow (Factory out)'!A18 -> 45636 | D18: =IF(C18="",0,C18-B18) -> 0
A19: ='PlanFollow (Factory out)'!A19 -> 45637 | B19: 17 | C19: 17 | D19: =IF(C19="",0,C19-B19) -> 0
A20: ='PlanFollow (Factory out)'!A20 -> 45638 | B20: 4.75 | C20: 4.75 | D20: =IF(C20="",0,C20-B20) -> 0
A21: ='PlanFollow (Factory out)'!A21 -> 45639 | D21: =IF(C21="",0,C21-B21) -> 0
A22: ='PlanFollow (Factory out)'!A22 -> 45640 | D22: =IF(C22="",0,C22-B22) -> 0
A23: ='PlanFollow (Factory out)'!A23 -> 45641 | D23: =IF(C23="",0,C23-B23) -> 0
A24: ='PlanFollow (Factory out)'!A24 -> 45642 | B24: 3 | C24: 3 | D24: =IF(C24="",0,C24-B24) -> 0
A25: ='PlanFollow (Factory out)'!A25 -> 45643 | B25: 9.16 | C25: 9.16 | D25: =IF(C25="",0,C25-B25) -> 0
A26: ='PlanFollow (Factory out)'!A26 -> 45644 | B26: 14 | C26: 14 | D26: =IF(C26="",0,C26-B26) -> 0
A27: ='PlanFollow (Factory out)'!A27 -> 45645 | B27: 41 | C27: 41 | D27: =IF(C27="",0,C27-B27) -> 0
A28: ='PlanFollow (Factory out)'!A28 -> 45646 | B28: 135.705 | C28: 135.705 | D28: =IF(C28="",0,C28-B28) -> 0
B34: =SUM(B10:B33) -> 237.215 | C34: =SUM(C10:C33) -> 237.215 | D34: =B34-C34 -> 0
B35: =B34/C6 -> 15.814333 | C35: =C34 -> 237.215

Sheet Prod.Output Summ
A1: Workday and time proportional data | C1: Plan changes in price | M1: Perfomance data
A2: Total workday | B2: =Headcount!F7 -> 15 | C2: REV | D2: Date | E2: + Sales | F2: - Sales | G2: + DC | H2: - DC | I2: + KFT Purch | J2: - KFT Purch. | K2: Reason of change | M2: Original plan follow | R2: Planned KFT prod. purchase cost | U2: =B16+I26-J26 -> 0
A3: Elapsed workday | B3: =Headcount!F8 -> 15 | C3: V04 | D3: 45629 | E3: 4121.6 | F3: 384 | K3: Alapanyaghiány: -1k 12-1428 | M3: Original Plan | O3: Actual | P3: Perf. | R3: Palnned KFT prod DC cost [KFTPURCHDC] | U3: =P17 -> 235627
C4: V05 | D4: 45635 | F4: 8620.58 | K4: Alapanyaghiány: -8k 2701-0425, -1,5k 27-0449, -2k 20-0406 | M4: Output [Qty] | N4: 484204 | O4: =Prod.Output!K2 -> 482422 | P4: =O4/N4 -> 0.99631973 | R4: Planned finished FG DC cost [KFTFGDC] | U4: =P16 -> 0
A5: Actual output in sales price | B5: =Prod.Output!J2 -> 297320.12 | C5: V06 | D5: 45638 | E5: 3750 | F5: 6869.88 | K5: Alapanyaghiány: -6k 12-1395, -2k 1201-1221 (V100-0106), -0,657k 1201-1204 (V101-0122),-1k 2701-0328, -0,086k 20-0635 (törölték) | M5: WH
A6: Time prop. Out in sales price | B6: =(B14/B2)*B3 -> 304159.68 | C6: V07 | D6: 45643 | F6: 1401.4 | K6: Alapanyaghiány: -1,4k 2701-0429 | M6: Output [Price] | N6: =B14 -> 304159.68 | O6: =Prod.Output!J2 -> 297320.12 | P6: =O6/N6 -> 0.97751326 | R6: KFTFGDC-KFTPURCHDC > FINISHFGDC | U6: =U3-U2 -> 235627
C7: V08 | D7: 45646 | E7: 4857.54 | M7: RM usage summarize
A8: Actual output in DC price | B8: =Prod.Output!L2 -> 235628.56 | C8: V09 | M8: Planned RM usage (shipping cost not inc.) | Q8: < In case of change must be updated manualy
A9: Time prop. Out in DC price | B9: =((P15/B2)*B3) -> 235627 | C9: V10 | M9: RM usage vs. Sales | P9: =P8/O14 -> 0
C10: V11 | M10: RM usage vs. Out | P10: =P8/O15 -> 0 | R10: Actual Sales | S10: Actual Margin
A11: Achievement (Time prop.) Original | B11: =B5/B6 -> 0.97751326 | C11: V12 | R11: =Sales_daily_plan_follow!AC10 -> 286233.07 | S11: =1-(Prod.Output!L2/Prod.Output!J2) -> 0.20749203
C12: V13 | O12: Sales Price | P12: DC price
A13: Original plan data | C13: V14 | M13: Sample Sales Plan | O13: 5805 | R13: RM Cost
A14: Orig. Output plan in EUR Sales | B14: 304159.68 | C14: V15 | M14: Sales Plan (Without samp.) | O14: =Sales_daily_plan_follow!AC9 -> 292030 | P14: 221401 | R14: 206592
A15: Orig. Output plan in EUR DC | B15: 221733.16 | C15: V16 | M15: Output plan (With samp.) | O15: =(B14+E26)-F26+O13 -> 305417.96 | P15: 235627
A16: Orig. KFT produced purch. Price | C16: V17 | M16: Finished output Plan
C17: V18 | M17: KFT Production output Plan | O17: =O15-O16 -> 305417.96 | P17: =P15-P16 -> 235627
A18: Calculated field | C18: V19 | M18: KFT prod ratio | O18: =O17/O15 -> 1 | P18: =P17/P15 -> 1
A19: Manual input | C19: V20 | M19: Finished ratio | O19: =O16/O15 -> 0 | P19: =P16/P15 -> 0
C20: V21 | M20: Planned DC stock movement (Output - Sales) | P20: =P15-P14 -> 14226
C21: V22 | P21: =1-P15/P14 -> -0.064254452
C22: V23
C23: V24 | M23: Manual Productivity | P23: Scrap Summarise
C24: V25 | M24: Shield | N24: =IF(TYPE(Shielding!M31)=16,0,Shielding!M31) -> 1.1751 | P24: Finish | R24: ='PlanFollow (Finished)'!C34*1000 -> 237215
C25: V26 | M25: Bending | N25: =IF(TYPE(Bending!O31)=16,0,Bending!O31) -> 1.04413 | P25: KFT prod. | R25: ='PlanFollow (Factory out)'!C34*1000 -> 246161
E26: =SUM(E3:E25) -> 12729.14 | F26: =SUM(F3:F25) -> 17275.86 | G26: =SUM(G3:G25) -> 0 | H26: =SUM(H3:H25) -> 0 | I26: =SUM(I3:I25) -> 0 | J26: =SUM(J3:J25) -> 0 | M26: ATT Tape | N26: =IF(TYPE('Attach Tape'!O31)=16,0,'Attach Tape'!O31) -> 0.95436 | P26: Reject With AA/TO | R26: =CAOI!O27+ADAMI!N27+'AD Auto PKY'!N33+CYT!N33+'Auto Bending'!N31+APIM!L31+APIM!M31+APIM!N31+USB!O31+'SS Auto Bending'!O32+'Conti Final Insp'!K33 -> 4020 | S26: =R26/R25 -> 0.016330775
M27: Handline mark | N27: =IF(TYPE('Hand L.mark'!O31)=16,0,'Hand L.mark'!O31) -> 1.007475 | P27: Reject without AA/TO | R27: =CAOI!O27+ADAMI!O27+'AD Auto PKY'!N34+CYT!N34+'Auto Bending'!N31+APIM!L31+APIM!M31+APIM!N31+USB!K34+'Visual Inspection'!K34+MIM!O31+'SS Auto Bending'!O32+'Conti Final Insp'!K34+'Hot Stamp'!M31+Shielding!P31+Bending!M32+'Attach Tape'!M32+'Hand L.mark'!L32+'Bending+ATT(Kombi sablon)'!M32 -> 2830 | S27: =R27/R25 -> 0.011496541
M28: ATT+Bending | N28: =IF(TYPE('Bending+ATT(Kombi sablon)'!O31)=16,0,'Bending+ATT(Kombi sablon)'!O31) -> 0.96949286 | P28: Ink-Jet BS-el együtt | Q28: 138 | R28: =R27+Q28 -> 2968
N29: =AVERAGE(N24:N28) -> 1.0301116 | P29: 1200-1368 CYT elüti a MA és S méreteket: | S29: =S31-129 -> -129 | T29: =T31-129 -> -129 | U29: =U31-129 -> 566 | V29: =V31-(129+22+27) -> 719 | W29: =W31-(129+22+27+45+10) -> 867 | X29: =X31-233 -> 1052 | Y29: =Y31-233 -> 1212 | Z29: =Z31-233 -> 1363 | AA29: =AA31-233 -> 1384 | AB29: =AB31-233 -> 2007 | AC29: =AC31-233 -> 2193 | AD29: =AD31-233 -> 2313 | AE29: =AE31-233 -> 2524 | ... AG29: =AG31-233 -> 2735
S30: 2 | T30: 3 | U30: 4 | V30: 5 | W30: 6 | X30: 9 | Y30: 10 | Z30: 11 | AA30: 12 | AB30: 13 | AC30: 16 | AD30: 17 | AE30: 18 | AF30: 19 | AG30: 20
Q31: =P27 -> Reject without AA/TO | S31: 0 | T31: 0 | U31: 695 | V31: 897 | W31: 1100 | X31: 1285 | Y31: 1445 | Z31: 1596 | AA31: 1617 | AB31: 2240 | AC31: 2426 | AD31: 2546 | AE31: 2757 | AF31: 2896 | AG31: 2968
D32: Corrected Efficency (excess) | E32: Nap / Day | F32: Cél / Target (daily) | G32: Átlag / AVG | H32: Shielding | I32: Bending | J32: Attach tape | K32: Attach+Bending | L32: Hand line marking | M32: Kumulált átlag / AVG Cumulative | N32: Kumulált átlag / AVG Cumulative-Corrected Efficency (excess) | O32: Összes létszám | Q32: =P25 -> KFT prod. | S32: 10800 | T32: 11600 | U32: 32600 | V32: 51000 | W32: 61000 | X32: 91376 | Y32: 104976 | Z32: 129976 | AA32: 157036 | AB32: 185536 | AC32: 211161 | AD32: 226661 | AE32: 231461 | AF32: 241161 | AG32: 246161
C33: =D33 -> 1.1042059 | D33: =G33*Headcount!S10 -> 1.1042059 | E33: =Headcount!A10 -> 2 | F33: 1 | G33: =AVERAGE(H33:L33) -> 0.938575 | H33: =Shielding!M9 -> 1.0516 | I33: =Bending!O9 -> - | J33: ='Attach Tape'!O9 -> 0.6759 | K33: ='Bending+ATT(Kombi sablon)'!O9 -> 1.0229 | L33: ='Hand L.mark'!O9 -> 1.0039 | M33: =G33 -> 0.938575 | N33: =D33 -> 1.1042059 | P33: =O33/N33 -> 0 | Q33: KUMULÁLT / Cumulative | S33: =S31/S32 -> 0 | T33: =T31/T32 -> 0 | U33: =U31/U32 -> 0.021319018 | V33: =V31/V32 -> 0.017588235 | W33: =W31/W32 -> 0.018032787 | X33: =X31/X32 -> 0.014062774 | Y33: =Y31/Y32 -> 0.013765051 | Z33: =Z31/Z32 -> 0.01227919 | ... AG33: =AG31/AG32 -> 0.01205715
C34: =AVERAGE($D$33:D34) -> 1.2067488 | D34: =G34*Headcount!S11 -> 1.3092917 | E34: =Headcount!A11 -> 3 | F34: 1 | G34: =AVERAGE(H34:L34) -> 1.0474333 | H34: =Shielding!M10 -> - | I34: =Bending!O10 -> - | J34: ='Attach Tape'!O10 -> 1.0796 | K34: ='Bending+ATT(Kombi sablon)'!O10 -> 1.053 | L34: ='Hand L.mark'!O10 -> 1.0097 | M34: =G34 -> 1.0474333 | N34: =D34 -> 1.3092917 | P34: =O34/N34 -> 0 | Q34: Napi / Daily | S34: =(S31-R31)/(S32-R32) -> 0 | T34: =(T31-S31)/(T32-S32) -> 0 | U34: =(U31-T31)/(U32-T32) -> 0.033095238 | V34: =(V31-U31)/(V32-U32) -> 0.010978261 | W34: =(W31-V31)/(W32-V32) -> 0.0203 | X34: =(X31-W31)/(X32-W32) -> 0.0060903345 | Y34: =(Y31-X31)/(Y32-X32) -> 0.011764706 | Z34: =(Z31-Y31)/(Z32-Y32) -> 0.00604 | ... AG34: =(AG31-AF31)/(AG32-AF32) -> 0.0144
C35: =AVERAGE($D$33:D35) -> 1.2211727 | D35: =G35*Headcount!S12 -> 1.2500206 | E35: =Headcount!A12 -> 4 | F35: 1 | G35: =AVERAGE(H35:L35) -> 0.965925 | H35: =Shielding!M11 -> - | I35: =Bending!O11 -> 0.9217 | J35: ='Attach Tape'!O11 -> 1.006 | K35: ='Bending+ATT(Kombi sablon)'!O11 -> 0.9263 | L35: ='Hand L.mark'!O11 -> 1.0097 | M35: =G35 -> 0.965925 | N35: =D35 -> 1.2500206 | P35: =O35/N35 -> 0 | Q35: Cél/Target | S35: 0.0165 | T35: 0.0165 | U35: 0.0165 | V35: 0.0165 | W35: 0.0165 | X35: 0.0165 | Y35: 0.0165 | Z35: 0.0165 | AA35: 0.0165 | AB35: 0.0165 | AC35: 0.0165 | AD35: 0.0165 | AE35: 0.0165 | AF35: 0.0165 | AG35: 0.0165
C36: =AVERAGE($D$33:D36) -> 1.2584389 | D36: =G36*Headcount!S13 -> 1.3702376 | E36: =Headcount!A13 -> 5 | F36: 1 | G36: =AVERAGE(H36:L36) -> 1.05882 | H36: =Shielding!M12 -> 1.2986 | I36: =Bending!O12 -> 0.9474 | J36: ='Attach Tape'!O12 -> 1.0397 | K36: ='Bending+ATT(Kombi sablon)'!O12 -> 1.0018 | L36: ='Hand L.mark'!O12 -> 1.0066 | M36: =G36 -> 1.05882 | N36: =D36 -> 1.3702376 | P36: =O36/N36 -> 0
C37: =AVERAGE($D$33:D37) -> 1.3033698 | D37: =G37*Headcount!S14 -> 1.4830933 | E37: =Headcount!A14 -> 6 | F37: 1 | G37: =AVERAGE(H37:L37) -> 1.0112 | H37: =Shielding!M13 -> - | I37: =Bending!O13 -> 0.9597 | J37: ='Attach Tape'!O13 -> 1.0661 | K37: ='Bending+ATT(Kombi sablon)'!O13 -> 1.0078 | L37: ='Hand L.mark'!O13 -> - | M37: =G37 -> 1.0112 | N37: =D37 -> 1.4830933 | P37: =O37/N37 -> 0 | R37: Napi csomi GY. | S37: 10800 | T37: 800 | U37: 21000 | V37: 18400 | W37: 10000 | X37: 30376 | Y37: 13600 | Z37: 25000 | AA37: 27000 | AB37: 28500 | AC37: 25625 | AD37: 15500 | AE37: 4800 | AF37: 9700 | AG37: 5000
C38: =AVERAGE($D$33:D38) -> 1.2826637 | D38: =G38*Headcount!S15 -> 1.1791333 | E38: =Headcount!A15 -> 9 | F38: 1 | G38: =AVERAGE(H38:L38) -> 0.97406667 | H38: =Shielding!M14 -> - | I38: =Bending!O14 -> 0.8379 | J38: ='Attach Tape'!O14 -> 1.021 | K38: ='Bending+ATT(Kombi sablon)'!O14 -> 1.0633 | L38: ='Hand L.mark'!O14 -> - | M38: =G38 -> 0.97406667 | N38: =D38 -> 1.1791333 | P38: =O38/N38 -> 0 | R38: Minta GY | S38: 0 | T38: 0 | U38: 0 | V38: 0 | W38: 0 | X38: 0 | Y38: 0 | Z38: 0 | AA38: 60 | AB38: 0 | AC38: 0 | AD38: 0 | AE38: 0 | AF38: 0 | AG38: 0 | AN38: =SUM(S38:AM38) -> 60
C39: =AVERAGE($D$33:D39) -> 1.2560506 | D39: =G39*Headcount!S16 -> 1.0963719 | E39: =Headcount!A16 -> 10 | F39: 1 | G39: =AVERAGE(H39:L39) -> 0.94686667 | H39: =Shielding!M15 -> - | I39: =Bending!O15 -> 0.9792 | J39: ='Attach Tape'!O15 -> 0.7688 | K39: ='Bending+ATT(Kombi sablon)'!O15 -> 1.0926 | L39: ='Hand L.mark'!O15 -> - | M39: =G39 -> 0.94686667 | N39: =D39 -> 1.0963719 | P39: =O39/N39 -> 0 | R39: Minta nélküli selejt | S39: =S31/(S32-AN38) -> 0 | T39: =T32/(#REF!-AN38) -> #REF! | U39: =U31/(U32-AN38) -> 0.021358328 | V39: =V31/(V32-AN38) -> 0.017608952 | W39: =W31/(W32-AN38) -> 0.018050542 | X39: =X31/(X32-AN38) -> 0.014072014 | Y39: =Y31/(Y32-AN38) -> 0.013772923 | Z39: =Z31/(Z32-AN38) -> 0.012284861 | AA39: =AA31/(AA32-AN38) -> 0.010300938 | AB39: =AB31/(AB32-AN38) -> 0.012077034 | AC39: =AC31/(AC32-AN38) -> 0.011492129 | AD39: =AD31/(AD32-AN38) -> 0.011235608 | AE39: =AE31/(AE32-AN38) -> 0.011914382 | AF39: =AF31/(AF32-AN38) -> 0.012011564 | AG39: =AG31/(AG32-AN38) -> 0.012060089
C40: =AVERAGE($D$33:D40) -> 1.2865475 | D40: =G40*Headcount!S17 -> 1.5000259 | E40: =Headcount!A17 -> 11 | F40: 1 | G40: =AVERAGE(H40:L40) -> 1.1739333 | H40: =Shielding!M16 -> - | I40: =Bending!O16 -> 1.569 | J40: ='Attach Tape'!O16 -> 0.8761 | K40: ='Bending+ATT(Kombi sablon)'!O16 -> 1.0767 | L40: ='Hand L.mark'!O16 -> - | M40: =G40 -> 1.1739333 | N40: =D40 -> 1.5000259 | P40: =O40/N40 -> 0
C41: =AVERAGE($D$33:D41) -> 1.2747089 | D41: =G41*Headcount!S18 -> 1.18 | E41: =Headcount!A18 -> 12 | F41: 1 | G41: =AVERAGE(H41:L41) -> 0.93416667 | H41: =Shielding!M17 -> - | I41: =Bending!O17 -> 1.0333 | J41: ='Attach Tape'!O17 -> 0.9005 | K41: ='Bending+ATT(Kombi sablon)'!O17 -> 0.8687 | L41: ='Hand L.mark'!O17 -> - | M41: =G41 -> 0.93416667 | N41: =D41 -> 1.18 | P41: =O41/N41 -> 0
C42: =AVERAGE($D$33:D42) -> 1.3642395 | D42: =G42*Headcount!S19 -> 2.1700152 | E42: =Headcount!A19 -> 13 | F42: 1 | G42: =AVERAGE(H42:L42) -> 1.0378333 | H42: =Shielding!M18 -> - | I42: =Bending!O18 -> 1.3808 | J42: ='Attach Tape'!O18 -> 0.7773 | K42: ='Bending+ATT(Kombi sablon)'!O18 -> 0.9554 | L42: ='Hand L.mark'!O18 -> - | M42: =G42 -> 1.0378333 | N42: =D42 -> 2.1700152 | P42: =O42/N42 -> 0
C43: =AVERAGE($D$33:D43) -> 1.3960773 | D43: =G43*Headcount!S20 -> 1.7144545 | E43: =Headcount!A20 -> 16 | F43: 1 | G43: =AVERAGE(H43:L43) -> 0.94295 | H43: =Shielding!M19 -> - | I43: =Bending!O19 -> - | J43: ='Attach Tape'!O19 -> 1.0757 | K43: ='Bending+ATT(Kombi sablon)'!O19 -> 0.8102 | L43: ='Hand L.mark'!O19 -> - | M43: =G43 -> 0.94295 | N43: =D43 -> 1.7144545 | P43: =O43/N43 -> 0
C44: =AVERAGE($D$33:D44) -> 1.4456057 | D44: =G44*Headcount!S21 -> 1.9904182 | E44: =Headcount!A21 -> 17 | F44: 1 | G44: =AVERAGE(H44:L44) -> 1.0426 | H44: =Shielding!M20 -> - | I44: =Bending!O20 -> - | J44: ='Attach Tape'!O20 -> 1.1986 | K44: ='Bending+ATT(Kombi sablon)'!O20 -> 0.8866 | L44: ='Hand L.mark'!O20 -> - | M44: =G44 -> 1.0426 | N44: =D44 -> 1.9904182 | P44: =O44/N44 -> 0
C45: =AVERAGE($D$33:D45) -> 1.4421927 | D45: =G45*Headcount!S22 -> 1.4012364 | E45: =Headcount!A22 -> 18 | F45: 1 | G45: =AVERAGE(H45:L45) -> 0.96335 | H45: =Shielding!M21 -> - | I45: =Bending!O21 -> - | J45: ='Attach Tape'!O21 -> 1.0376 | K45: ='Bending+ATT(Kombi sablon)'!O21 -> 0.8891 | L45: ='Hand L.mark'!O21 -> - | M45: =G45 -> 0.96335 | N45: =D45 -> 1.4012364 | P45: =O45/N45 -> 0
C46: =AVERAGE($D$33:D46) -> 1.438375 | D46: =G46*Headcount!S23 -> 1.3887455 | E46: =Headcount!A23 -> 19 | F46: 1 | G46: =AVERAGE(H46:L46) -> 0.8986 | H46: =Shielding!M22 -> - | I46: =Bending!O22 -> 0.8705 | J46: ='Attach Tape'!O22 -> 0.9068 | K46: ='Bending+ATT(Kombi sablon)'!O22 -> 0.9185 | L46: ='Hand L.mark'!O22 -> - | M46: =G46 -> 0.8986 | N46: =D46 -> 1.3887455 | P46: =O46/N46 -> 0
C47: =AVERAGE($D$33:D47) -> 1.4144758 | D47: =G47*Headcount!S24 -> 1.0798864 | E47: =Headcount!A24 -> 20 | F47: 1 | G47: =AVERAGE(H47:L47) -> 0.91375 | H47: =Shielding!M23 -> - | I47: =Bending!O23 -> 0.9418 | J47: ='Attach Tape'!O23 -> 0.8857 | K47: ='Bending+ATT(Kombi sablon)'!O23 -> - | L47: ='Hand L.mark'!O23 -> - | M47: =G47 -> 0.91375 | N47: =D47 -> 1.0798864 | P47: =O47/N47 -> 0
C48: =AVERAGE($D$33:D48) -> 1.326071 | D48: =G48*Headcount!S25 -> 0 | E48: =Headcount!A25 -> 0
C49: =AVERAGE($D$33:D49) -> 1.2480668 | D49: =G49*Headcount!S26 -> 0 | E49: =Headcount!A26 -> 0
C50: =AVERAGE($D$33:D50) -> 1.1787298 | D50: =G50*Headcount!S27 -> 0 | E50: =Headcount!A27 -> 0
C51: =AVERAGE($D$33:D51) -> 1.1166914 | D51: =G51*Headcount!S28 -> 0 | E51: =Headcount!A28 -> 0
C52: =AVERAGE($D$33:D52) -> 1.0608568 | D52: =G52*Headcount!S29 -> 0 | E52: =Headcount!A29 -> 0

Sheet Meeting minutes
A1: Dátum (date) | B1: Feladat (Task) | C1: Felelős személy (PIC) | D1: Határidő (Dead line) | E1: Státusz (status) | F1: Komment (Comment)
A2: 45244 | B2: Fólia vágó akció lista | C2: Debreczeni Ottó | D2: 45260 | E2: Lezárt
A3: 45244 | B3: IQC layout kialakítása SS hajlítónál | C3: Urbán Orsolya | D3: 45254 | E3: Lezárt | F3: Vizuál lesz helyette
A4: 45244 | B4: 1397-tel mi a helyzet? Mi a terv, hogy fogjuk megelőzni a jövőbeni gyártásnál, hogy ne váljon szét a ragasztó? | C4: Rebicsek Ádám | D4: 45260 | E4: Lezárt | F4: Új ragasztóval kész a teszt--> 12.11-én megnézni kinyílt-e a ragasztó --> 2023.12.12nél tovább kezelve
A5: 45244 | B5: 1171 hajlítógép után görgőzés.--> Végső megoldás? Ha igen, költség vonzatát megvizsgálni | C5: Dömök-Demeter Petra | D5: 45260 | E5: Lezárt | F5: SH Orsi | G5: Módosítva a műveletterv és az SH is jó.
A6: 45244 | B6: 1221 150-150db teszt gyártása DMC jelölése mind2 tekercses INK-JETen | C6: Luda Ferenc | D6: 45260 | E6: Lezárt
A7: 45244 | B7: 1221 AD AMI /MIM előtt emelt színtű ellenőrzés vonalra, ellenőrzés elhagyásának vizsgálata végett | C7: Luda Ferenc | D7: 45275 | E7: Lezárt | F7: WO kész. 0 selejt esett ki AD AMI-n USB után
A8: 45261 | B8: Minta rendelés jóváhagyásának hiánya --> Minden esetben legyen másik fél általi jóváhagyás a Bcben. (Rajz + regisztráció) Punching esetén fontos a szerszám szám feltüntetése ha vágott ha profilozott | C8: Gergely Dániel | D8: 45282 | E8: Lezárt | F8: 2024-től Csabi ellenőrzi le a rajzokat
A9: 45261 | B9: 1201-1222-ből ami MIM-en kiesett, az mind rossz is volt. Tudunk ebből levonni valami konklúziót? | C9: Dulcz Csaba | D9: 45268 | E9: Lezárt | F9: Sajnos alsó határos volt. --> Teszt Ink-jet 1-en
A10: 45264 | B10: 1db 3R volt, 1397-es termék, SS hajlítógépen problémás volt | C10: Dulcz Csaba | D10: 45268 | E10: Lezárt
A11: 45264 | B11: 2700-0271 (EOL) transzfer 2700-0361-re. Megbeszélés alapján speciális WO-val a 0L-2700-0361-be be kell építeni a 07-2700-0271-et, a hiányzó műveletekkel együttú | C11: Luda Ferenc | D11: 45268 | E11: Lezárt
A12: 45264 | B12: 1200-1397 - ragasztásához beírni a nyomkodás műveletet is | C12: Gergely Dániel | D12: 45265 | E12: Lezárt
A13: 45264 | B13: SS hajlító után IQC vagy vizuál ellenőrzés? | C13: Rebicsek Ádám | D13: 45268 | E13: Lezárt | F13: SS auto hajlítós műv. Tervek átnézése IQC vs Vizuál --> Marad vizuál.
A14: 45264 | B14: 1 éven túl gyártott anyagok listájnál mérnökség töltse ki a táblázatot, hogy melyik oszlop releváns az adott itemnél | C14: Gergely Dániel | D14: 45268 | E14: Lezárt | F14: Lista kitöltve
A15: 45265 | B15: 3R nem volt, 14-es AD PYP még mindig áll fejlesztés miatt | C15: - | D15: - | E15: -
A16: 45266 | B16: 2800-0507 szűkítés lazítása az alapanyag ablak miatt. Alapanyag megvizsgálása az eltett minta alapján. | C16: Rebicsek Ádám | D16: 45268 | E16: Lezárt
A17: 45266 | B17: 2700-0410 APIM-on megvizsgálni a lehetőségét, hogy egyszer kerüljön fel. | C17: Gergely Dániel | D17: 45268 | E17: Lezárt | F17: 1x APIM lett beállítva 2 jelölésre
A18: 45266 | B18: 2700-0410-nél ha nem lehet egyszerre mindkét oldali jelölés, akkor műveletterv módosítás. (Apim művelet 2X) | C18: Dömök-Demeter Petra | D18: 45268 | E18: Lezárt | F18: 1x APIM lett beállítva 2 jelölésre
A19: 45266 | B19: 1200-1314 JSZ selejt a kábel szennyezettsége miatt. Alapanyag vizsgálata(emelt szintre emelés), jelzés a beszállítónak. | C19: Rebicsek Ádám | D19: 45275 | E19: Lezárt | F19: Ádám emailje a válasz 02.20
A20: 45267 | B20: 2700-0410 APIM 1-ben program módosítás az új rajz szerint. | C20: Dulcz Csaba / Urbán Orsolya | D20: 45351 | E20: Lezárt | F20: Program kész az APIM 1-re. Első gyártást megnézni-->nem volt Januárban több gyártás, termelés jelzi, ha lesz, de egyenlőre nincs behelyezve rendelés.--> 09.25-én indulna, de reggel óta nem indult el gond miatt.
A21: 45268 | B21: CYT 2-n tönkrement a csapágy, fél műszakos javítás, 4-es 3R APIM 2. PDCA-ban kezelve | C21: - | D21: - | E21: - | F21: -
A22: 45271 | B22: Nem volt semmi említésre méltó esemény.1222-es terméknél volt fül sérülés, amit a beállítók orvosoltak a CYTen kaptonnal és nyomás állítással, + alapanyagban TP-s az anyag | C22: - | D22: - | E22: - | F22: Ma tűrésen kívüli TP is volt benne --> Ádám elengedte
A23: 45272 | B23: 1200-1397 tesztje új ragasztóval nem volt jobb --> Beszállítóval egyeztetni a szivacs kiszakadásának az okát | C23: Rebicsek Ádám | D23: 45282 | E23: Lezárt | F23: 01.04 Petra levele magyarázat.
A24: 45272 | B24: 1221 DMC jelölés teszt eredménye alapján a tekercses INK-JET 1 után, nem rosszabb a jelölés minősége--> DMC hullámosságra döntés | C24: Rebicsek Ádám | D24: 45275 | E24: Lezárt | F24: Ádám nem fogadja el a hullámosságot vevői elfogadás nélkül
A25: 45272 | B25: 3R nem volt! | C25: - | D25: - | E25: -
A26: 45273 | B26: 1314 2x-i felfűzés helyett 1-be jelölés | C26: Dulcz Csaba | D26: 45275 | E26: Lezárt | F26: Elfogadva a 4M
A27: 45273 | B27: 1397 es anyagból 3mm-rel rövidebb teszt ragasztása, következő gyártásnál | C27: Urbán Orsolya | D27: 45322 | E27: Lezárt | F27: Teszt anyag Lacinál. Nem lett jó.
A28: 45274 | B28: 1221-es anyag HA nagy számú selejtet okozott. Visszajelzés küldése a beszállítónak | C28: Rebicsek Ádám | D28: 45275 | E28: Lezárt | F28: 2024.01.23 – Eszkaláltam Okunak, felvette a kapcsolatot SEIW-vel, h nézzék meg mennyire kritikus a téma--> HA elengedve
A29: 45274 | B29: Címke nyomtatás WI véglegesítése | C29: Gergely Dániel | D29: 45281 | E29: Lezárt | F29: Doksi kiadva 01.31
A30: 45274 | B30: 3R nem volt az előző napon | C30: - | D30: - | E30: -
A31: 45275 | B31: 1200-1361-es termék nem tud menni az AD PYP-en, mert az anyag túl görbe. 3R form készült. Az elmúlt gyártások során is magas volt a selejt, átlag 5.49%. Ideiglenesen vevői kérés miatt áthelyezve CYT-re, a további gyártások átgondolása. | C31: Gergely Dániel | D31: 45306 | E31: Lezárt | F31: BC-ben rögzíteni a művelettervben, hogy csak AD PYP14-en mehet
A32: 45299 | B32: 1200-1039 Alapanyagban ferde az ablak. | C32: Rebicsek Ádám | D32: 45322 | E32: Nyitott | F32: Nincs speckó rá, jelzést kell küldeni a beszállító felé.-->24.08.14-én levél küldve a beszállítónak. Válaszra várunk.
A33: 45299 | B33: 1200-1397 támszalaghiba kivizsgálás a következő beérkezésen. | C33: Rebicsek Ádám | D33: 45322 | E33: Lezárt | F33: 2024.01.23 – Dec 12-én jött be 6k, ami még akció előtti anyag, a Jan 9-i már jó anyag kell, hogy legyen à Nyomon követjük a belső selejttel, h valóban így van e.--> 02.06 Támszalag nélküli találatok miatt 3R-ek készültek. LOT szám átküldve Ádámnak. 02.06--> 6 beérkezés vizsgálva, mind ok volt.
A34: 45299 | B34: 1200-1397 a decemberi beérkezésbő Vizuális ellenőrzésen kiteszik a nem megfelelő támszalagos terméket. | C34: Rebicsek Ádám | D34: 45322 | E34: Lezárt | F34: Válasz a 33. sor komment oszlopában.
A35: 45299 | B35: 1200-1367 nem tud menni az AD PYP-en. Át kell tenni CYT-re. Ideiglenes 4M elkészítése. | C35: Luda Ferenc | D35: 45322 | E35: Lezárt | F35: 4M elfogadva.
A36: 45300 | B36: 1 éven túli doksi frissítése | C36: Rebicsek Ádám | D36: 45303 | E36: Lezárt | F36: Emlékeztető elkészítve (havi szintet emlékeztetése Ádámnak)
A37: 45301 | B37: CYT-ek óránkénti kimenetel vizsgálata a tavalyi mintára az 1201-1221 kevés kimenete miatt. | C37: Urbán Orsolya | D37: 45301 | E37: Lezárt | F37: Óránkénti mérlegelés helyett leütés felírása
A38: 45301 | B38: IQC és Labor teljesítmény bónusz javaslata Oku san felé. | C38: Rebicsek Ádám | D38: 45301 | E38: Lezárt | F38: Bevezetve 02.01-től, doksi módosításról emailt ír Ádám Adriennek. Bevezetve.
A39: 45301 | B39: 1201-1221 1 LOT CYT-en vonalellenőrzéssel, darabszám nyomonkövetéssel. | C39: Luda Ferenc / Urbán Orsolya | D39: 45322 | E39: Lezárt
A40: 45302 | B40: 2700-0426 / 0427 / 0428 EATON termékek művelettervének felülvizsgálata USB--> Vizuál?? | C40: Rebicsek Ádám | D40: 45302 | E40: Lezárt | F40: Vizuál lesz
A41: 45302 | B41: 2700-0427 és 2700-0428 jelölésének megvizsgálása Manuál ink-jet helyett APIM + 27-0426 is. | C41: Dulcz Csaba | D41: 45322 | E41: Lezárt | F41: Letesztelve OK!
A42: 45302 | B42: V100-0157 ragasztó hosszabb méretben 100 db rendelés | C42: Dömök-Demeter Petra | D42: 45322 | E42: Lezárt | F42: megrendelve 2024.01.16, teszt elkészült 02.05, Lacinak átadva.
A43: 45302 | B43: 1200-1397 Az SS Bending random szétdobálja az anyagot. | C43: Dulcz Csaba | D43: 45322 | E43: Lezárt | F43: Állított Csabi a gépen. Azóta nem ismétlődött meg.
A44: 45303 | B44: V100-0157 extra erős ragasztórétegű és erős ragasztórétegű ragasztó rövidebb méretben 2X100 db rendelés (15X5) | C44: Dömök-Demeter Petra | D44: 45322 | E44: Lezárt | F44: megrendelve 2024.01.16, teszt elkészült 02.05, Lacinak átadva.
A45: 45303 | B45: Tabletekre a BC applikáció letöltése | C45: Himpli Attila | D45: 45322 | E45: Lezárt | F45: Kész
A46: 45306 | B46: 1200-1282 Jelölési hiba döntésre vár.--> Oku san döntése: le kell mosni | C46: Rebicsek Ádám | D46: 45310 | E46: Lezárt | F46: Bónuszmegvonás O. Sanyitól.
A47: 45307 | B47: 1200-1397-es anyag legkésőbb 01.18-án újra kell kezdeni a gyártást, mert nem fogjuk tudni kiszolgálni a vásárlót. Döntés a későbbi gyártásról? | C47: Rebicsek Ádám | D47: 45310 | E47: Lezárt | F47: 4X is lenyomkodva kiszállítás előtt.
A48: 45308 | B48: 2700-0426 melegprés lapját ellenőrizni, nehogy selejt legyen mint a 427-ből. | C48: Dulcz Csaba | D48: 45308 | E48: Lezárt | F48: Rendben volt.
A49: 45308 | B49: A minták beépülő alapanyagaira a BC-ben való lefejlesztéséig kézzel írni a cimkére az azonosítókat. | C49: Gergely Dániel | D49: 45382 | E49: Lezárt | F49: BC lefejlesztve.
A50: 45308 | B50: SS hajlítógép átállásakor a hajlítás szögét a programm adja. Mégis átálláskor korrigálni kell, miért? | C50: Dulcz Csaba | D50: 45310 | E50: Lezárt | F50: Normális, ha korrigálni kell, amikor gond van a géppel, de nem törvényszerű.
A51: 45309 | B51: 1397 - 25db normál csiptetés és fordított hajlítás --> 18x5ös ragasztóval; 25db fordított hajlítás (Csabi féle módszer)--> 22x5-ös ragasztóval | C51: Urbán Orsolya | D51: 45351 | E51: Lezárt | F51: Ragasztó beérkezett. 01.31 Teszt elkészült, eredményre vár.
... A59: 45315 | B59: 1200-1362 tisztasági teszt miatt a széles fehér ragasztóval ragasztani 30 db-ot és Daninak átadni. | C59: Urbán Orsolya | D59: 45315 | E59: Lezárt | F59: Anyag átadva Daninak 01.24
A60: 45316 | B60: 2701-0374 kapcsoló kódok beállítva. Tesztelés alatt. | C60: Urbán Orsolya | D60: 45316 | E60: Lezárt
A61: 45316 | B61: Apim beállítási lap módosítása. | C61: Dulcz Csaba | D61: 45322 | E61: Lezárt | F61: Dokumentum kiadva 02.02
A62: 45316 | B62: APIM check list készítése a műszakonkénti ellenőrzésekre. | C62: Urbán Orsolya | D62: 45322 | E62: Lezárt | F62: Elfogadásra vár Laci által. (01.25)--> törölve
A63: 45316 | B63: 2700-0432 0,056K hiányzik a 3K-s megrendeléshez. Januárról kitolva áprilisra, betett rendelés nincs több, így anyag sincs rendelve hozzá. Infó, hogy kell-e ebből még gyártanunk, várjunk-e vagy lecsomagoltassuk utolsó darabig? (Mintázás volt az új designra. 2701-0432) | C63: Szabó Krisztián | D63: 45322 | E63: Lezárt | F63: A maradék termékre törlést kérnek.
A64: 45317 | B64: SAMP-00072-es minta fehér ragasztóját 13+/-1-re lehet tenni! | D64: 45317 | E64: Lezárt
A65: 45317 | B65: CYT decemberi teljesítménye az 1201-1221-nek. | C65: Urbán Orsolya | D65: 45318 | E65: Lezárt | F65: Adatok küldése Orsitól 01.26.
A66: 45317 | B66: CYT vonal és vonal nélkül vágni 50-50 db-ot. | C66: Dulcz Csaba | D66: 45317 | E66: Lezárt | F66: Kiértékellés email Csabitól 01.26.
A67: 45317 | B67: 2700-0429/0430/0431/0432 termék USB vagy Conti Final Insp ellenőrzés a következő gyártástól?? | C67: Rebicsek Ádám | D67: 45322 | E67: Lezárt | F67: Contira tenni. --> Email Daninak róla 02.26
A68: 45317 | B68: 2700-0361 termék tesztelés sárga tape nélkül. 100 db | C68: Urbán Orsolya | D68: 45317 | E68: Lezárt | F68: Teszt kész, Danira vár a kiértékelés. Sárga tape törlése a művelettervből.
A69: 45317 | B69: Dani eldönti, hogy kell-e a sárga tape a teszt alapján a 2700-0361-es termékre. (Vevő nem is kérte) | C69: Gergely Dániel | D69: 45322 | E69: Lezárt | F69: Új műveletterv aktív. 01.30
A70: 45321 | B70: SS Bending túlterheltsége miatt a 2702-0329-es terméket kézi hajlításra bevisszük. (6,5K) | D70: 45321 | E70: Lezárt
A71: 45322 | B71: USB vákumasztal teszt, ha ok, akkor megcsinálni minden asztalra. | C71: Dulcz Csaba | D71: 45331 | E71: Lezárt | F71: Klaudiáék tesztelnek.
A72: 45327 | B72: 1200-1397 selejt kábellel tesztelés fordított irányú hajlítással. | C72: Dulcz Csaba | D72: 45331 | E72: Lezárt | F72: Teszt eredményre vár. --> Indul változás. 04.17
A73: 45327 | B73: USB tesztelés után eltömődött az elszívó az alsó sorban. Csabi ellenőrzi. | C73: Dulcz Csaba | D73: 45331 | E73: Lezárt | F73: Teszt asztal javítva.
A74: 45327 | B74: Nissotól rendelt ragasztó letesztelése, ha beért. (megrendelve 01.23) | C74: Urbán Orsolya | D74: 45331 | E74: Lezárt | F74: Azóta sem kaptam ragasztót.
A75: 45328 | B75: USB újabb teszt az új elszívó asztallal. | C75: Varga Klaudia | D75: 45331 | E75: Lezárt | F75: Csabira vár a kiértékelés a szennyeződésre.
A76: 45329 | B76: 2700-0417 megnevezés átírása a művelettervben | C76: Gergely Dániel | D76: 45329 | E76: Lezárt
A77: 45329 | B77: 1200-1397 SS B. tárazási segédlet módosítás kaptonozás miatt. | C77: Dulcz Csaba | D77: 45351 | E77: Lezárt | F77: Módosítva.
A78: 45331 | B78: 1200-1283 Ink-Jetre betervezésnél jelzés Csabinak. | C78: Luda Ferenc / Urbán Orsolya | D78: 45382 | E78: Lezárt | F78: Lement, CYT-nél jelzés Csabinak.--> Csabinak jelezve. Selejt CYT után átadva--> Eredmény
A79: 45331 | B79: 1201-1221 Sárga Tape pozíció ellenőrzésének szükségessége | C79: Rebicsek Ádám | D79: 45335 | E79: Lezárt | F79: Dani szerint nem szükséges. --> Egyeztetni Klaudiával, hogy nézve van -e a pozíció szálkereszttel--> Igen nézve van, de szükséges ???, ez az alap bejegyzés :) :) --> szálkereszten nem kell. Csak az a lényeg, hogy az ablakon ne legyen a ragasztó, mert nincs funkcionalitása a tapenak.
A80: 45331 | B80: 1200-1397 vevőnek kép küldése a jelenlegi és az "Új" hajlításról ragasztóval és ragasztó nélkül. | C80: Rebicsek Ádám | D80: 45331 | E80: Lezárt | F80: Levél kiküldve 02.09
A81: 45334 | B81: MIM-en kitett 1201-1196 mérése. | C81: Varga Klaudia | D81: 45334 | E81: Lezárt | F81: Emailban elküldve az összes eredmény.
A82: 45335 | B82: Nem történt semmi említésre méltó esemény. | C82: - | D82: - | E82: -
A83: 45336 | B83: Nem történt semmi említésre méltó esemény. | C83: - | D83: - | E83: -
A84: 45337 | B84: SAMP-116 maradék anyagát 0124-re legyártani, a SAMP-00124-et nem szabad lezárni! | C84: Luda Ferenc / Urbán Orsolya | D84: 45337 | E84: Lezárt
A85: 45337 | B85: SAMP-00124 műveletterv és dátum módosítása | C85: Gergely Dániel | D85: 45337 | E85: Lezárt
A86: 45337 | B86: 1200-1344 0F-es készletéből 125 db-ot átméretni folyamatképesség miatt. | C86: Varga Klaudia | D86: 45345 | E86: Lezárt | F86: Email elküldve 02.21
A87: 45338 | B87: Mai naptól életbe lép a higító újrahasznosítás az APIM 1-2 és Ink-Jet 1-en! | C87: - | D87: 45338 | E87: Lezárt
A88: 45341 | B88: Nem történt semmi említésre méltó esemény. | C88: - | D88: - | E88: -
A89: 45343 | B89: 1200-1398 - rajza (felirat) nem egyértelmű. Egyértelműsítés a vevői rajz alapján! | C89: Gergely Dániel | D89: 45345 | E89: Lezárt | F89: 07.03-án rajz módosítva.
A90: 45344 | B90: 1200-1398 felirat pozíciójának (11-)ről változtatása a megfelelő méretre, plusz a vágott anyagnál is feltüntetni a jelölési méreteket. | C90: Gergely Dániel | D90: 45344 | E90: Lezárt
A91: 45345 | B91: Nem volt 3R, gépek problémamentesen működtek | C91: - | D91: - | E91: -
A92: 45348 | B92: Szűkített tűrés utasítás átnézése "S" méret miatt | C92: Rebicsek Ádám | D92: 45351 | E92: Lezárt | F92: Új doksi kiadva 05.08
A93: 45348 | B93: 1200-1344 CPK mérés kiértékelése. | C93: Rebicsek Ádám | D93: 45352 | E93: Lezárt | F93: CPK OK!
A94: 45349 | B94: Nem történt semmi említésre méltó esemény. | C94: - | D94: - | E94: -
A95: 45350 | B95: 1200-1337 "hártya" elengedve, műszaknaplózva. | C95: - | D95: - | E95: -
A96: 45350 | B96: 1201-1196 probléma a punchingolás során. 90.11° a szög | C96: Debreczeni Ottó | D96: 45350 | E96: Lezárt
A97: 45351 | B97: 2700-0427 / 0428 / 0426 APIM-ra áthelyezhető? Teszt oké volt! | C97: Gergely Dániel | D97: 45355 | E97: Lezárt | F97: Áthelyezve 4M-el 08. hóban.
A98: 45352 | B98: Nem történt semmi említésre méltó esemény. | C98: - | D98: - | E98: -
A99: 45355 | B99: 1200-1233 és 1201-1221 között alapanyagban mi a különbség? | C99: Rebicsek Ádám | D99: 45369 | E99: Lezárt | F99: Beszállító felé jelezve, szerintük nincs különbség a két gyártásában.
A100: 45356 | B100: 2700-0428 SH módosítás APIM adatokból. | C100: Gergely Dániel | D100: 45365 | E100: Nyitott | F100: Orsi küldi az SH adatokat.--> elküldve 03.06--> 4M Csabitól --> 4M elfogadva, SH-t kell módosítás a márciusi email alapján.
A101: 45357 | B101: 2700-0369 IQC behelyezése a művelettervbe. | C101: Gergely Dániel | D101: 45359 | E101: Nyitott
A102: 45357 | B102: 2700-0369 vágott GND mérete kissebbre vehető? | C102: Gergely Dániel | D102: 45359 | E102: Nyitott
A103: 45357 | B103: 2700-0369 Rajz átnézése. (GND pozíció minimum értéke nincs feltüntetve) | C103: Gergely Dániel | D103: 45365 | E103: Nyitott
A104: 45357 | B104: GND ragasztás ellenőrzésére sztenderd folyamat? | C104: Rebicsek Ádám | D104: 45382 | E104: Lezárt | F104: 24.08.14: Danival egyeztet róla Ádám , levélben egyeztetve róla 24.08.30-án
A105: 45358 | B105: 1201-1221 vevői reklamáció mikor volt és mit válaszoltunk rá? (Esetleg 4M a bevezetett intézkedésről, hogy csak az Ink-Jet 2-en lehet feliratozni) | C105: Rebicsek Ádám | D105: 45382 | E105: Nyitott
A106: 45359 | B106: Nem történt semmi említésre méltó esemény. | C106: - | D106: - | E106: -
A107: 45362 | B107: Nem történt semmi említésre méltó esemény. | C107: - | D107: - | E107: -
...

Sheet Prod.Output
A1: Könyvelési dátum | B1: Adagszám | C1: Cikkszám | D1: Mennyiség | E1: Sales Price | F1: DC Price | G1: DC TTL Line | H1: Átellenőrzés | I1: Mennyiség | J1: TTL in Sales price | K1: TTL QTY | L1: TTL DC
A2: 45628 | B2: WO-041477 | C2: 07-2701-0430H | D2: 1.2 | E2: =IF(TYPE(VLOOKUP(C2,'Sales_DC Price'!K:L,2,0))=16,0,VLOOKUP(C2,'Sales_DC Price'!K:L,2,0)*D2) -> 1500 | F2: =IF(TYPE(VLOOKUP(C2,'Sales_DC Price'!Q:R,2,0))=16,0,VLOOKUP(C2,'Sales_DC Price'!Q:R,2,0)) -> 966.53414 | G2: =F2*D2 -> 1159.841 | J2: =SUM(E2:E9133) -> 297320.12 | K2: =SUM(D:D)*1000 -> 482422 | L2: =SUM(G2:G9134) -> 235628.56
A3: 45628 | B3: WO-041260 | C3: 07-2701-0431H | D3: 0.4 | E3: =IF(TYPE(VLOOKUP(C3,'Sales_DC Price'!K:L,2,0))=16,0,VLOOKUP(C3,'Sales_DC Price'!K:L,2,0)*D3) -> 412 | F3: =IF(TYPE(VLOOKUP(C3,'Sales_DC Price'!Q:R,2,0))=16,0,VLOOKUP(C3,'Sales_DC Price'!Q:R,2,0)) -> 735.14859 | G3: =F3*D3 -> 294.05944
A4: 45628 | B4: WO-041477 | C4: 07-2701-0430H | D4: 0.4 | E4: =IF(TYPE(VLOOKUP(C4,'Sales_DC Price'!K:L,2,0))=16,0,VLOOKUP(C4,'Sales_DC Price'!K:L,2,0)*D4) -> 500 | F4: =IF(TYPE(VLOOKUP(C4,'Sales_DC Price'!Q:R,2,0))=16,0,VLOOKUP(C4,'Sales_DC Price'!Q:R,2,0)) -> 966.53414 | G4: =F4*D4 -> 386.61366
A5: 45628 | B5: WO-041473 | C5: 07-2701-0430H | D5: 0.6 | E5: =IF(TYPE(VLOOKUP(C5,'Sales_DC Price'!K:L,2,0))=16,0,VLOOKUP(C5,'Sales_DC Price'!K:L,2,0)*D5) -> 750 | F5: =IF(TYPE(VLOOKUP(C5,'Sales_DC Price'!Q:R,2,0))=16,0,VLOOKUP(C5,'Sales_DC Price'!Q:R,2,0)) -> 966.53414 | G5: =F5*D5 -> 579.92048
A6: 45628 | B6: WO-037105 | C6: 07-2700-0362H | D6: 2 | E6: =IF(TYPE(VLOOKUP(C6,'Sales_DC Price'!K:L,2,0))=16,0,VLOOKUP(C6,'Sales_DC Price'!K:L,2,0)*D6) -> 1652.4 | F6: =IF(TYPE(VLOOKUP(C6,'Sales_DC Price'!Q:R,2,0))=16,0,VLOOKUP(C6,'Sales_DC Price'!Q:R,2,0)) -> 587.45417 | G6: =F6*D6 -> 1174.9083
A7: 45628 | B7: WO-038349 | C7: 07-2800-0526H | D7: 2 | E7: =IF(TYPE(VLOOKUP(C7,'Sales_DC Price'!K:L,2,0))=16,0,VLOOKUP(C7,'Sales_DC Price'!K:L,2,0)*D7) -> 561 | F7: =IF(TYPE(VLOOKUP(C7,'Sales_DC Price'!Q:R,2,0))=16,0,VLOOKUP(C7,'Sales_DC Price'!Q:R,2,0)) -> 206.8331 | G7: =F7*D7 -> 413.6662
A8: 45628 | B8: WO-038347 | C8: 07-2700-0256H | D8: 1 | E8: =IF(TYPE(VLOOKUP(C8,'Sales_DC Price'!K:L,2,0))=16,0,VLOOKUP(C8,'Sales_DC Price'!K:L,2,0)*D8) -> 792.2 | F8: =IF(TYPE(VLOOKUP(C8,'Sales_DC Price'!Q:R,2,0))=16,0,VLOOKUP(C8,'Sales_DC Price'!Q:R,2,0)) -> 489.0523 | G8: =F8*D8 -> 489.0523
A9: 45628 | B9: WO-036191 | C9: 07-1200-1324H | D9: 6 | E9: =IF(TYPE(VLOOKUP(C9,'Sales_DC Price'!K:L,2,0))=16,0,VLOOKUP(C9,'Sales_DC Price'!K:L,2,0)*D9) -> 1064.64 | F9: =IF(TYPE(VLOOKUP(C9,'Sales_DC Price'!Q:R,2,0))=16,0,VLOOKUP(C9,'Sales_DC Price'!Q:R,2,0)) -> 143.70284 | G9: =F9*D9 -> 862.21704
A10: 45628 | B10: WO-037104 | C10: 07-2700-0049H | D10: 2 | E10: =IF(TYPE(VLOOKUP(C10,'Sales_DC Price'!K:L,2,0))=16,0,VLOOKUP(C10,'Sales_DC Price'!K:L,2,0)*D10) -> 680 | F10: =IF(TYPE(VLOOKUP(C10,'Sales_DC Price'!Q:R,2,0))=16,0,VLOOKUP(C10,'Sales_DC Price'!Q:R,2,0)) -> 273.9903 | G10: =F10*D10 -> 547.9806
A11: 45628 | B11: WO-038392 | C11: 07-2700-0440H | D11: 3 | E11: =IF(TYPE(VLOOKUP(C11,'Sales_DC Price'!K:L,2,0))=16,0,VLOOKUP(C11,'Sales_DC Price'!K:L,2,0)*D11) -> 3057 | F11: =IF(TYPE(VLOOKUP(C11,'Sales_DC Price'!Q:R,2,0))=16,0,VLOOKUP(C11,'Sales_DC Price'!Q:R,2,0)) -> 755.76559 | G11: =F11*D11 -> 2267.2968
A12: 45628 | B12: WO-040920 | C12: 07-2700-0422H | D12: 3 | E12: =IF(TYPE(VLOOKUP(C12,'Sales_DC Price'!K:L,2,0))=16,0,VLOOKUP(C12,'Sales_DC Price'!K:L,2,0)*D12) -> 3888.9 | F12: =IF(TYPE(VLOOKUP(C12,'Sales_DC Price'!Q:R,2,0))=16,0,VLOOKUP(C12,'Sales_DC Price'!Q:R,2,0)) -> 1219.8347 | G12: =F12*D12 -> 3659.5041
A13: 45628 | B13: WO-041495 | C13: 07-2701-0429H | D13: 1.2 | E13: =IF(TYPE(VLOOKUP(C13,'Sales_DC Price'!K:L,2,0))=16,0,VLOOKUP(C13,'Sales_DC Price'!K:L,2,0)*D13) -> 1156.8 | F13: =IF(TYPE(VLOOKUP(C13,'Sales_DC Price'!Q:R,2,0))=16,0,VLOOKUP(C13,'Sales_DC Price'!Q:R,2,0)) -> 730.47328 | G13: =F13*D13 -> 876.56794
A14: 45628 | B14: WO-041492 | C14: 07-2701-0429H | D14: 1 | E14: =IF(TYPE(VLOOKUP(C14,'Sales_DC Price'!K:L,2,0))=16,0,VLOOKUP(C14,'Sales_DC Price'!K:L,2,0)*D14) -> 964 | F14: =IF(TYPE(VLOOKUP(C14,'Sales_DC Price'!Q:R,2,0))=16,0,VLOOKUP(C14,'Sales_DC Price'!Q:R,2,0)) -> 730.47328 | G14: =F14*D14 -> 730.47328
... A24: 45630 | B24: WO-039868 | C24: 07-1200-1369H | D24: 3 | E24: =IF(TYPE(VLOOKUP(C24,'Sales_DC Price'!K:L,2,0))=16,0,VLOOKUP(C24,'Sales_DC Price'!K:L,2,0)*D24) -> 903 | F24: =IF(TYPE(VLOOKUP(C24,'Sales_DC Price'!Q:R,2,0))=16,0,VLOOKUP(C24,'Sales_DC Price'!Q:R,2,0)) -> 233.704 | G24: =F24*D24 -> 701.112
A25: 45630 | B25: WO-039748 | C25: 07-2700-0439H | D25: 3 | E25: =1408*D25 -> 4224 | F25: =IF(TYPE(VLOOKUP(C25,'Sales_DC Price'!Q:R,2,0))=16,0,VLOOKUP(C25,'Sales_DC Price'!Q:R,2,0)) -> 821.7578 | G25: =F25*D25 -> 2465.2734
A26: 45630 | B26: WO-040395 | C26: 07-1200-1404H | D26: 7 | E26: =IF(TYPE(VLOOKUP(C26,'Sales_DC Price'!K:L,2,0))=16,0,VLOOKUP(C26,'Sales_DC Price'!K:L,2,0)*D26) -> 3255 | F26: =IF(TYPE(VLOOKUP(C26,'Sales_DC Price'!Q:R,2,0))=16,0,VLOOKUP(C26,'Sales_DC Price'!Q:R,2,0)) -> 390.84752 | G26: =F26*D26 -> 2735.9326
A27: 45630 | B27: WO-039390 | C27: 07-1200-0951H | D27: 1 | E27: =IF(TYPE(VLOOKUP(C27,'Sales_DC Price'!K:L,2,0))=16,0,VLOOKUP(C27,'Sales_DC Price'!K:L,2,0)*D27) -> 268.3816 | F27: =IF(TYPE(VLOOKUP(C27,'Sales_DC Price'!Q:R,2,0))=16,0,VLOOKUP(C27,'Sales_DC Price'!Q:R,2,0)) -> 95.0903 | G27: =F27*D27 -> 95.0903
A28: 45630 | B28: WO-040387 | C28: 07-1200-1395H | D28: 10 | E28: =662*D28 -> 6620 | F28: =IF(TYPE(VLOOKUP(C28,'Sales_DC Price'!Q:R,2,0))=16,0,VLOOKUP(C28,'Sales_DC Price'!Q:R,2,0)) -> 548.46776 | G28: =F28*D28 -> 5484.6776
A29: 45630 | B29: WO-041496 | C29: 07-2701-0429H | D29: 1.2 | E29: =IF(TYPE(VLOOKUP(C29,'Sales_DC Price'!K:L,2,0))=16,0,VLOOKUP(C29,'Sales_DC Price'!K:L,2,0)*D29) -> 1156.8 | F29: =IF(TYPE(VLOOKUP(C29,'Sales_DC Price'!Q:R,2,0))=16,0,VLOOKUP(C29,'Sales_DC Price'!Q:R,2,0)) -> 730.47328 | G29: =F29*D29 -> 876.56794
A30: 45630 | B30: WO-041481 | C30: 07-2701-0430H | D30: 0.4 | E30: =IF(TYPE(VLOOKUP(C30,'Sales_DC Price'!K:L,2,0))=16,0,VLOOKUP(C30,'Sales_DC Price'!K:L,2,0)*D30) -> 500 | F30: =IF(TYPE(VLOOKUP(C30,'Sales_DC Price'!Q:R,2,0))=16,0,VLOOKUP(C30,'Sales_DC Price'!Q:R,2,0)) -> 966.53414 | G30: =F30*D30 -> 386.61366
A31: 45630 | B31: WO-041477 | C31: 07-2701-0430H | D31: 1.4 | E31: =IF(TYPE(VLOOKUP(C31,'Sales_DC Price'!K:L,2,0))=16,0,VLOOKUP(C31,'Sales_DC Price'!K:L,2,0)*D31) -> 1750 | F31: =IF(TYPE(VLOOKUP(C31,'Sales_DC Price'!Q:R,2,0))=16,0,VLOOKUP(C31,'Sales_DC Price'!Q:R,2,0)) -> 966.53414 | G31: =F31*D31 -> 1353.1478
A32: 45630 | B32: WO-038556 | C32: 07-1200-1392H | D32: 1 | E32: =IF(TYPE(VLOOKUP(C32,'Sales_DC Price'!K:L,2,0))=16,0,VLOOKUP(C32,'Sales_DC Price'!K:L,2,0)*D32) -> 686 | F32: =IF(TYPE(VLOOKUP(C32,'Sales_DC Price'!Q:R,2,0))=16,0,VLOOKUP(C32,'Sales_DC Price'!Q:R,2,0)) -> 303.46993 | G32: =F32*D32 -> 303.46993
A33: 45630 | B33: WO-041495 | C33: 07-2701-0429H | D33: 1 | E33: =IF(TYPE(VLOOKUP(C33,'Sales_DC Price'!K:L,2,0))=16,0,VLOOKUP(C33,'Sales_DC Price'!K:L,2,0)*D33) -> 964 | F33: =IF(TYPE(VLOOKUP(C33,'Sales_DC Price'!Q:R,2,0))=16,0,VLOOKUP(C33,'Sales_DC Price'!Q:R,2,0)) -> 730.47328 | G33: =F33*D33 -> 730.47328
A34: 45630 | B34: WO-034989 | C34: 07-1200-0225H | D34: 5 | E34: =IF(TYPE(VLOOKUP(C34,'Sales_DC Price'!K:L,2,0))=16,0,VLOOKUP(C34,'Sales_DC Price'!K:L,2,0)*D34) -> 2975 | F34: =IF(TYPE(VLOOKUP(C34,'Sales_DC Price'!Q:R,2,0))=16,0,VLOOKUP(C34,'Sales_DC Price'!Q:R,2,0)) -> 169.67503 | G34: =F34*D34 -> 848.37515
A35: 45631 | B35: WO-041496 | C35: 07-2701-0429H | D35: 0.8 | E35: =IF(TYPE(VLOOKUP(C35,'Sales_DC Price'!K:L,2,0))=16,0,VLOOKUP(C35,'Sales_DC Price'!K:L,2,0)*D35) -> 771.2 | F35: =IF(TYPE(VLOOKUP(C35,'Sales_DC Price'!Q:R,2,0))=16,0,VLOOKUP(C35,'Sales_DC Price'!Q:R,2,0)) -> 730.47328 | G35: =F35*D35 -> 584.37862
A36: 45631 | B36: WO-041260 | C36: 07-2701-0431H | D36: 1.2 | E36: =IF(TYPE(VLOOKUP(C36,'Sales_DC Price'!K:L,2,0))=16,0,VLOOKUP(C36,'Sales_DC Price'!K:L,2,0)*D36) -> 1236 | F36: =IF(TYPE(VLOOKUP(C36,'Sales_DC Price'!Q:R,2,0))=16,0,VLOOKUP(C36,'Sales_DC Price'!Q:R,2,0)) -> 735.14859 | G36: =F36*D36 -> 882.17831
A37: 45631 | B37: WO-041260 | C37: 07-2701-0431H | D37: 0.4 | E37: =IF(TYPE(VLOOKUP(C37,'Sales_DC Price'!K:L,2,0))=16,0,VLOOKUP(C37,'Sales_DC Price'!K:L,2,0)*D37) -> 412 | F37: =IF(TYPE(VLOOKUP(C37,'Sales_DC Price'!Q:R,2,0))=16,0,VLOOKUP(C37,'Sales_DC Price'!Q:R,2,0)) -> 735.14859 | G37: =F37*D37 -> 294.05944
A38: 45631 | B38: WO-041646 | C38: 07-1200-1368H | D38: 5 | E38: =IF(TYPE(VLOOKUP(C38,'Sales_DC Price'!K:L,2,0))=16,0,VLOOKUP(C38,'Sales_DC Price'!K:L,2,0)*D38) -> 1194.1 | F38: =IF(TYPE(VLOOKUP(C38,'Sales_DC Price'!Q:R,2,0))=16,0,VLOOKUP(C38,'Sales_DC Price'!Q:R,2,0)) -> 224.99589 | G38: =F38*D38 -> 1124.9795
A39: 45631 | B39: WO-034986 | C39: 07-1200-1323H | D39: 5 | E39: =IF(TYPE(VLOOKUP(C39,'Sales_DC Price'!K:L,2,0))=16,0,VLOOKUP(C39,'Sales_DC Price'!K:L,2,0)*D39) -> 1622.5 | F39: =IF(TYPE(VLOOKUP(C39,'Sales_DC Price'!Q:R,2,0))=16,0,VLOOKUP(C39,'Sales_DC Price'!Q:R,2,0)) -> 160.20901 | G39: =F39*D39 -> 801.04505
A40: 45631 | B40: WO-037579 | C40: 07-1200-1398H | D40: 1 | E40: =IF(TYPE(VLOOKUP(C40,'Sales_DC Price'!K:L,2,0))=16,0,VLOOKUP(C40,'Sales_DC Price'!K:L,2,0)*D40) -> 884 | F40: =IF(TYPE(VLOOKUP(C40,'Sales_DC Price'!Q:R,2,0))=16,0,VLOOKUP(C40,'Sales_DC Price'!Q:R,2,0)) -> 560.28428 | G40: =F40*D40 -> 560.28428
... A46: 45631 | B46: WO-039044 | C46: 07-2701-0414H | D46: 5 | E46: =IF(TYPE(VLOOKUP(C46,'Sales_DC Price'!K:L,2,0))=16,0,VLOOKUP(C46,'Sales_DC Price'!K:L,2,0)*D46) -> 2706.3 | F46: =IF(TYPE(VLOOKUP(C46,'Sales_DC Price'!Q:R,2,0))=16,0,VLOOKUP(C46,'Sales_DC Price'!Q:R,2,0)) -> 405.79775 | G46: =F46*D46 -> 2028.9887
A47: 45631 | B47: WO-039749 | C47: 07-2700-0450H | D47: 3 | E47: =1320*D47 -> 3960 | F47: =IF(TYPE(VLOOKUP(C47,'Sales_DC Price'!Q:R,2,0))=16,0,VLOOKUP(C47,'Sales_DC Price'!Q:R,2,0)) -> 776.8178 | G47: =F47*D47 -> 2330.4534
A48: 45632 | B48: WO-042013 | C48: 07-2701-0429H | D48: 2 | E48: =IF(TYPE(VLOOKUP(C48,'Sales_DC Price'!K:L,2,0))=16,0,VLOOKUP(C48,'Sales_DC Price'!K:L,2,0)*D48) -> 1928 | F48: =IF(TYPE(VLOOKUP(C48,'Sales_DC Price'!Q:R,2,0))=16,0,VLOOKUP(C48,'Sales_DC Price'!Q:R,2,0)) -> 730.47328 | G48: =F48*D48 -> 1460.9466
A49: 45632 | B49: WO-041260 | C49: 07-2701-0431H | D49: 1 | E49: =IF(TYPE(VLOOKUP(C49,'Sales_DC Price'!K:L,2,0))=16,0,VLOOKUP(C49,'Sales_DC Price'!K:L,2,0)*D49) -> 1030 | F49: =IF(TYPE(VLOOKUP(C49,'Sales_DC Price'!Q:R,2,0))=16,0,VLOOKUP(C49,'Sales_DC Price'!Q:R,2,0)) -> 735.14859 | G49: =F49*D49 -> 735.14859
A50: 45632 | B50: WO-038836 | C50: 07-2701-0328H | D50: 1 | E50: =IF(TYPE(VLOOKUP(C50,'Sales_DC Price'!K:L,2,0))=16,0,VLOOKUP(C50,'Sales_DC Price'!K:L,2,0)*D50) -> 1960 | F50: =IF(TYPE(VLOOKUP(C50,'Sales_DC Price'!Q:R,2,0))=16,0,VLOOKUP(C50,'Sales_DC Price'!Q:R,2,0)) -> 1617.8707 | G50: =F50*D50 -> 1617.8707
A51: 45632 | B51: WO-039044 | C51: 07-2701-0414H | D51: 5 | E51: =IF(TYPE(VLOOKUP(C51,'Sales_DC Price'!K:L,2,0))=16,0,VLOOKUP(C51,'Sales_DC Price'!K:L,2,0)*D51) -> 2706.3 | F51: =IF(TYPE(VLOOKUP(C51,'Sales_DC Price'!Q:R,2,0))=16,0,VLOOKUP(C51,'Sales_DC Price'!Q:R,2,0)) -> 405.79775 | G51: =F51*D51 -> 2028.9887
A52: 45632 | B52: WO-036805 | C52: 07-2700-0346H | D52: 5 | E52: =IF(TYPE(VLOOKUP(C52,'Sales_DC Price'!K:L,2,0))=16,0,VLOOKUP(C52,'Sales_DC Price'!K:L,2,0)*D52) -> 1735 | F52: =IF(TYPE(VLOOKUP(C52,'Sales_DC Price'!Q:R,2,0))=16,0,VLOOKUP(C52,'Sales_DC Price'!Q:R,2,0)) -> 308.29659 | G52: =F52*D52 -> 1541.4829
A53: 45632 | B53: WO-040648 | C53: 07-2701-0425H | D53: 2 | E53: =IF(TYPE(VLOOKUP(C53,'Sales_DC Price'!K:L,2,0))=16,0,VLOOKUP(C53,'Sales_DC Price'!K:L,2,0)*D53) -> 1551.9 | F53: =IF(TYPE(VLOOKUP(C53,'Sales_DC Price'!Q:R,2,0))=16,0,VLOOKUP(C53,'Sales_DC Price'!Q:R,2,0)) -> 647.7551 | G53: =F53*D53 -> 1295.5102
A54: 45632 | B54: WO-038963 | C54: 07-1200-1308H | D54: 3 | E54: =IF(TYPE(VLOOKUP(C54,'Sales_DC Price'!K:L,2,0))=16,0,VLOOKUP(C54,'Sales_DC Price'!K:L,2,0)*D54) -> 300 | F54: =IF(TYPE(VLOOKUP(C54,'Sales_DC Price'!Q:R,2,0))=16,0,VLOOKUP(C54,'Sales_DC Price'!Q:R,2,0)) -> 93.61659 | G54: =F54*D54 -> 280.84977
A55: 45632 | B55: WO-038964 | C55: 07-1200-1308H | D55: 3 | E55: =IF(TYPE(VLOOKUP(C55,'Sales_DC Price'!K:L,2,0))=16,0,VLOOKUP(C55,'Sales_DC Price'!K:L,2,0)*D55) -> 300 | F55: =IF(TYPE(VLOOKUP(C55,'Sales_DC Price'!Q:R,2,0))=16,0,VLOOKUP(C55,'Sales_DC Price'!Q:R,2,0)) -> 93.61659 | G55: =F55*D55 -> 280.84977
A56: 45632 | B56: WO-038965 | C56: 07-1200-1308H | D56: 3 | E56: =IF(TYPE(VLOOKUP(C56,'Sales_DC Price'!K:L,2,0))=16,0,VLOOKUP(C56,'Sales_DC Price'!K:L,2,0)*D56) -> 300 | F56: =IF(TYPE(VLOOKUP(C56,'Sales_DC Price'!Q:R,2,0))=16,0,VLOOKUP(C56,'Sales_DC Price'!Q:R,2,0)) -> 93.61659 | G56: =F56*D56 -> 280.84977
A57: 45632 | B57: WO-041763 | C57: 07-1200-1308H | D57: 3 | E57: =IF(TYPE(VLOOKUP(C57,'Sales_DC Price'!K:L,2,0))=16,0,VLOOKUP(C57,'Sales_DC Price'!K:L,2,0)*D57) -> 300 | F57: =IF(TYPE(VLOOKUP(C57,'Sales_DC Price'!Q:R,2,0))=16,0,VLOOKUP(C57,'Sales_DC Price'!Q:R,2,0)) -> 93.61659 | G57: =F57*D57 -> 280.84977
A58: 45632 | B58: WO-041496 | C58: 07-2701-0429H | D58: 1 | E58: =IF(TYPE(VLOOKUP(C58,'Sales_DC Price'!K:L,2,0))=16,0,VLOOKUP(C58,'Sales_DC Price'!K:L,2,0)*D58) -> 964 | F58: =IF(TYPE(VLOOKUP(C58,'Sales_DC Price'!Q:R,2,0))=16,0,VLOOKUP(C58,'Sales_DC Price'!Q:R,2,0)) -> 730.47328 | G58: =F58*D58 -> 730.47328
A59: 45635 | B59: WO-042184 | C59: 07-2701-0429H | D59: 1.6 | E59: =IF(TYPE(VLOOKUP(C59,'Sales_DC Price'!K:L,2,0))=16,0,VLOOKUP(C59,'Sales_DC Price'!K:L,2,0)*D59) -> 1542.4 | F59: =IF(TYPE(VLOOKUP(C59,'Sales_DC Price'!Q:R,2,0))=16,0,VLOOKUP(C59,'Sales_DC Price'!Q:R,2,0)) -> 730.47328 | G59: =F59*D59 -> 1168.7572
... A80: 45637 | B80: WO-042019 | C80: 07-1200-1368H | D80: 5 | E80: =IF(TYPE(VLOOKUP(C80,'Sales_DC Price'!K:L,2,0))=16,0,VLOOKUP(C80,'Sales_DC Price'!K:L,2,0)*D80) -> 1194.1 | F80: =IF(TYPE(VLOOKUP(C80,'Sales_DC Price'!Q:R,2,0))=16,0,VLOOKUP(C80,'Sales_DC Price'!Q:R,2,0)) -> 224.99589 | G80: =F80*D80 -> 1124.9795
A81: 45637 | B81: WO-042342 | E81: =IF(TYPE(VLOOKUP(C81,'Sales_DC Price'!K:L,2,0))=16,0,VLOOKUP(C81,'Sales_DC Price'!K:L,2,0)*D81) -> 0 | F81: =IF(TYPE(VLOOKUP(C81,'Sales_DC Price'!Q:R,2,0))=16,0,VLOOKUP(C81,'Sales_DC Price'!Q:R,2,0)) -> 0 | G81: =F81*D81 -> 0 | H81: 07-2701-0430H | I81: 0.001
A82: 45637 | B82: WO-039133 | C82: 07-9000-0462H | D82: 6 | E82: 1086 | F82: 81.37 | G82: 488.22
A83: 45637 | B83: WO-039134 | C83: 07-9000-0461H | D83: 5 | E83: 810 | F83: 58.41284 | G83: 292.0642
A84: 45637 | B84: WO-040262 | C84: 07-1200-0953H | D84: 1 | E84: 205.776 | F84: 82.34 | G84: 82.34
A85: 45637 | B85: WO-040127 | C85: 07-1201-1200H | D85: 10 | E85: 1730 | F85: 151.58225 | G85: 1515.8225
A86: 45637 | B86: WO-035686 | C86: 07-2700-0357H | D86: 5 | E86: 2515 | F86: 432.73672 | G86: 2163.6836
A87: 45637 | B87: WO-041596 | C87: 07-1200-1189H | D87: 5 | E87: 950 | F87: 132.49188 | G87: 662.4594
A88: 45638 | B88: WO-042431 | E88: 0 | F88: 0 | G88: 0 | H88: 07-2701-0430H | I88: 0.001
A89: 45638 | B89: WO-041747 | C89: 07-1200-1233H | D89: 1 | E89: 361.2 | F89: 283.47798 | G89: 283.47798
A90: 45638 | B90: WO-039554 | C90: 07-1200-1100H | D90: 2 | E90: 420.6 | F90: 158.36579 | G90: 316.73158
A91: 45638 | B91: WO-041746 | C91: 07-1200-1184H | D91: 1 | E91: 994 | F91: 848.53837 | G91: 848.53837
A92: 45638 | B92: WO-041746 | C92: 07-1200-1184H | D92: 2 | E92: 1988 | F92: 848.53837 | G92: 1697.0767
A93: 45638 | B93: WO-034980 | C93: 07-1200-1379H | D93: 5 | E93: 1262.5 | F93: 148.41275 | G93: 742.06375
A94: 45638 | B94: WO-041747 | C94: 07-1200-1233H | D94: 1 | E94: 361.2 | F94: 283.47798 | G94: 283.47798
A95: 45638 | B95: WO-041203 | C95: 07-1200-1308H | D95: 3 | E95: 300 | F95: 93.61659 | G95: 280.84977
A96: 45638 | B96: WO-041202 | C96: 07-1200-1308H | D96: 3 | E96: 300 | F96: 93.61659 | G96: 280.84977
A97: 45638 | B97: WO-041201 | C97: 07-1200-1308H | D97: 3 | E97: 300 | F97: 93.61659 | G97: 280.84977
A98: 45638 | B98: WO-041200 | C98: 07-1200-1308H | D98: 3 | E98: 300 | F98: 93.61659 | G98: 280.84977
A99: 45638 | B99: WO-041199 | C99: 07-1200-1308H | D99: 3 | E99: 300 | F99: 93.61659 | G99: 280.84977
A100: 45638 | B100: WO-041752 | C100: 07-1200-1413H | D100: 3 | E100: 702 | F100: 147.47997 | G100: 442.43991
... A104: 45638 | B104: WO-039145 | C104: 07-1200-1337H | D104: 3 | E104: 1350 | F104: 275.85792 | G104: 827.57376
A105: 45638 | B105: WO-042409 | E105: 0 | F105: 0 | G105: 0 | H105: 07-2701-0429H | I105: 0.001
A106: 45639 | B106: WO-042799 | E106: =IF(TYPE(VLOOKUP(C106,'Sales_DC Price'!K:L,2,0))=16,0,VLOOKUP(C106,'Sales_DC Price'!K:L,2,0)*D106) -> 0 | F106: =IF(TYPE(VLOOKUP(C106,'Sales_DC Price'!Q:R,2,0))=16,0,VLOOKUP(C106,'Sales_DC Price'!Q:R,2,0)) -> 0 | G106: =F106*D106 -> 0 | H106: 07-2701-0429H | I106: 0.001
A107: 45639 | B107: WO-042624 | E107: =IF(TYPE(VLOOKUP(C107,'Sales_DC Price'!K:L,2,0))=16,0,VLOOKUP(C107,'Sales_DC Price'!K:L,2,0)*D107) -> 0 | F107: =IF(TYPE(VLOOKUP(C107,'Sales_DC Price'!Q:R,2,0))=16,0,VLOOKUP(C107,'Sales_DC Price'!Q:R,2,0)) -> 0 | G107: =F107*D107 -> 0 | H107: 07-2701-0430H | I107: 0.001
A108: 45639 | B108: WO-042096 | C108: 07-1201-1222H | D108: 2 | E108: =276.2*D108 -> 552.4 | F108: =IF(TYPE(VLOOKUP(C108,'Sales_DC Price'!Q:R,2,0))=16,0,VLOOKUP(C108,'Sales_DC Price'!Q:R,2,0)) -> 225.23381 | G108: =F108*D108 -> 450.46762
A109: 45639 | B109: WO-040423 | C109: 07-2000-0419H | D109: 5 | E109: =IF(TYPE(VLOOKUP(C109,'Sales_DC Price'!K:L,2,0))=16,0,VLOOKUP(C109,'Sales_DC Price'!K:L,2,0)*D109) -> 1875 | F109: =IF(TYPE(VLOOKUP(C109,'Sales_DC Price'!Q:R,2,0))=16,0,VLOOKUP(C109,'Sales_DC Price'!Q:R,2,0)) -> 145.88199 | G109: =F109*D109 -> 729.40995
A110: 45639 | B110: WO-040126 | C110: 07-2000-0419H | D110: 5 | E110: =IF(TYPE(VLOOKUP(C110,'Sales_DC Price'!K:L,2,0))=16,0,VLOOKUP(C110,'Sales_DC Price'!K:L,2,0)*D110) -> 1875 | F110: =IF(TYPE(VLOOKUP(C110,'Sales_DC Price'!Q:R,2,0))=16,0,VLOOKUP(C110,'Sales_DC Price'!Q:R,2,0)) -> 145.88199 | G110: =F110*D110 -> 729.40995
A111: 45639 | B111: WO-041596 | C111: 07-1200-1189H | D111: 5 | E111: =IF(TYPE(VLOOKUP(C111,'Sales_DC Price'!K:L,2,0))=16,0,VLOOKUP(C111,'Sales_DC Price'!K:L,2,0)*D111) -> 950 | F111: =IF(TYPE(VLOOKUP(C111,'Sales_DC Price'!Q:R,2,0))=16,0,VLOOKUP(C111,'Sales_DC Price'!Q:R,2,0)) -> 132.49188 | G111: =F111*D111 -> 662.4594
A112: 45639 | B112: WO-042441 | E112: =IF(TYPE(VLOOKUP(C112,'Sales_DC Price'!K:L,2,0))=16,0,VLOOKUP(C112,'Sales_DC Price'!K:L,2,0)*D112) -> 0 | F112: =IF(TYPE(VLOOKUP(C112,'Sales_DC Price'!Q:R,2,0))=16,0,VLOOKUP(C112,'Sales_DC Price'!Q:R,2,0)) -> 0 | G112: =F112*D112 -> 0 | H112: 07-2701-0429H | I112: 0.001
A113: 45639 | B113: WO-15862 | C113: 07-2700-0427H | D113: 1.5 | E113: =IF(TYPE(VLOOKUP(C113,'Sales_DC Price'!K:L,2,0))=16,0,VLOOKUP(C113,'Sales_DC Price'!K:L,2,0)*D113) -> 3825 | F113: =IF(TYPE(VLOOKUP(C113,'Sales_DC Price'!Q:R,2,0))=16,0,VLOOKUP(C113,'Sales_DC Price'!Q:R,2,0)) -> 1248.1361 | G113: =F113*D113 -> 1872.2042
A114: 45639 | B114: WO-042142 | C114: 07-2701-0414H | D114: 5 | E114: =IF(TYPE(VLOOKUP(C114,'Sales_DC Price'!K:L,2,0))=16,0,VLOOKUP(C114,'Sales_DC Price'!K:L,2,0)*D114) -> 2706.3 | F114: =IF(TYPE(VLOOKUP(C114,'Sales_DC Price'!Q:R,2,0))=16,0,VLOOKUP(C114,'Sales_DC Price'!Q:R,2,0)) -> 405.79775 | G114: =F114*D114 -> 2028.9887
A115: 45639 | B115: WO-039044 | C115: 07-2701-0414H | D115: 5 | E115: =IF(TYPE(VLOOKUP(C115,'Sales_DC Price'!K:L,2,0))=16,0,VLOOKUP(C115,'Sales_DC Price'!K:L,2,0)*D115) -> 2706.3 | F115: =IF(TYPE(VLOOKUP(C115,'Sales_DC Price'!Q:R,2,0))=16,0,VLOOKUP(C115,'Sales_DC Price'!Q:R,2,0)) -> 405.79775 | G115: =F115*D115 -> 2028.9887
A116: 45642 | B116: WO-042898 | E116: =IF(TYPE(VLOOKUP(C116,'Sales_DC Price'!K:L,2,0))=16,0,VLOOKUP(C116,'Sales_DC Price'!K:L,2,0)*D116) -> 0 | F116: =IF(TYPE(VLOOKUP(C116,'Sales_DC Price'!Q:R,2,0))=16,0,VLOOKUP(C116,'Sales_DC Price'!Q:R,2,0)) -> 0 | G116: =F116*D116 -> 0 | H116: 07-2701-0429H | I116: 0.001
A117: 45642 | B117: WO-038105 | C117: 07-2701-0390H | D117: 8 | E117: 3066 | F117: =IF(TYPE(VLOOKUP(C117,'Sales_DC Price'!Q:R,2,0))=16,0,VLOOKUP(C117,'Sales_DC Price'!Q:R,2,0)) -> 276.29284 | G117: =F117*D117 -> 2210.3427
A118: 45642 | B118: WO-039234 | C118: 07-1200-1394H | D118: 3 | E118: =IF(TYPE(VLOOKUP(C118,'Sales_DC Price'!K:L,2,0))=16,0,VLOOKUP(C118,'Sales_DC Price'!K:L,2,0)*D118) -> 540 | F118: =IF(TYPE(VLOOKUP(C118,'Sales_DC Price'!Q:R,2,0))=16,0,VLOOKUP(C118,'Sales_DC Price'!Q:R,2,0)) -> 150.26659 | G118: =F118*D118 -> 450.79977
A119: 45642 | B119: WO-040822 | C119: 07-1200-1362H | D119: 3 | E119: =350*D119 -> 1050 | F119: =IF(TYPE(VLOOKUP(C119,'Sales_DC Price'!Q:R,2,0))=16,0,VLOOKUP(C119,'Sales_DC Price'!Q:R,2,0)) -> 401.18718 | G119: =F119*D119 -> 1203.5615
A120: 45642 | B120: WO-040648 | C120: 07-2701-0425H | D120: 6 | E120: =IF(TYPE(VLOOKUP(C120,'Sales_DC Price'!K:L,2,0))=16,0,VLOOKUP(C120,'Sales_DC Price'!K:L,2,0)*D120) -> 4655.7 | F120: =IF(TYPE(VLOOKUP(C120,'Sales_DC Price'!Q:R,2,0))=16,0,VLOOKUP(C120,'Sales_DC Price'!Q:R,2,0)) -> 647.7551 | G120: =F120*D120 -> 3886.5306
A121: 45642 | B121: WO-040237 | C121: 07-2700-0367H | D121: 4.5 | E121: =IF(TYPE(VLOOKUP(C121,'Sales_DC Price'!K:L,2,0))=16,0,VLOOKUP(C121,'Sales_DC Price'!K:L,2,0)*D121) -> 2653.2 | F121: =IF(TYPE(VLOOKUP(C121,'Sales_DC Price'!Q:R,2,0))=16,0,VLOOKUP(C121,'Sales_DC Price'!Q:R,2,0)) -> 470.61682 | G121: =F121*D121 -> 2117.7757
A122: 45642 | B122: WO-040920 | C122: 07-2700-0422H | D122: 2 | E122: =IF(TYPE(VLOOKUP(C122,'Sales_DC Price'!K:L,2,0))=16,0,VLOOKUP(C122,'Sales_DC Price'!K:L,2,0)*D122) -> 2592.6 | F122: =IF(TYPE(VLOOKUP(C122,'Sales_DC Price'!Q:R,2,0))=16,0,VLOOKUP(C122,'Sales_DC Price'!Q:R,2,0)) -> 1219.8347 | G122: =F122*D122 -> 2439.6694
A123: 45642 | B123: WO-039183 | C123: 07-1201-1217H | D123: 0.125 | E123: =IF(TYPE(VLOOKUP(C123,'Sales_DC Price'!K:L,2,0))=16,0,VLOOKUP(C123,'Sales_DC Price'!K:L,2,0)*D123) -> 62.5 | F123: =IF(TYPE(VLOOKUP(C123,'Sales_DC Price'!Q:R,2,0))=16,0,VLOOKUP(C123,'Sales_DC Price'!Q:R,2,0)) -> 497.89281 | G123: =F123*D123 -> 62.236601
A124: 45642 | B124: WO-041124 | C124: 07-2000-0419H | D124: 5 | E124: =IF(TYPE(VLOOKUP(C124,'Sales_DC Price'!K:L,2,0))=16,0,VLOOKUP(C124,'Sales_DC Price'!K:L,2,0)*D124) -> 1875 | F124: =IF(TYPE(VLOOKUP(C124,'Sales_DC Price'!Q:R,2,0))=16,0,VLOOKUP(C124,'Sales_DC Price'!Q:R,2,0)) -> 145.88199 | G124: =F124*D124 -> 729.40995
A125: 45642 | B125: WO-042142 | C125: 07-2701-0414H | D125: 5 | E125: =IF(TYPE(VLOOKUP(C125,'Sales_DC Price'!K:L,2,0))=16,0,VLOOKUP(C125,'Sales_DC Price'!K:L,2,0)*D125) -> 2706.3 | F125: =IF(TYPE(VLOOKUP(C125,'Sales_DC Price'!Q:R,2,0))=16,0,VLOOKUP(C125,'Sales_DC Price'!Q:R,2,0)) -> 405.79775 | G125: =F125*D125 -> 2028.9887
A126: 45642 | B126: WO-041020 | C126: 07-1200-1398H | D126: 3 | E126: =IF(TYPE(VLOOKUP(C126,'Sales_DC Price'!K:L,2,0))=16,0,VLOOKUP(C126,'Sales_DC Price'!K:L,2,0)*D126) -> 2652 | F126: =IF(TYPE(VLOOKUP(C126,'Sales_DC Price'!Q:R,2,0))=16,0,VLOOKUP(C126,'Sales_DC Price'!Q:R,2,0)) -> 560.28428 | G126: =F126*D126 -> 1680.8528
A127: 45642 | B127: WO-039145 | C127: 07-1200-1337H | D127: 3 | E127: =IF(TYPE(VLOOKUP(C127,'Sales_DC Price'!K:L,2,0))=16,0,VLOOKUP(C127,'Sales_DC Price'!K:L,2,0)*D127) -> 1350 | F127: =IF(TYPE(VLOOKUP(C127,'Sales_DC Price'!Q:R,2,0))=16,0,VLOOKUP(C127,'Sales_DC Price'!Q:R,2,0)) -> 275.85792 | G127: =F127*D127 -> 827.57376
A128: 45643 | B128: WO-041576 | C128: 07-2000-0002H | D128: 0.15 | E128: =IF(TYPE(VLOOKUP(C128,'Sales_DC Price'!K:L,2,0))=16,0,VLOOKUP(C128,'Sales_DC Price'!K:L,2,0)*D128) -> 0 | F128: =IF(TYPE(VLOOKUP(C128,'Sales_DC Price'!Q:R,2,0))=16,0,VLOOKUP(C128,'Sales_DC Price'!Q:R,2,0)) -> 0 | G128: =F128*D128 -> 0
A129: 45643 | B129: WO-041577 | C129: 07-2000-0002H | D129: 0.2 | E129: =IF(TYPE(VLOOKUP(C129,'Sales_DC Price'!K:L,2,0))=16,0,VLOOKUP(C129,'Sales_DC Price'!K:L,2,0)*D129) -> 0 | F129: =IF(TYPE(VLOOKUP(C129,'Sales_DC Price'!Q:R,2,0))=16,0,VLOOKUP(C129,'Sales_DC Price'!Q:R,2,0)) -> 0 | G129: =F129*D129 -> 0
A130: 45643 | B130: WO-042966 | E130: =IF(TYPE(VLOOKUP(C130,'Sales_DC Price'!K:L,2,0))=16,0,VLOOKUP(C130,'Sales_DC Price'!K:L,2,0)*D130) -> 0 | F130: =IF(TYPE(VLOOKUP(C130,'Sales_DC Price'!Q:R,2,0))=16,0,VLOOKUP(C130,'Sales_DC Price'!Q:R,2,0)) -> 0 | G130: =F130*D130 -> 0 | H130: 07-2701-0429H | I130: 0.001
A131: 45643 | B131: WO-042098 | C131: 07-1201-1221H | D131: 2 | E131: =IF(TYPE(VLOOKUP(C131,'Sales_DC Price'!K:L,2,0))=16,0,VLOOKUP(C131,'Sales_DC Price'!K:L,2,0)*D131) -> 720 | F131: =IF(TYPE(VLOOKUP(C131,'Sales_DC Price'!Q:R,2,0))=16,0,VLOOKUP(C131,'Sales_DC Price'!Q:R,2,0)) -> 326.49362 | G131: =F131*D131 -> 652.98724
A132: 45643 | B132: WO-042965 | E132: =IF(TYPE(VLOOKUP(C132,'Sales_DC Price'!K:L,2,0))=16,0,VLOOKUP(C132,'Sales_DC Price'!K:L,2,0)*D132) -> 0 | F132: =IF(TYPE(VLOOKUP(C132,'Sales_DC Price'!Q:R,2,0))=16,0,VLOOKUP(C132,'Sales_DC Price'!Q:R,2,0)) -> 0 | G132: =F132*D132 -> 0 | H132: 07-2701-0430H | I132: 0.001
A133: 45643 | B133: WO-042292 | C133: 07-2701-0430H | D133: 3 | E133: =IF(TYPE(VLOOKUP(C133,'Sales_DC Price'!K:L,2,0))=16,0,VLOOKUP(C133,'Sales_DC Price'!K:L,2,0)*D133) -> 3750 | F133: =IF(TYPE(VLOOKUP(C133,'Sales_DC Price'!Q:R,2,0))=16,0,VLOOKUP(C133,'Sales_DC Price'!Q:R,2,0)) -> 966.53414 | G133: =F133*D133 -> 2899.6024
A134: 45643 | B134: WO-038836 | C134: 07-2701-0328H | D134: 1 | E134: =IF(TYPE(VLOOKUP(C134,'Sales_DC Price'!K:L,2,0))=16,0,VLOOKUP(C134,'Sales_DC Price'!K:L,2,0)*D134) -> 1960 | F134: =IF(TYPE(VLOOKUP(C134,'Sales_DC Price'!Q:R,2,0))=16,0,VLOOKUP(C134,'Sales_DC Price'!Q:R,2,0)) -> 1617.8707 | G134: =F134*D134 -> 1617.8707
A135: 45643 | B135: WO-042189 | C135: 07-2701-0429H | D135: 3 | E135: =IF(TYPE(VLOOKUP(C135,'Sales_DC Price'!K:L,2,0))=16,0,VLOOKUP(C135,'Sales_DC Price'!K:L,2,0)*D135) -> 2892 | F135: =IF(TYPE(VLOOKUP(C135,'Sales_DC Price'!Q:R,2,0))=16,0,VLOOKUP(C135,'Sales_DC Price'!Q:R,2,0)) -> 730.47328 | G135: =F135*D135 -> 2191.4198
A136: 45643 | B136: WO-042291 | C136: 07-2701-0430H | D136: 3 | E136: =IF(TYPE(VLOOKUP(C136,'Sales_DC Price'!K:L,2,0))=16,0,VLOOKUP(C136,'Sales_DC Price'!K:L,2,0)*D136) -> 3750 | F136: =IF(TYPE(VLOOKUP(C136,'Sales_DC Price'!Q:R,2,0))=16,0,VLOOKUP(C136,'Sales_DC Price'!Q:R,2,0)) -> 966.53414 | G136: =F136*D136 -> 2899.6024
A137: 45643 | B137: WO-041561 | C137: 07-1200-1297H | D137: 6 | E137: =IF(TYPE(VLOOKUP(C137,'Sales_DC Price'!K:L,2,0))=16,0,VLOOKUP(C137,'Sales_DC Price'!K:L,2,0)*D137) -> 1380 | F137: =IF(TYPE(VLOOKUP(C137,'Sales_DC Price'!Q:R,2,0))=16,0,VLOOKUP(C137,'Sales_DC Price'!Q:R,2,0)) -> 190.03058 | G137: =F137*D137 -> 1140.1835
...

Sheet Postpones
A1: Postpone | E1: TTL Value | G1: =SUM(G4:G308) -> 0 | I1: =O1-G1 -> 43305.3 | K1: Pull-in | M1: TTL Value | O1: =SUM(S:S) -> 43305.3
E2: TTL Qty | G2: =SUM(F:F) -> 0 | M2: TTL Qty | O2: =SUM(O4:O831) -> 55000
A3: Date | B3: Customer | C3: ItemCode | D3: ToYear | E3: ToMonth | F3: Postp. Quantity | G3: Összeg / Rest Value | J3: Date | K3: Customer | L3: ItemCode | M3: Line | N3: Quantity | O3: OpenQty | P3: New Request | Q3: Old Reqest | R3: ETA | S3: Rest Value | T3: Delta | U3: Postpone | V3: FromYear | W3: ToYear | X3: FromMonth | Y3: ToMonth
